Workbook
Name a: [3]Terminal!$F$1:$F$3
Name countif: #REF!
Name countif: #REF!
Name countif: #REF!
Name countif: #REF!
Name countif: #REF!
Name D: #REF!
Name D: #REF!
Name D: #REF!
Name D: #REF!
Name D: #REF!
Name E: #REF!
Name E: #REF!
Name E: #REF!
Name Erstelldatum: #REF!
Name Erstelldatum: #REF!
Name Erstelldatum: #REF!
Name Erstelldatum: #REF!
Name Erstelldatum: #REF!
Name EXCEL_EXPORT1: #REF!
Name EXCEL_EXPORT1: #REF!
Name EXCEL_EXPORT1: #REF!
Name FZG_Beschriftung: #REF!
Name FZG_Beschriftung: #REF!
Name FZG_Beschriftung: #REF!
Name PA_Beschriftung: #REF!
Name PA_Beschriftung: #REF!
Name PA_Beschriftung: #REF!
Name Planungsstand: #REF!
Name Planungsstand: #REF!
Name Planungsstand: #REF!
Name Vergleichsplanung: #REF!
Name Vergleichsplanung: #REF!
Name Vergleichsplanung: #REF!
Name x: #REF!
Name x: #REF!
Name x: #REF!
Name Z: #REF!
Name Z: #REF!
Name Z: #REF!
Name 公用设备大类: OFFSET([4]资源数据源!$S$1,1,0,COUNTA([4]资源数据源!$S:$S)-COUNTIF([4]资源数据源!$S:$S,0)-1,1)
Name 公用设备大类: OFFSET([5]资源数据源!$S$1,1,0,COUNTA([5]资源数据源!$S:$S)-COUNTIF([5]资源数据源!$S:$S,0)-1,1)
Name 公用设备大类: OFFSET([5]资源数据源!$S$1,1,0,COUNTA([5]资源数据源!$S:$S)-COUNTIF([5]资源数据源!$S:$S,0)-1,1)
Name 公用设备大类: OFFSET([6]资源数据源!$Q$1,1,0,COUNTA([6]资源数据源!$Q:$Q)-COUNTIF([6]资源数据源!$Q:$Q,0)-1,1)
Name 公用设备大类: OFFSET([5]资源数据源!$S$1,1,0,COUNTA([5]资源数据源!$S:$S)-COUNTIF([5]资源数据源!$S:$S,0)-1,1)
Name 公用设备大类: OFFSET([4]资源数据源!$S$1,1,0,COUNTA([4]资源数据源!$S:$S)-COUNTIF([4]资源数据源!$S:$S,0)-1,1)
Name 公用设备大类: OFFSET([7]资源数据源!$S$1,1,0,COUNTA([7]资源数据源!$S:$S)-COUNTIF([7]资源数据源!$S:$S,0)-1,1)
Name 公用设备名称: OFFSET([4]资源数据源!$G$1,MATCH('[4]项目评估汇总-样表'!$C1,[4]资源数据源!$F:$F,0)-1,0,COUNTIF([4]资源数据源!$F:$F,'[4]项目评估汇总-样表'!$C1),1)
Name 公用设备名称: OFFSET([5]资源数据源!$G$1,MATCH(设备投资明细!#REF!,[5]资源数据源!$F:$F,0)-1,0,COUNTIF([5]资源数据源!$F:$F,设备投资明细!#REF!),1)
Name 公用设备名称: OFFSET([5]资源数据源!$G$1,MATCH([5]项目设备投入!$C1,[5]资源数据源!$F:$F,0)-1,0,COUNTIF([5]资源数据源!$F:$F,[5]项目设备投入!$C1),1)
Name 公用设备名称: OFFSET([6]资源数据源!$G$1,MATCH('[8]项目设备投入 '!$C1,[6]资源数据源!$F:$F,0)-1,0,COUNTIF([6]资源数据源!$F:$F,'[8]项目设备投入 '!$C1),1)
Name 公用设备名称: OFFSET([5]资源数据源!$G$1,MATCH([5]项目设备投入!$C1,[5]资源数据源!$F:$F,0)-1,0,COUNTIF([5]资源数据源!$F:$F,[5]项目设备投入!$C1),1)
Name 公用设备名称: OFFSET([4]资源数据源!$G$1,MATCH('[4]项目评估汇总-样表'!$C1,[4]资源数据源!$F:$F,0)-1,0,COUNTIF([4]资源数据源!$F:$F,'[4]项目评估汇总-样表'!$C1),1)
Name 公用设备名称: OFFSET([7]资源数据源!$G$1,MATCH('[7]项目评估汇总-样表'!$C1,[7]资源数据源!$F:$F,0)-1,0,COUNTIF([7]资源数据源!$F:$F,'[7]项目评估汇总-样表'!$C1),1)
Name 项目评估: #REF!
Name 项目评估: #REF!
Name 项目评估: #REF!
Name 专用工装设备大类: OFFSET([4]资源数据源!$W$1,1,0,COUNTA([4]资源数据源!$W:$W)-COUNTIF([4]资源数据源!$W:$W,0)-1,1)
Name 专用工装设备大类: OFFSET([5]资源数据源!$W$1,1,0,COUNTA([5]资源数据源!$W:$W)-COUNTIF([5]资源数据源!$W:$W,0)-1,1)
Name 专用工装设备大类: OFFSET([5]资源数据源!$W$1,1,0,COUNTA([5]资源数据源!$W:$W)-COUNTIF([5]资源数据源!$W:$W,0)-1,1)

Sheet 项目汇总
B2: #REF!
B4: 区分 | C4: 客户目标价格（工厂实际） | E4: 第一轮报价 | G4: 备注
C6: 金额 | D6: 收入比 | E6: 金额 | F6: 收入比
B7: 目标销售数量（PCS） | C7: 450000 | E7: =C7 -> 450000
B8: 核算分摊数量 | C8: 450000
B9: 回路工时(s) | C9: =C29*3600/C10 -> #REF! | E9: =E29*3600/E10 -> #REF!
B10: 回路数 | C10: 2305 | E10: =C10 -> 2305
B11: 回路销售单价 | C11: =C14/C10 -> 2.9501085 | E11: =E14/E10 -> 2.9501085
B12: 运营成本工时费（不包含折旧） | C12: 52.275345 | E12: 52.275345
B13: 运营成本直接人工费率 | C13: =C33/C29 -> #REF! | E13: =E33/E29 -> #REF!
B14: 目标销售单价（元） | C14: 6800 | E14: =C14 -> 6800
B15: 目标销售收入（元） | C15: 2475000000
B16: 目标利润额（元）
B17: 目标实现利润点（%） | C17: -0.004040404
B18: 返点金额（QS）（元） | C18: 10000000 | E18: 10000000
B19: 毛利（元） | C19: =(C14-C26)*C7 -> #REF! | E19: =(E14-E26)*E7 -> #REF!
B20: 毛利（%） | C20: =(C14-C27-C33-C34-C47-C50-(C18/C7))/C14 -> #REF! | E20: =(E14-E27-E33-E34-E47-E50-(E18/E7))/E14 -> #REF!
B21: 项目新增投资（元）
B22: -设备、模具、工装板类 | C22: #REF!
B23: -辅助工具类 | C23: #REF!
B24: 本阶段已投资（元） | C24: 0
B25: 剩余投资金额（元） | C25: #REF!
B26: 单套项目总成本（元/PCS） | C26: =C27+C33+C34+C45+C47+C50 -> #REF! | E26: =E27+E33+E34+E45+E47+E50 -> #REF!
B27: 单套材料成本（元/PCS） | C27: #REF! | D27: =C27/$C$14 -> #REF! | E27: =F27*E14 -> 4624 | F27: 0.68
B28: 回路材料成本 | C28: 1.7353579 | E28: =E27/E10 -> 2.0060738
B29: 总工时（H) | C29: =C30+C31 -> #REF! | E29: =E30+E31 -> #REF!
B30: —前工程工时（H) | C30: #REF! | E30: =C30 -> #REF!
B31: —后工程工时（H) | C31: #REF! | E31: =C31 -> #REF!
B32: 回路制造费用
B33: 单套直接人工（元/PCS） | C33: #REF! | D33: =C33/$C$14 -> #REF! | E33: =C33 -> #REF!
B34: 单套制造费用（元/PCS） | C34: =SUM(C35:C40) -> #REF! | D34: =C34/$C$14 -> #REF!
B35: —间接人工 | C35: #REF! | D35: =C35/$C$14 -> #REF!
B36: —低值易耗品费 | C36: 4.7988473 | D36: =C36/$C$14 -> 0.00070571284
B37: —机物料消耗 | C37: 122.05998 | D37: =C37/$C$14 -> 0.017949997
B38: —厂房分摊 | C38: 51.756883 | D38: =C38/$C$14 -> 0.0076113063
B39: —自动化仓、仓库分摊 | C39: 35.367203 | D39: =C39/$C$14 -> 0.0052010593
B40: —其他制费 | C40: 26.094095 | D40: =C40/$C$14 -> 0.0038373669
C41: 318.79962 | D41: =C41/$C$14 -> 0.046882297
B42: 单套期间费用成本（元/PCS） | C42: 14.613367 | D42: =C42/$C$14 -> 0.0021490245
B43: 销售费用（元/PCS） | C43: 294.7029 | D43: =C43/$C$14 -> 0.043338662
B44: 管理费用（元/PCS） | C44: 9.378915 | D44: =C44/$C$14 -> 0.0013792522
B45: 研发费用（元/PCS） | C45: 0.10443883 | D45: =C45/$C$14 -> 1.5358652e-05
B46: 财务费用（元/PCS） | C46: 53.863337 | D46: 0.0065874332
B47: 单套设备成本（元/PCS） | C47: =C48+C49 -> 0
B48: —共用设备（元/PCS)
B49: —专用设备（元/PCS)
B50: 单套包装、物流费用（元/PCS）

Sheet 项目评估汇总（昆山90%）
A1: 吉利P162大电池包高压 | F1: 2026 | G1: 2027 | H1: 2028 | I1: 2029 | J1: 2030 | K1: 2031 | L1: 2032 | M1: 2033
A2: 内 容 | E2: 产 品 周 期 汇 总 | N2: 备 注 | P2: 1 | Q2: 2
C3: 费率 | E3: 目标汇总值 | F3: ="第一年"&F1&"年" -> 第一年2026年 | G3: ="第二年"&G1&"年" -> 第二年2027年 | H3: ="第三年"&H1&"年" -> 第三年2028年 | I3: ="第四年"&I1&"年" -> 第四年2029年 | J3: ="第五年"&J1&"年" -> 第五年2030年 | K3: ="第六年"&K1&"年" -> 第六年2031年 | L3: ="第七年"&L1&"年" -> 第七年2032年 | M3: ="第八年"&M1&"年" -> 第八年2033年 | P3: {=TRANSPOSE(配置明细!$B$3:$B$4)} -> 6608523073 | Q3: 6608523072
A4: 回路数（PCS） | F4: =配置明细!P14 -> 27 | G4: =F4 -> 27 | H4: =G4 -> 27 | I4: =H4 -> 27 | J4: =I4 -> 27 | P4: =VLOOKUP(P3,配置明细!$B:$P,15,0) -> 25 | Q4: =VLOOKUP(Q3,配置明细!$B:$P,15,0) -> 2
A5: 目标销售数量（PCS） | E5: =SUM(F5:K5) -> 201000 | F5: 48000 | G5: 48000 | H5: 42000 | I5: 39000 | J5: 24000 | P5: =P37 -> 201000 | Q5: =Q37 -> 201000
A6: 目标销售单价（元） | F6: {=SUMPRODUCT(P6:Q6,P35:Q35)} -> 585.59777 | G6: =F6 -> 585.59777 | H6: =G6 -> 585.59777 | I6: =H6 -> 585.59777 | J6: =I6 -> 585.59777 | N6: 平均售价 | P6: =(P15+P16+P20+P23+P31+P32)/85% -> 442.67059 | Q6: =(Q15+Q16+Q20+Q23+Q31+Q32)/85% -> 142.92718
A7: 回路单价 （元） | F7: =F6/F4 -> 21.688806 | G7: =G6/G4 -> 21.688806 | H7: =H6/H4 -> 21.688806 | I7: =I6/I4 -> 21.688806 | J7: =I7 -> 21.688806 | N7: =(E9-E13)/E5 -> 585.59777 | P7: =P6/P4 -> 17.706824 | Q7: =Q6/Q4 -> 71.46359
A8: 回路工时 （秒） | F8: =(配置明细!L14+配置明细!M14+配置明细!N14)*3600/F4 -> 213.06667 | G8: =F8 -> 213.06667 | H8: =G8 -> 213.06667 | I8: =H8 -> 213.06667 | J8: =I8 -> 213.06667
A9: 目标销售收入（元） | E9: =SUM(F9:M9) -> 1.1770515e+08 | F9: =F6*F5 -> 28108693 | G9: =G6*G5 -> 28108693 | H9: =H6*H5 -> 24595106 | I9: =I6*I5 -> 22838313 | J9: =J6*J5 -> 14054346 | N9: =E9/E5 -> 585.59777 | P9: =P6*P5 -> 88976788 | Q9: =Q6*Q5 -> 28728363
A10: 目标利润额（元） | E10: =E9-E14 -> 17655773 | F10: =(F6-F14)*F5 -> 4216303.9 | G10: =(G6-G14)*G5 -> 4216303.9 | H10: =(H6-H14)*H5 -> 3689265.9 | I10: =(I6-I14)*I5 -> 3425746.9 | J10: =(J6-J14)*J5 -> 2108152 | P10: =(P6-P14)*P5 -> 13346518 | Q10: =(Q6-Q14)*Q5 -> 4309254.5
A11: 毛利（%） | E11: =(E9-E15-E16-E20-E23-E13-E31-E32)/E9 -> 0.15 | F11: =((F6-F15-F16-F20-F23)-(F13/F5)-F31-F32)/F6 -> 0.15 | G11: =((G6-G15-G16-G20-G23)-(G13/G5)-G31-G32)/G6 -> 0.15 | H11: =((H6-H15-H16-H20-H23)-(H13/H5)-H31-H32)/H6 -> 0.15 | I11: =((I6-I15-I16-I20-I23)-(I13/I5)-I31-I32)/I6 -> 0.15 | J11: =((J6-J15-J16-J20-J23)-(J13/J5)-J31-J32)/J6 -> 0.15 | P11: =((P6-P15-P16-P20-P23)-(P13/P5)-P31-P32)/P6 -> 0.15 | Q11: =((Q6-Q15-Q16-Q20-Q23)-(Q13/Q5)-Q31-Q32)/Q6 -> 0.15
A12: 毛利（元） | E12: =E11*E9 -> 17655773 | F12: =F11*F9 -> 4216303.9 | G12: =G11*G9 -> 4216303.9 | H12: =H11*H9 -> 3689265.9 | I12: =I11*I9 -> 3425746.9 | J12: =J11*J9 -> 2108152 | P12: =P11*P9 -> 13346518 | Q12: =Q11*Q9 -> 4309254.5
A13: 返点金额（QS）（元） | E13: =SUM(F13:J13) -> 0
A14: 单套项目总成本（元/PCS） | E14: =F14*$F$5+G14*$G$5+H14*$H$5+$I$5*I14+J14*$J$5+K14*$K$5+L14*$L$5+M14*$M$5 -> 1.0004938e+08 | F14: =F16+F15+F20+F23+F31+F32 -> 497.7581 | G14: =G16+G15+G20+G23+G31+G32 -> 497.7581 | H14: =H16+H15+H20+H23+H31+H32 -> 497.7581 | I14: =I16+I15+I20+I23+I31+I32 -> 497.7581 | J14: =J16+J15+J20+J23+J31+J32 -> 497.7581 | L14: =L16+L15+L20+L23+L31+L32 -> 0 | M14: =M16+M15+M20+M23+M31+M32 -> 0 | N14: =(E14/$E$5)/($N$7-$E$13/$E$5) -> 0.85 | O14: {=SUMPRODUCT(P14:Q14,$P$35:$Q$35)-J14} -> 0 | P14: =P16+P15+P20+P23+P31+P32 -> 376.27 | Q14: =Q16+Q15+Q20+Q23+Q31+Q32 -> 121.4881
A15: 单套材料成本（元/PCS） | D15: BOM材料成本 | E15: =F15*$F$5+G15*$G$5+H15*$H$5+$I$5*I15+J15*$J$5+K15*$K$5+L15*$L$5+M15*$M$5 -> 77813357 | F15: =配置明细!G14 -> 387.13113 | G15: =F15 -> 387.13113 | H15: =G15 -> 387.13113 | I15: =H15 -> 387.13113 | J15: =I15 -> 387.13113 | N15: =(E15/$E$5)/($N$7-$E$13/$E$5) -> 0.6610871 | O15: {=SUMPRODUCT(P15:Q15,$P$35:$Q$35)-J15} -> 0 | P15: =VLOOKUP(P3,配置明细!$B$2:$G$13,6,0) -> 296.27997 | Q15: =VLOOKUP(Q3,配置明细!$B$2:$G$13,6,0) -> 90.851159
A16: 单套直接人工（元/PCS） | E16: =F16*$F$5+G16*$G$5+H16*$H$5+$I$5*I16+J16*$J$5+K16*$K$5+L16*$L$5+M16*$M$5 -> 9376443.1 | F16: =F17+F18+F19 -> 46.648971 | G16: =G17+G18+G19 -> 46.648971 | H16: =H17+H18+H19 -> 46.648971 | I16: =H16 -> 46.648971 | J16: =I16 -> 46.648971 | N16: =(E16/$E$5)/($N$7-$E$13/$E$5) -> 0.079660431 | O16: {=SUMPRODUCT(P16:Q16,$P$35:$Q$35)-J16} -> 0 | P16: =P17+P18+P19 -> 32.870301 | Q16: =Q17+Q18+Q19 -> 13.77867
B17: —前工程效率-开线 | C17: 工厂开线标准工时费 | D17: 工厂开线标准工时费*工时 | E17: =F17*$F$5+G17*$G$5+H17*$H$5+$I$5*I17+J17*$J$5+K17*$K$5+L17*$L$5+M17*$M$5 -> 0 | F17: =配置明细!L14*运营工时费报价基准!E8/运营工时费报价基准!$M$5 -> 0 | G17: =F17 -> 0 | H17: =G17 -> 0 | I17: =H17 -> 0 | J17: =I17 -> 0 | N17: =(E17/$E$5)/($N$7-$E$13/$E$5) -> 0 | O17: {=SUMPRODUCT(P17:Q17,$P$35:$Q$35)-J17} -> 0 | P17: =VLOOKUP(P3,配置明细!$B$2:$L$14,11,0)*运营工时费报价基准!$D$6/运营工时费报价基准!$M$5 -> 0 | Q17: =VLOOKUP(Q3,配置明细!$B$2:$L$14,11,0)*运营工时费报价基准!$D$6/运营工时费报价基准!$M$5 -> 0
B18: —前工程效率 - 公共制程 | C18: 工厂公共制程标准工时费 | D18: 工厂公共制程标准工时费*工时 | E18: =F18*$F$5+G18*$G$5+H18*$H$5+$I$5*I18+J18*$J$5+K18*$K$5+L18*$L$5+M18*$M$5 -> 5597701.3 | F18: =配置明细!M14*运营工时费报价基准!$E$8/运营工时费报价基准!$M$5 -> 27.84926 | G18: =F18 -> 27.84926 | H18: =G18 -> 27.84926 | I18: =H18 -> 27.84926 | J18: =I18 -> 27.84926 | N18: =(E18/$E$5)/($N$7-$E$13/$E$5) -> 0.047556978 | O18: {=SUMPRODUCT(P18:Q18,$P$35:$Q$35)-J18} -> 3.907985e-14 | P18: =VLOOKUP(P3,配置明细!$B$2:$M$14,12,0)*运营工时费报价基准!$E$8/运营工时费报价基准!$M$5 -> 18.65375 | Q18: =VLOOKUP(Q3,配置明细!$B$2:$M$14,12,0)*运营工时费报价基准!$E$8/运营工时费报价基准!$M$5 -> 9.1955105
B19: —后工程 - 总装 | C19: 工厂总装标准工时费 | D19: 工厂总装标准工时费*工时 | E19: =F19*$F$5+G19*$G$5+H19*$H$5+$I$5*I19+J19*$J$5+K19*$K$5+L19*$L$5+M19*$M$5 -> 3778741.8 | F19: =配置明细!N14*运营工时费报价基准!$E$8/运营工时费报价基准!$M$5 -> 18.79971 | G19: =F19 -> 18.79971 | H19: =G19 -> 18.79971 | I19: =H19 -> 18.79971 | J19: =I19 -> 18.79971 | N19: =(E19/$E$5)/($N$7-$E$13/$E$5) -> 0.032103453 | O19: {=SUMPRODUCT(P19:Q19,$P$35:$Q$35)-J19} -> 3.907985e-14 | P19: =VLOOKUP(P3,配置明细!$B$2:$N$14,13,0)*运营工时费报价基准!$E$8/运营工时费报价基准!$M$5 -> 14.216551 | Q19: =VLOOKUP(Q3,配置明细!$B$2:$N$14,13,0)*运营工时费报价基准!$E$8/运营工时费报价基准!$M$5 -> 4.5831592
A20: 单套设备成本（元/PCS） | E20: =F20*$F$5+G20*$G$5+H20*$H$5+$I$5*I20+J20*$J$5+K20*$K$5+L20*$L$5+M20*$M$5 -> 2968152.1 | F20: =F21+F22 -> 14.766926 | G20: =G21+G22 -> 14.766926 | H20: =H21+H22 -> 14.766926 | I20: =H20 -> 14.766926 | J20: =I20 -> 14.766926 | N20: =(E20/$E$5)/($N$7-$E$13/$E$5) -> 0.025216841 | O20: {=SUMPRODUCT(P20:Q20,$P$35:$Q$35)-J20} -> 0 | P20: =P21+P22 -> 9.803013 | Q20: =Q21+Q22 -> 4.9639131
B21: —共用设备（元/PCS) | D21: 年折旧*使用年限/产量 | E21: =F21*$F$5+G21*$G$5+H21*$H$5+$I$5*I21+J21*$J$5+K21*$K$5+L21*$L$5+M21*$M$5 -> 1769533.1 | F21: =设备投资明细!K20 -> 8.8036475 | G21: =F21 -> 8.8036475 | H21: =G21 -> 8.8036475 | I21: =H21 -> 8.8036475 | J21: =I21 -> 8.8036475 | N21: =(E21/$E$5)/($N$7-$E$13/$E$5) -> 0.015033608 | O21: {=SUMPRODUCT(P21:Q21,$P$35:$Q$35)-J21} -> 0 | P21: =设备投资明细!Q20 -> 5.8543015 | Q21: =设备投资明细!R20 -> 2.9493459
B22: —专用设备（元/PCS) | D22: 总价值／产量 | E22: =F22*$F$5+G22*$G$5+H22*$H$5+$I$5*I22+J22*$J$5+K22*$K$5+L22*$L$5+M22*$M$5 -> 1198619 | F22: =设备投资明细!J29+项目专用模具!L11+'项目工装投入 '!L16 -> 5.9632786 | G22: =F22 -> 5.9632786 | H22: =G22 -> 5.9632786 | I22: =H22 -> 5.9632786 | J22: =I22 -> 5.9632786 | N22: =(E22/$E$5)/($N$7-$E$13/$E$5) -> 0.010183233 | O22: {=SUMPRODUCT(P22:Q22,$P$35:$Q$35)-J22} -> 0 | P22: =设备投资明细!Q29+项目专用模具!O10+'项目工装投入 '!O15 -> 3.9487114 | Q22: =设备投资明细!R29+项目专用模具!P10+'项目工装投入 '!P15 -> 2.0145672
A23: 制造费用(单套) D=①+②+③+④ | E23: =F23*$F$5+G23*$G$5+H23*$H$5+$I$5*I23+J23*$J$5+K23*$K$5+L23*$L$5+M23*$M$5 -> 5260466.3 | F23: =F24+F25+F26+F27+F28+F29+F30 -> 26.171474 | G23: =G24+G25+G26+G27+G28+G29+G30 -> 26.171474 | H23: =H24+H25+H26+H27+H28+H29+H30 -> 26.171474 | I23: =I24+I25+I26+I27+I28+I29+I30 -> 26.171474 | J23: =J24+J25+J26+J27+J28+J29+J30 -> 26.171474 | N23: =(E23/$E$5)/($N$7-$E$13/$E$5) -> 0.044691895 | O23: {=SUMPRODUCT(P23:Q23,$P$35:$Q$35)-J23} -> -3.5527137e-14 | P23: =P24+P25+P26+P27+P28+P29+P30 -> 18.558704 | Q23: =Q24+Q25+Q26+Q27+Q28+Q29+Q30 -> 7.6127703
B24: —间接人工 | C24: 工厂费率 | D24: 工厂费率*工时 | E24: =F24*$F$5+G24*$G$5+H24*$H$5+$I$5*I24+J24*$J$5+K24*$K$5+L24*$L$5+M24*$M$5 -> 2079440.6 | F24: =(配置明细!$L$14+配置明细!$M$14+配置明细!$N$14)*运营工时费报价基准!E10 -> 10.345476 | G24: =F24 -> 10.345476 | H24: =G24 -> 10.345476 | I24: =H24 -> 10.345476 | J24: =I24 -> 10.345476 | N24: =(E24/$E$5)/($N$7-$E$13/$E$5) -> 0.017666522 | O24: {=SUMPRODUCT(P24:Q24,$P$35:$Q$35)-J24} -> -2.3092639e-14 | P24: =(VLOOKUP(P$3,配置明细!$B$2:$L$14,11,0)+VLOOKUP(P$3,配置明细!$B$3:$M$14,12,0)+VLOOKUP(P$3,配置明细!$B$3:$N$14,13,0))*运营工时费报价基准!$E$10 -> 7.2897408 | Q24: =(VLOOKUP(Q$3,配置明细!$B$2:$L$14,11,0)+VLOOKUP(Q$3,配置明细!$B$3:$M$14,12,0)+VLOOKUP(Q$3,配置明细!$B$3:$N$14,13,0))*运营工时费报价基准!$E$10 -> 3.055735
B25: —低值易耗品 | C25: 工厂费率 | D25: 工厂费率*工时 | E25: =F25*$F$5+G25*$G$5+H25*$H$5+$I$5*I25+J25*$J$5+K25*$K$5+L25*$L$5+M25*$M$5 -> 163876.36 | F25: =(配置明细!$L$14+配置明细!$M$14+配置明细!$N$14)*运营工时费报价基准!E11 -> 0.81530525 | G25: =F25 -> 0.81530525 | H25: =G25 -> 0.81530525 | I25: =H25 -> 0.81530525 | J25: =I25 -> 0.81530525 | N25: =(E25/$E$5)/($N$7-$E$13/$E$5) -> 0.0013922615 | O25: {=SUMPRODUCT(P25:Q25,$P$35:$Q$35)-J25} -> 0 | P25: =(VLOOKUP(P$3,配置明细!$B$2:$L$14,11,0)+VLOOKUP(P$3,配置明细!$B$3:$M$14,12,0)+VLOOKUP(P$3,配置明细!$B$3:$N$14,13,0))*运营工时费报价基准!$E$11 -> 0.57448918 | Q25: =(VLOOKUP(Q$3,配置明细!$B$2:$L$14,11,0)+VLOOKUP(Q$3,配置明细!$B$3:$M$14,12,0)+VLOOKUP(Q$3,配置明细!$B$3:$N$14,13,0))*运营工时费报价基准!$E$11 -> 0.24081607
B26: —机物料消耗 | C26: 工厂费率 | D26: 工厂费率*工时 | E26: =F26*$F$5+G26*$G$5+H26*$H$5+$I$5*I26+J26*$J$5+K26*$K$5+L26*$L$5+M26*$M$5 -> 772510.19 | F26: =(配置明细!$L$14+配置明细!$M$14+配置明细!$N$14)*运营工时费报价基准!E12 -> 3.8433343 | G26: =F26 -> 3.8433343 | H26: =G26 -> 3.8433343 | I26: =H26 -> 3.8433343 | J26: =I26 -> 3.8433343 | N26: =(E26/$E$5)/($N$7-$E$13/$E$5) -> 0.0065630958 | O26: {=SUMPRODUCT(P26:Q26,$P$35:$Q$35)-J26} -> 0 | P26: =(VLOOKUP(P$3,配置明细!$B$2:$L$14,11,0)+VLOOKUP(P$3,配置明细!$B$3:$M$14,12,0)+VLOOKUP(P$3,配置明细!$B$3:$N$14,13,0))*运营工时费报价基准!$E$12 -> 2.7081317 | Q26: =(VLOOKUP(Q$3,配置明细!$B$2:$L$14,11,0)+VLOOKUP(Q$3,配置明细!$B$3:$M$14,12,0)+VLOOKUP(Q$3,配置明细!$B$3:$N$14,13,0))*运营工时费报价基准!$E$12 -> 1.1352026
B27: —厂房分摊 | C27: 工厂费率 | D27: 工厂费率*工时 | E27: =F27*$F$5+G27*$G$5+H27*$H$5+$I$5*I27+J27*$J$5+K27*$K$5+L27*$L$5+M27*$M$5 -> 1240910.5 | F27: =(配置明细!$L$14+配置明细!$M$14+配置明细!$N$14)*运营工时费报价基准!E13 -> 6.1736842 | G27: =F27 -> 6.1736842 | H27: =G27 -> 6.1736842 | I27: =H27 -> 6.1736842 | J27: =I27 -> 6.1736842 | N27: =(E27/$E$5)/($N$7-$E$13/$E$5) -> 0.010542534 | O27: {=SUMPRODUCT(P27:Q27,$P$35:$Q$35)-J27} -> 0 | P27: =(VLOOKUP(P$3,配置明细!$B$2:$L$14,11,0)+VLOOKUP(P$3,配置明细!$B$3:$M$14,12,0)+VLOOKUP(P$3,配置明细!$B$3:$N$14,13,0))*运营工时费报价基准!$E$13 -> 4.350168 | Q27: =(VLOOKUP(Q$3,配置明细!$B$2:$L$14,11,0)+VLOOKUP(Q$3,配置明细!$B$3:$M$14,12,0)+VLOOKUP(Q$3,配置明细!$B$3:$N$14,13,0))*运营工时费报价基准!$E$13 -> 1.8235162
B28: —自动化仓、仓库分摊 | C28: 工厂费率 | D28: 工厂费率*工时 | E28: =F28*$F$5+G28*$G$5+H28*$H$5+$I$5*I28+J28*$J$5+K28*$K$5+L28*$L$5+M28*$M$5 -> 77840.228 | F28: =(配置明细!$L$14+配置明细!$M$14+配置明细!$N$14)*运营工时费报价基准!E14 -> 0.38726481 | G28: =F28 -> 0.38726481 | H28: =G28 -> 0.38726481 | I28: =H28 -> 0.38726481 | J28: =I28 -> 0.38726481 | N28: =(E28/$E$5)/($N$7-$E$13/$E$5) -> 0.00066131539 | O28: {=SUMPRODUCT(P28:Q28,$P$35:$Q$35)-J28} -> 4.9960036e-16 | P28: =(VLOOKUP(P$3,配置明细!$B$2:$L$14,11,0)+VLOOKUP(P$3,配置明细!$B$3:$M$14,12,0)+VLOOKUP(P$3,配置明细!$B$3:$N$14,13,0))*运营工时费报价基准!$E$14 -> 0.27287871 | Q28: =(VLOOKUP(Q$3,配置明细!$B$2:$L$14,11,0)+VLOOKUP(Q$3,配置明细!$B$3:$M$14,12,0)+VLOOKUP(Q$3,配置明细!$B$3:$N$14,13,0))*运营工时费报价基准!$E$14 -> 0.1143861
B29: —其他制费 | C29: 工厂费率 | D29: 工厂费率*工时 | E29: =F29*$F$5+G29*$G$5+H29*$H$5+$I$5*I29+J29*$J$5+K29*$K$5+L29*$L$5+M29*$M$5 -> 536821.54 | F29: =(配置明细!$L$14+配置明细!$M$14+配置明细!$N$14)*运营工时费报价基准!E15 -> 2.6707539 | G29: =F29 -> 2.6707539 | H29: =G29 -> 2.6707539 | I29: =H29 -> 2.6707539 | J29: =I29 -> 2.6707539 | N29: =(E29/$E$5)/($N$7-$E$13/$E$5) -> 0.0045607311 | O29: {=SUMPRODUCT(P29:Q29,$P$35:$Q$35)-J29} -> -3.9968029e-15 | P29: =(VLOOKUP(P$3,配置明细!$B$2:$L$14,11,0)+VLOOKUP(P$3,配置明细!$B$3:$M$14,12,0)+VLOOKUP(P$3,配置明细!$B$3:$N$14,13,0))*运营工时费报价基准!$E$15 -> 1.8818955 | Q29: =(VLOOKUP(Q$3,配置明细!$B$2:$L$14,11,0)+VLOOKUP(Q$3,配置明细!$B$3:$M$14,12,0)+VLOOKUP(Q$3,配置明细!$B$3:$N$14,13,0))*运营工时费报价基准!$E$15 -> 0.78885848
B30: -材料损耗 | C30: 材料*0.5% | E30: =F30*$F$5+G30*$G$5+H30*$H$5+$I$5*I30+J30*$J$5+K30*$K$5+L30*$L$5+M30*$M$5 -> 389066.78 | F30: =F15*0.5% -> 1.9356556 | G30: =G15*0.5% -> 1.9356556 | H30: =H15*0.5% -> 1.9356556 | I30: =I15*0.5% -> 1.9356556 | J30: =J15*0.5% -> 1.9356556 | N30: =(E30/$E$5)/($N$7-$E$13/$E$5) -> 0.0033054355 | O30: {=SUMPRODUCT(P30:Q30,$P$35:$Q$35)-J30} -> 0 | P30: =P15*0.5% -> 1.4813998 | Q30: =Q15*0.5% -> 0.45425579
A31: 研发费用（元/PCS） | D31: 投入费/产量 | E31: =F31*$F$5+G31*$G$5+H31*$H$5+$I$5*I31+J31*$J$5+K31*$K$5+L31*$L$5+M31*$M$5 -> 563400 | F31: ='研发费用 '!F19 -> 2.8029851 | G31: =F31 -> 2.8029851 | H31: =G31 -> 2.8029851 | I31: =H31 -> 2.8029851 | J31: =I31 -> 2.8029851 | N31: =(E31/$E$5)/($N$7-$E$13/$E$5) -> 0.0047865365 | O31: {=SUMPRODUCT(P31:Q31,$P$35:$Q$35)-J31} -> -1.110223e-14 | P31: ='研发费用 '!$F$21*P4 -> 2.5953566 | Q31: ='研发费用 '!$F$21*Q4 -> 0.20762852
A32: 单套包装、物流费用（元/PCS） | D32: 投入费/产量 | E32: =F32*$F$5+G32*$G$5+H32*$H$5+$I$5*I32+J32*$J$5+K32*$K$5+L32*$L$5+M32*$M$5 -> 4067560.5 | F32: =包装物流费用!L14 -> 20.236619 | G32: =F32 -> 20.236619 | H32: =G32 -> 20.236619 | I32: =H32 -> 20.236619 | J32: =I32 -> 20.236619 | N32: =(E32/$E$5)/($N$7-$E$13/$E$5) -> 0.0345572 | O32: {=SUMPRODUCT(P32:Q32,$P$35:$Q$35)-J32} -> 0 | P32: =VLOOKUP(P3,包装物流费用!$A$3:$L$13,12,0) -> 16.162657 | Q32: =VLOOKUP(Q3,包装物流费用!$A$3:$L$13,12,0) -> 4.0739627
A34: 解释：
A35: 低值易耗品费：工装板、模块、辅助工具、物料盒等 | N35: 第一页 | O35: =设备投资明细!N31 -> 装车比 | P35: {=TRANSPOSE(配置明细!E3:E4)} -> 1 | Q35: 1
A36: 机物料消耗：质量检验测试、开机测试 | O36: =设备投资明细!N32 -> 总量纲 | P36: =$E$5 -> 201000 | Q36: =$E$5 -> 201000
A37: 其他制费：差旅费、水电费、劳保用品、备品备件等 | O37: =设备投资明细!N33 -> 数量 | P37: =P35*P36 -> 201000 | Q37: =Q35*Q36 -> 201000
A39: 删除辅助工装类→和低值易耗品重复

Sheet 客户报价逻辑
B2: 零件号 | C2: 零件名称 | D2: 用量 | E2: 铜重 | F2: 铝重 | G2: 材料成本 （元） | H2: 废品率 （0.9%） | I2: 实际工时 | J2: 直接人工 (35元/H) | K2: 制造费 (47元/H) | L2: 人工+制造费 | M2: 管理费 (6%) | N2: 利润 | O2: 出厂价 | P2: 包装费 | Q2: 运输费 | R2: 到厂价
C3: *零件名称 | D3: *标配/选配 | E3: 铜重
B4: =配置明细!B3 -> 6608523073 | C4: =配置明细!D3 -> 组合式充电插座线束总成 | D4: =配置明细!E3 -> 1 | E4: =配置明细!I3 -> 0 | F4: =配置明细!J3 -> 0 | G4: =配置明细!G3 -> 296.27997 | H4: =G4*1% -> 2.9627997 | I4: =配置明细!M3+配置明细!N3 -> 1.126 | J4: =I4*35 -> 39.41 | K4: =$K$20*I4 -> 52.57294 | L4: =K4+J4 -> 91.98294 | M4: =(G4+L4)*6% -> 23.295775 | N4: =(L4+H4+G4)*6% -> 23.473543 | O4: =N4+M4+L4+G4+H4 -> 437.99503 | P4: =包装物流费用!E4+包装物流费用!F4 -> 5.9517567 | Q4: =包装物流费用!I4+包装物流费用!J4+包装物流费用!K4 -> 4.75 | R4: =Q4+P4+O4 -> 448.69678
B5: =配置明细!B4 -> 6608523072 | C5: =配置明细!D4 -> 充电线束总成 | D5: =配置明细!E4 -> 1 | E5: =配置明细!I4 -> 0 | F5: =配置明细!J4 -> 0 | G5: =配置明细!G4 -> 90.851159 | H5: =G5*1% -> 0.90851159 | I5: =配置明细!M4+配置明细!N4 -> 0.472 | J5: =I5*35 -> 16.52 | K5: =$K$20*I5 -> 22.03768 | L5: =K5+J5 -> 38.55768 | M5: =(G5+L5)*6% -> 7.7645303 | N5: =(L5+H5+G5)*6% -> 7.819041 | O5: =N5+M5+L5+G5+H5 -> 145.90092 | P5: =包装物流费用!E5+包装物流费用!F5 -> 1.1125093 | Q5: =包装物流费用!I5+包装物流费用!J5+包装物流费用!K5 -> 2.2333333 | R5: =Q5+P5+O5 -> 149.24676
B6: =配置明细!#REF! -> #REF! | C6: =配置明细!#REF! -> #REF! | D6: =配置明细!#REF! -> #REF! | E6: =配置明细!#REF! -> #REF! | F6: =配置明细!#REF! -> #REF! | G6: =配置明细!#REF! -> #REF! | H6: =G6*1% -> #REF! | I6: =配置明细!#REF!+配置明细!#REF! -> #REF! | J6: =I6*35 -> #REF! | K6: =$K$20*I6 -> #REF! | L6: =K6+J6 -> #REF! | M6: =(G6+L6)*6% -> #REF! | N6: =(L6+H6+G6)*6% -> #REF! | O6: =N6+M6+L6+G6+H6 -> #REF! | P6: =包装物流费用!#REF!+包装物流费用!#REF! -> #REF! | Q6: =包装物流费用!#REF!+包装物流费用!#REF!+包装物流费用!#REF! -> #REF! | R6: =Q6+P6+O6 -> #REF!
B7: =配置明细!#REF! -> #REF! | C7: =配置明细!#REF! -> #REF! | D7: =配置明细!#REF! -> #REF! | E7: =配置明细!#REF! -> #REF! | F7: =配置明细!#REF! -> #REF! | G7: =配置明细!#REF! -> #REF! | H7: =G7*1% -> #REF! | I7: =配置明细!#REF!+配置明细!#REF! -> #REF! | J7: =I7*35 -> #REF! | K7: =$K$20*I7 -> #REF! | L7: =K7+J7 -> #REF! | M7: =(G7+L7)*6% -> #REF! | N7: =(L7+H7+G7)*6% -> #REF! | O7: =N7+M7+L7+G7+H7 -> #REF! | P7: =包装物流费用!#REF!+包装物流费用!#REF! -> #REF! | Q7: =包装物流费用!#REF!+包装物流费用!#REF!+包装物流费用!#REF! -> #REF! | R7: =Q7+P7+O7 -> #REF!
B8: =配置明细!#REF! -> #REF! | C8: =配置明细!#REF! -> #REF! | D8: =配置明细!#REF! -> #REF! | E8: =配置明细!#REF! -> #REF! | F8: =配置明细!#REF! -> #REF! | G8: =配置明细!#REF! -> #REF! | H8: =G8*1% -> #REF! | I8: =配置明细!#REF!+配置明细!#REF! -> #REF! | J8: =I8*35 -> #REF! | K8: =$K$20*I8 -> #REF! | L8: =K8+J8 -> #REF! | M8: =(G8+L8)*6% -> #REF! | N8: =(L8+H8+G8)*6% -> #REF! | O8: =N8+M8+L8+G8+H8 -> #REF! | P8: =包装物流费用!#REF!+包装物流费用!#REF! -> #REF! | Q8: =包装物流费用!#REF!+包装物流费用!#REF!+包装物流费用!#REF! -> #REF! | R8: =Q8+P8+O8 -> #REF!
B9: =配置明细!#REF! -> #REF! | C9: =配置明细!#REF! -> #REF! | D9: =配置明细!#REF! -> #REF! | E9: =配置明细!#REF! -> #REF! | F9: =配置明细!#REF! -> #REF! | G9: =配置明细!#REF! -> #REF! | H9: =G9*1% -> #REF! | I9: =配置明细!#REF!+配置明细!#REF! -> #REF! | J9: =I9*35 -> #REF! | K9: =$K$20*I9 -> #REF! | L9: =K9+J9 -> #REF! | M9: =(G9+L9)*6% -> #REF! | N9: =(L9+H9+G9)*6% -> #REF! | O9: =N9+M9+L9+G9+H9 -> #REF! | P9: =包装物流费用!#REF!+包装物流费用!#REF! -> #REF! | Q9: =包装物流费用!#REF!+包装物流费用!#REF!+包装物流费用!#REF! -> #REF! | R9: =Q9+P9+O9 -> #REF!
B10: =配置明细!#REF! -> #REF! | C10: =配置明细!#REF! -> #REF! | D10: =配置明细!#REF! -> #REF! | E10: =配置明细!#REF! -> #REF! | F10: =配置明细!#REF! -> #REF! | G10: =配置明细!#REF! -> #REF! | H10: =G10*1% -> #REF! | I10: =配置明细!#REF!+配置明细!#REF! -> #REF! | J10: =I10*35 -> #REF! | K10: =$K$20*I10 -> #REF! | L10: =K10+J10 -> #REF! | M10: =(G10+L10)*6% -> #REF! | N10: =(L10+H10+G10)*6% -> #REF! | O10: =N10+M10+L10+G10+H10 -> #REF! | P10: =包装物流费用!#REF!+包装物流费用!#REF! -> #REF! | Q10: =包装物流费用!#REF!+包装物流费用!#REF!+包装物流费用!#REF! -> #REF! | R10: =Q10+P10+O10 -> #REF!
B11: =配置明细!#REF! -> #REF! | C11: =配置明细!#REF! -> #REF! | D11: =配置明细!#REF! -> #REF! | E11: =配置明细!#REF! -> #REF! | F11: =配置明细!#REF! -> #REF! | G11: =配置明细!#REF! -> #REF! | H11: =G11*1% -> #REF! | I11: =配置明细!#REF!+配置明细!#REF! -> #REF! | J11: =I11*35 -> #REF! | K11: =$K$20*I11 -> #REF! | L11: =K11+J11 -> #REF! | M11: =(G11+L11)*6% -> #REF! | N11: =(L11+H11+G11)*6% -> #REF! | O11: =N11+M11+L11+G11+H11 -> #REF! | P11: =包装物流费用!#REF!+包装物流费用!#REF! -> #REF! | Q11: =包装物流费用!#REF!+包装物流费用!#REF!+包装物流费用!#REF! -> #REF! | R11: =Q11+P11+O11 -> #REF!
B12: =配置明细!#REF! -> #REF! | C12: =配置明细!#REF! -> #REF! | D12: =配置明细!#REF! -> #REF! | E12: =配置明细!#REF! -> #REF! | F12: =配置明细!#REF! -> #REF! | G12: =配置明细!#REF! -> #REF! | H12: =G12*1% -> #REF! | I12: =配置明细!#REF!+配置明细!#REF! -> #REF! | J12: =I12*35 -> #REF! | K12: =$K$20*I12 -> #REF! | L12: =K12+J12 -> #REF! | M12: =(G12+L12)*6% -> #REF! | N12: =(L12+H12+G12)*6% -> #REF! | O12: =N12+M12+L12+G12+H12 -> #REF! | P12: =包装物流费用!#REF!+包装物流费用!#REF! -> #REF! | Q12: =包装物流费用!#REF!+包装物流费用!#REF!+包装物流费用!#REF! -> #REF! | R12: =Q12+P12+O12 -> #REF!
B13: =配置明细!#REF! -> #REF! | C13: =配置明细!#REF! -> #REF! | D13: =配置明细!#REF! -> #REF! | E13: =配置明细!#REF! -> #REF! | F13: =配置明细!#REF! -> #REF! | G13: =配置明细!#REF! -> #REF! | H13: =G13*1% -> #REF! | I13: =配置明细!#REF!+配置明细!#REF! -> #REF! | J13: =I13*35 -> #REF! | K13: =$K$20*I13 -> #REF! | L13: =K13+J13 -> #REF! | M13: =(G13+L13)*6% -> #REF! | N13: =(L13+H13+G13)*6% -> #REF! | O13: =N13+M13+L13+G13+H13 -> #REF! | P13: =包装物流费用!#REF!+包装物流费用!#REF! -> #REF! | Q13: =包装物流费用!#REF!+包装物流费用!#REF!+包装物流费用!#REF! -> #REF! | R13: =Q13+P13+O13 -> #REF!
B14: =配置明细!#REF! -> #REF! | C14: =配置明细!#REF! -> #REF! | D14: =配置明细!#REF! -> #REF! | E14: =配置明细!#REF! -> #REF! | F14: =配置明细!#REF! -> #REF! | G14: =配置明细!#REF! -> #REF! | H14: =G14*1% -> #REF! | I14: =配置明细!#REF!+配置明细!#REF! -> #REF! | J14: =I14*35 -> #REF! | K14: =$K$20*I14 -> #REF! | L14: =K14+J14 -> #REF! | M14: =(G14+L14)*6% -> #REF! | N14: =(L14+H14+G14)*6% -> #REF! | O14: =N14+M14+L14+G14+H14 -> #REF! | P14: =包装物流费用!#REF!+包装物流费用!#REF! -> #REF! | Q14: =包装物流费用!#REF!+包装物流费用!#REF!+包装物流费用!#REF! -> #REF! | R14: =Q14+P14+O14 -> #REF!
B17: 装车比 | E17: {=SUMPRODUCT($D$4:$D$14,E4:E14)} -> #REF! | F17: {=SUMPRODUCT($D$4:$D$14,F4:F14)} -> #REF! | G17: {=SUMPRODUCT($D$4:$D$14,G4:G14)} -> #REF! | H17: {=SUMPRODUCT($D$4:$D$14,H4:H14)} -> #REF! | I17: {=SUMPRODUCT($D$4:$D$14,I4:I14)} -> #REF! | J17: {=SUMPRODUCT($D$4:$D$14,J4:J14)} -> #REF! | K17: {=SUMPRODUCT($D$4:$D$14,K4:K14)} -> #REF! | L17: {=SUMPRODUCT($D$4:$D$14,L4:L14)} -> #REF! | ... R17: {=SUMPRODUCT($D$4:$D$14,R4:R14)} -> #REF!
R19: ='项目评估汇总（昆山90%）'!N9 -> 585.59777
K20: =37.36-1.25+0.27+11.52-1.38+0.17 -> 46.69

Sheet 运营工时费报价基准
B2: 1、运营工时费 25年1-6月 基准
B4: 区分 元/h | D4: K1K2工厂 | E4: K3工厂 | F4: 宁波工厂 | G4: 仪征工厂 | H4: 重庆工厂 低压 | I4: 重庆工厂 高压 | J4: 天津工厂
B5: 直接人工-出勤工时 | D5: 28.606853 | E5: =E8 -> 26.272887 | F5: 26.76716 | G5: 28.169428 | H5: 31.176795 | I5: 32.034397 | J5: 27.711746 | L5: 效率 | M5: =工厂效率!D17 -> 0.9
C6: -前工程效率-开线 元/h | D6: 30.198448 | G6: 28.028971 | H6: 34.195473
C7: -前工程效率 - 公共制程 元/h | D7: 28.188328 | G7: 27.662417 | H7: 30.866301
C8: -后工程 - 总装 元/h | D8: 28.580082 | E8: 26.272887 | F8: 26.76716 | G8: 32.856511 | H8: 31.038701 | I8: 32.034397 | J8: 27.711746
B9: 制造费用 | D9: 16.14+损耗 | E9: 15.17+损耗 | F9: 20.32+损耗 | G9: 15.13+损耗 | H9: 15.81+损耗 | I9: 23.46+损耗 | J9: 16.22+损耗
C10: -间接人工 元/h | D10: 8.4990788 | E10: 6.4740149 | F10: 9.45 （16.16） | G10: 10.393806 | H10: 9.748783 | I10: 11.162784 | J10: 8.8160737
C11: -低值易耗品费 元/h | D11: 0.87635407 | E11: 0.51020354 | F11: 0.41150703 | G11: 0.79522147 | H11: 2.1303395 | I11: 2.8080612 | J11: 0.51 （0.23）
C12: -机物料消耗 元/h | D12: 1.8562976 | E12: 2.4050903 | F12: 1.0939274 | G12: 0.69071852 | H12: 0.98154286 | I12: 4.9691472 | J12: 2.41 （0.11）
C13: -厂房分摊 元/h | D13: 1.45 | E13: 3.8633819 | F13: 3.2642647 | G13: 0.6107946 | H13: 1.0053462 | I13: 2.7842904 | J13: 2.9830898
C14: -自动化仓、仓库分摊 元/h | D14: 2.03 | E14: 0.24234344 | F14: 2.4354479 | G14: 0.51592727 | H14: 0.89453553 | I14: 0.89939771 | J14: 0
C15: -其他制费 元/h | D15: 1.423375 | E15: 1.6713103 | F15: 3.6629747 | G15: 2.1267819 | H15: 1.0477841 | I15: 0.83737698 | J15: 1.4978537
C16: -材料损耗 材料*0.5% | D16: 材料*0.5% | E16: 材料*0.5% | F16: 材料*0.5% | G16: 材料*0.5% | H16: 材料*0.5% | I16: 材料*0.5% | J16: 材料*0.5%
B18: 宁波工厂-间接人工 ：因产值低，按照昆山低压与仪征平均取数
B19: 天津工厂-低值易耗+机物料消耗 ：项目前期使用昆山高压物料，按照昆山高压取数
B20: K1K2工厂-厂房、自动化仓库摊销：25年1-6月产能不足，数据参考25年下半年预算

Sheet 工厂效率
B2: ● 25年报价效率：昆山低压、宁波、仪征、天津、重庆低压
B4: 总工时 | C4: 项目节拍 PCS/h | G4: 描述
C5: ≤5 | D5: 5~10 | E5: 10~20 | F5: ＞20
B6: ≤4h | C6: 0.9 | D6: 0.95 | E6: 1 | F6: 1.05 | G6: 单回路工时＞42S
B7: 4h~20h | C7: 0.85 | D7: 0.9 | E7: 0.95 | F7: 1
B8: ＞20h | C8: 0.8 | D8: 0.85 | E8: 0.9 | F8: 0.95
B9: ≤4h | C9: 0.85 | D9: 0.9 | E9: 0.95 | F9: 1 | G9: 单回路工时＜42S
B10: 4h~20h | C10: 0.8 | D10: 0.85 | E10: 0.9 | F10: 0.95
B11: ＞20h | C11: 0.75 | D11: 0.8 | E11: 0.85 | F11: 0.9
B14: ● 25年报价效率：昆山高压、天津高压、重庆高压
B16: 项目节拍 PCS/h | C16: ≤10 | D16: 10~20 | E16: >20 | F16: 描述
B17: 2025报价LE | C17: 0.85 | D17: 0.9 | E17: 0.95 | F17: 单班JPH效率

Sheet 设备投资明细
A1: ='项目评估汇总（昆山90%）'!A1 -> 吉利P162大电池包高压 | Q1: 1 | R1: 2
A2: 一、公用设备投入（前工程） | G2: 需求资产 | I2: 剩余资产 | K2: 新增资产 | M2: 单价 （标准件-财务； 非标件-申购部门） | N2: 备注 | O2: 适用范围 | P2: 供应商 | Q2: {=TRANSPOSE(配置明细!$B$3:$B$4)} -> 6608523073 | R2: 6608523072
A3: 编号 | B3: 归属 | C3: 项目投资名称 | D3: 设备名称 | E3: 工艺报价参考规格型号 | F3: 单位 | G3: 数量 | H3: 金额 | I3: 数量 | J3: 金额 | K3: 数量 | L3: 金额 | Q3: {=TRANSPOSE(配置明细!D3:D4)} -> 组合式充电插座线束总成 | R3: 充电线束总成
A4: A0001 | B4: 公用设备类 | C4: 开线 | D4: 全自动开线机/Kappa350 | E4: Kappa350 | F4: 台 | G4: =SUM(Q4:R4) -> 0.12 | K4: =G4-I4 -> 0.12 | L4: =K4*M4 -> 93600 | M4: 780000 | Q4: 0.07 | R4: 0.05
A5: A0001 | B5: 公用设备类 | C5: 开线 | D5: 全自动开线压接机/Alpha550 | E5: Alpha550 | F5: 台 | G5: =SUM(Q5:R5) -> 0.28 | K5: =G5-I5 -> 0.28 | L5: =K5*M5 -> 341946.9 | M5: 1221238.9 | Q5: 0.28 | R5: 0
A6: A0001 | B6: 公用设备类 | C6: 压接 | D6: 大平方压接机/XYD-30T | E6: XYD-30T | F6: 台 | G6: =SUM(Q6:R6) -> 0.86 | K6: =G6-I6 -> 0.86 | L6: =K6*M6 -> 72699.403 | M6: 84534.19 | Q6: 0 | R6: 0.86
A7: A0001 | B7: 公用设备类 | C7: 压接 | D7: 小平方压接机-变频/XYD-4T | E7: XYD-4T | F7: 台 | G7: =SUM(Q7:R7) -> 0.49 | K7: =G7-I7 -> 0.49 | L7: =K7*M7 -> 7742 | M7: 15800 | O7: 焊120铝（安奕吉 HVW-12/骄成 WL-B-AH9994-F） | Q7: 0.49 | R7: 0
A8: A0001 | B8: 公用设备类 | C8: 焊接 | D8: 焊接机/安奕吉 HVW-6 | E8: 安奕吉 HVW-6 | F8: 台 | G8: =SUM(Q8:R8) -> 0.54 | K8: =G8-I8 -> 0.54 | L8: =K8*M8 -> 420531.48 | M8: 778762 | O8: 焊50铝（安奕吉 HVW-6/骄成 WD-AH9940-F） | Q8: 0 | R8: 0.54
A9: A0001 | B9: 公用设备类 | C9: 焊接 | D9: 焊接机/骄成 WD-M9960-F 10KW | E9: 骄成 WD-M9960-F 10KW | F9: 台 | G9: =SUM(Q9:R9) -> 1.38 | K9: =G9-I9 -> 1.38 | L9: =K9*M9 -> 857307.47 | M9: 621237.3 | O9: 焊4方/6方铝（安奕吉 HVW-4/ WS-PH9810-F） | Q9: 1.38 | R9: 0
A10: A0001 | B10: 公用设备类 | C10: 去绝缘皮 | D10: 切剥翻一体机/定制 | E10: 定制 | F10: 台 | G10: =SUM(Q10:R10) -> 0.86 | K10: =G10-I10 -> 0.86 | L10: =K10*M10 -> 120400 | M10: 140000 | O10: 并线焊（安奕吉 AW-4/骄成 WE-AH9810-L） | Q10: 0 | R10: 0.86
A11: A0001 | B11: 公用设备类 | C11: 检测设备 | D11: 高压&气密检测/STRONG TEST-HG01 | E11: STRONG TEST-HG01 | F11: 台 | G11: =SUM(Q11:R11) -> 1.7 | K11: =G11-I11 -> 1.7 | L11: =K11*M11 -> 663000 | M11: 390000 | Q11: 0.84 | R11: 0.86
A12: A0001 | B12: 公用设备类 | C12: 检测设备 | D12: 低压电测台：小（10≤模块数≥2）/斜面-TS1700 | G12: =SUM(Q12:R12) -> 0.43 | K12: =G12-I12 -> 0.43 | L12: =K12*M12 -> 86000 | M12: 200000 | Q12: 0.43 | R12: 0
A13: A0001 | B13: 公用设备类 | C13: 扭力台 | D13: 扭力站/ST-HG-SCR | E13: ST-HG-SCR | F13: 台 | G13: =SUM(Q13:R13) -> 1 | K13: =G13-I13 -> 1 | L13: =K13*M13 -> 188000 | M13: 188000 | Q13: 1 | R13: 0
A14: A0001 | B14: 公用设备类 | C14: 焊接 | D14: 焊接机/Schunk Minic 2 plus | E14: Schunk Minic 2 plus | F14: 台 | G14: =SUM(Q14:R14) -> 0.05 | K14: =G14-I14 -> 0.05 | L14: =K14*M14 -> 11021.416 | M14: 220428.32 | Q14: 0.05 | R14: 0
A15: A0001 | B15: 公用设备类 | C15: 焊接 | D15: 焊接机/骄成 WD-MP9900-F | E15: 骄成 WD-MP9900-F | F15: 台 | G15: =SUM(Q15:R15) -> 0.14 | K15: =G15-I15 -> 0.14 | L15: =K15*M15 -> 86973.222 | M15: 621237.3 | Q15: 0.14 | R15: 0
G20: 合计 | H20: =SUM(L4:L19) -> 2949221.9 | J20: 单套费用 | K20: =H20/10*6/'项目评估汇总（昆山90%）'!E5 -> 8.8036475 | Q20: {=SUMPRODUCT(Q4:Q18,$M$4:$M$18)/10*6/Q33} -> 5.8543015 | R20: {=SUMPRODUCT(R4:R18,$M$4:$M$18)/10*6/R33} -> 2.9493459
A21: 二、专用设备投入（后工程）
A22: B0001 | B22: 专用设备 | C22: 高压气密测试模块 | D22: 高压测试模块/定制 | E22: 定制 | F22: 个 | G22: =SUM(Q22:R22) -> 6.81 | K22: =G22-I22 -> 6.81 | L22: =K22*M22 -> 79677 | M22: 11700 | O22: 充电座的需增加插拔次数监控功能 | Q22: 4.81 | R22: 2
A23: B0001 | B23: 专用设备 | C23: 卡钉台 | D23: 卡钉测试台/小（10≤模块数≥1） | E23: 小（10≤模块数≥1） | F23: 个 | G23: =SUM(Q23:R23) -> 1 | K23: =G23-I23 -> 1 | L23: =K23*M23 -> 90000 | M23: 90000 | Q23: 1 | R23: 0
K24: =G24-I24 -> 0 | L24: =K24*M24 -> 0
F27: pc | K27: =G27-I27 -> 0 | L27: =K27*M27 -> 0
G29: 合计 | H29: =SUM(L22:L28) -> 169677 | I29: 单套费用 | J29: =H29/'项目评估汇总（昆山90%）'!E5 -> 0.84416418 | Q29: {=SUMPRODUCT(Q22:Q27,$M$22:$M$27)/Q33} -> 0.72774627 | R29: {=SUMPRODUCT(R22:R27,$M$22:$M$27)/R33} -> 0.11641791
M31: 第二页 | N31: 装车比 | Q31: ='项目评估汇总（昆山90%）'!P35 -> 1 | R31: ='项目评估汇总（昆山90%）'!Q35 -> 1
N32: 总量纲 | Q32: ='项目评估汇总（昆山90%）'!$E$5 -> 201000 | R32: ='项目评估汇总（昆山90%）'!$E$5 -> 201000
A33: 填写说明： | N33: 数量 | Q33: =Q32*Q31 -> 201000 | R33: =R32*R31 -> 201000
A34: 1. 涉及自动化产线投资金额，自动化产线-公用件占比全产线金额的80%；自动化产线-专用件占比全产线金额的20%；
A35: 2. 涉及自动化产线需在备注列维护内容：a.公共部分占比自动化设备费用80%； 2、xx平参考设备尺寸：xxm*xxm*xxm； 3、涉及工序：开线，剥皮，去屏蔽层，预装；压接屏蔽环；压接端子；装塑壳；插位；
A36: 3. 如果项目设备/项目专用模具/项目工装投入表格中涉及新增内容在下拉箭头中无法选中，通知设备工程师至W:\昆山泽轩\动能工业中心\前期工艺部\04-前期设备中“泽轩设备数据库信息”中添加新增设备信息； | Q36: =Q29+项目专用模具!O10+'项目工装投入 '!O15 -> 3.9487114 | R36: =R29+项目专用模具!P10+'项目工装投入 '!P15 -> 2.0145672
O37: {=SUMPRODUCT(Q29:R29,Q31:R31)} -> 0.84416418

Sheet 项目专用模具
A1: ='项目评估汇总（昆山90%）'!A1 -> 吉利P162大电池包高压 | O1: 1 | P1: 2
A2: 专用模具投入 | G2: 需求模具（元） | I2: 沿用模具（元） | K2: 新增模具（元） | M2: 备 注 | N2: 单价 | O2: {=TRANSPOSE(配置明细!$B$3:$B$4)} -> 6608523073 | P2: 6608523072
A3: 编号 | B3: 归属 | C3: 项目投资名称 | D3: 名称 | E3: 型号 | F3: 单位 | G3: 需求数量 | H3: 需求金额 | I3: 沿用数量 | J3: 沿用金额 | K3: 新增数量 | L3: 新增金额 | M3: 设备按生命周期量核算模具的数量(低压模具20万次；高压模具5万次；防水栓模具无限制生命周期) | O3: {=TRANSPOSE(配置明细!D3:D4)} -> 组合式充电插座线束总成 | P3: 充电线束总成
A4: C0001 | B4: 模具类 | C4: 模具/模块/治具 | D4: 焊接治具/焊接治具 | E4: 焊接治具 | F4: 个 | G4: =SUM(O4:P4) -> 5 | K4: =G4-I4 -> 5 | L4: =K4*N4 -> 900000 | N4: 180000 | O4: 3 | P4: 2
A5: C0001 | B5: 模具类 | C5: 模具/模块/治具 | D5: 压接模具/小模具（40行程） | F5: 个 | G5: =SUM(O5:P5) -> 3.71 | K5: =G5-I5 -> 3.71 | L5: =K5*N5 -> 14840 | N5: 4000 | O5: 3.71 | P5: 0
A6: C0001 | B6: 模具类 | C6: 模具/模块/治具 | D6: 防水栓模具 | F6: 个 | G6: =SUM(O6:P6) -> 2.41 | K6: =G6-I6 -> 2.41 | L6: =K6*N6 -> 67480 | N6: 28000 | O6: 2.41 | P6: 0
A7: C0001 | B7: 模具类 | C7: 模具/模块/治具 | D7: 压接模具/大模具（50行程） | F7: 个 | G7: =SUM(O7:P7) -> 2 | K7: =G7-I7 -> 2 | L7: =K7*N7 -> 18000 | N7: 9000 | O7: 0 | P7: 2
K8: =G8-I8 -> 0
L10: =SUM(L4:L9) -> 1000320 | O10: {=SUMPRODUCT(O4:O9,$N$4:$N$9)/O14} -> 3.0961194 | P10: {=SUMPRODUCT(P4:P9,$N$4:$N$9)/P14} -> 1.880597
K11: 单套费用 | L11: =L10/'项目评估汇总（昆山90%）'!E5 -> 4.9767164
L12: 第三页 | N12: =设备投资明细!N31 -> 装车比 | O12: ='项目评估汇总（昆山90%）'!P35 -> 1 | P12: =设备投资明细!R31 -> 1
N13: =设备投资明细!N32 -> 总量纲 | O13: ='项目评估汇总（昆山90%）'!P36 -> 201000 | P13: =设备投资明细!R32 -> 201000
N14: =设备投资明细!N33 -> 数量 | O14: =O12*O13 -> 201000 | P14: =P12*P13 -> 201000
M16: {=SUMPRODUCT(O10:P10,O12:P12)} -> 4.9767164
A17: 说明：模具，夹具，模块

Sheet 项目工装投入 
A1: ='项目评估汇总（昆山90%）'!A1 -> 吉利P162大电池包高压 | O1: 1 | P1: 2
A2: 新增工装投入 | G2: 需求工装（元） | I2: 沿用工装（元） | K2: 新增工装（元） | M2: 备 注 | N2: 单价 | O2: {=TRANSPOSE(配置明细!$B$3:$B$4)} -> 6608523073 | P2: 6608523072
A3: 编号 | B3: 归属 | C3: 项目投资名称 | D3: 名称 | E3: 规格型号 | F3: 单位 | G3: 需求数量 | H3: 需求金额 | I3: 沿用数量 | J3: 沿用金额 | K3: 预估/实际数量 | L3: 预估/实际金额 | O3: {=TRANSPOSE(配置明细!D3:D4)} -> 组合式充电插座线束总成 | P3: 充电线束总成
A4: D0001 | B4: 工装类 | C4: 电脑 | D4: 电脑/一体机 | E4: 一体机 | F4: 台 | G4: =SUM(O4:P4) -> 2.91 | K4: =G4-I4 -> 2.91 | L4: =N4*K4 -> 12222 | N4: 4200 | O4: 2.07 | P4: 0.84
A5: D0001 | B5: 工装类 | C5: 辅助工装 | D5: 气动辅助工装/定制 | E5: 定制 | F5: 个 | G5: =SUM(O5:P5) -> 0 | K5: =G5-I5 -> 0 | L5: =N5*K5 -> 0
A6: D0001 | B6: 工装类 | C6: 辅助工装 | D6: 插位回拉工装/定制 | E6: QDKZQ | F6: 个 | G6: =SUM(O6:P6) -> 0 | K6: =G6-I6 -> 0 | L6: =N6*K6 -> 0
A7: D0001 | B7: 工装类 | C7: 辅助工装 | D7: 插位诱导工装/定制 | E7: 定制 | F7: 个 | G7: =SUM(O7:P7) -> 0 | K7: =G7-I7 -> 0 | L7: =N7*K7 -> 0
A8: D0001 | B8: 工装类 | C8: 辅助工装 | D8: 插拔力测试工装/定制 | E8: 定制 | F8: 个 | G8: =SUM(O8:P8) -> 0.41 | K8: =G8-I8 -> 0.41 | L8: =N8*K8 -> 16400 | N8: 40000 | O8: 0.41 | P8: 0
A9: D0001 | B9: 工装类 | C9: 辅助工装 | D9: 焊接机侧推工装/定制 | E9: 定制 | F9: 个 | G9: =SUM(O9:P9) -> 0 | K9: =G9-I9 -> 0 | L9: =N9*K9 -> 0
A10: D0001 | B10: 工装类 | C10: 扭力检测仪 | D10: 扭力检测仪/- | F10: 个 | G10: =SUM(O10:P10) -> 0 | K10: =G10-I10 -> 0 | L10: =N10*K10 -> 0
A11: D0001 | B11: 工装类 | C11: 辅助工装 | D11: 橡胶件气动扩张钳/QDKZQ | G11: =SUM(O11:P11) -> 0 | K11: =G11-I11 -> 0 | L11: =N11*K11 -> 0
G12: =SUM(O12:P12) -> 0
K15: 合计 | L15: {=SUMPRODUCT(G4:G12,N4:N12)} -> 28622 | O15: {=SUMPRODUCT(O4:O10,$N$4:$N$10)/O19} -> 0.12484577 | P15: {=SUMPRODUCT(P4:P10,$N$4:$N$10)/P19} -> 0.017552239
K16: 单套成本 | L16: =L15/'项目评估汇总（昆山90%）'!E5 -> 0.14239801
N17: =项目专用模具!N12 -> 装车比 | O17: ='项目评估汇总（昆山90%）'!P35 -> 1 | P17: ='项目评估汇总（昆山90%）'!Q35 -> 1
M18: 第四页 | N18: =项目专用模具!N13 -> 总量纲 | O18: ='项目评估汇总（昆山90%）'!P36 -> 201000 | P18: ='项目评估汇总（昆山90%）'!Q36 -> 201000
N19: =项目专用模具!N14 -> 数量 | O19: =O17*O18 -> 201000 | P19: =P17*P18 -> 201000
M22: {=SUMPRODUCT(O15:P15,O17:P17)} -> 0.14239801

Sheet 研发费用 
A1: ='项目评估汇总（昆山90%）'!A1 -> 吉利P162大电池包高压 | F1: 金额单位：元
A2: 研发费用成本（不包含收费样线） | G2: 备 注
A3: 编号 | B3: 归属 | C3: 项目投资名称 | D3: 单位 | E3: 新增数量 | F3: 新增金额
A4: E0001 | B4: 研发费用类 | C4: 原 材 料
A5: E0002 | B5: 研发费用类 | C5: 手工样线 | F5: 59200
A6: E0003 | B6: 研发费用类 | C6: 试验样线/样品费用
A7: E0004 | B7: 研发费用类 | C7: 工 资
A8: E0005 | B8: 研发费用类 | C8: 差 旅 费 | F8: 4200
A9: E0006 | B9: 研发费用类 | C9: 交 际 费
A10: E0007 | B10: 研发费用类 | C10: 常规DVP测试 | F10: 500000
A11: E0008 | B11: 研发费用类 | C11: 实验费
A12: E0009 | B12: 研发费用类 | C12: 资讯设备费
A13: E0010 | B13: 研发费用类 | C13: 空运费
A14: E0011 | B14: 研发费用类 | C14: 气味实验
A15: E0011 | B15: 研发费用类 | C15: 管理费用 | G15: 28,170元,费用总金额*5%
A16: E0012 | B16: 研发费用类 | C16: 专利费
A17: E0013 | B17: 研发费用类 | C17: 场地租赁
E18: 合计 | F18: =SUM(F4:F17) -> 563400
E19: 单套成本 | F19: =F18/'项目评估汇总（昆山90%）'!E5 -> 2.8029851
F21: =F19/配置明细!P14 -> 0.10381426 | G21: 第五页

Sheet 包装物流费用
A1: ='项目评估汇总（昆山90%）'!A1 -> 吉利P162大电池包高压 | F1: 金额单位：元
A2: 包装物流成本明细
A3: 客户零件号 | B3: SAP号 | C3: 物料描述 | D3: 用量 | E3: 内包装 | F3: 外包装 | G3: 运费 | H3: 服务费 | I3: 短驳（合肥仓库到客户）+其他 | J3: 三方仓费用 | K3: 围板箱折叠费 | L3: 合计 | M3: 备注
A4: =配置明细!B3 -> 6608523073 | C4: =配置明细!D3 -> 组合式充电插座线束总成 | D4: =配置明细!E3 -> 1 | E4: 4.2566 | F4: 1.6951567 | G4: 5.4609 | J4: 4.75 | L4: =SUM(E4:K4) -> 16.162657
A5: =配置明细!B4 -> 6608523072 | C5: =配置明细!D4 -> 充电线束总成 | D5: =配置明细!E4 -> 1 | E5: 0.773478 | F5: 0.33903134 | G5: 0.72811999 | J5: 2.2333333 | L5: =SUM(E5:K5) -> 4.0739627
A14: 单套成本 | E14: {=SUMPRODUCT(E4:E13,$D$4:$D$13)} -> 5.030078 | F14: {=SUMPRODUCT(F4:F13,$D$4:$D$13)} -> 2.034188 | G14: {=SUMPRODUCT(G4:G13,$D$4:$D$13)} -> 6.18902 | H14: {=SUMPRODUCT(H4:H13,$D$4:$D$13)} -> 0 | I14: {=SUMPRODUCT(I4:I13,$D$4:$D$13)} -> 0 | J14: {=SUMPRODUCT(J4:J13,$D$4:$D$13)} -> 6.9833333 | K14: {=SUMPRODUCT(K4:K13,$D$4:$D$13)} -> 0 | L14: {=SUMPRODUCT(L4:L13,$D$4:$D$13)} -> 20.236619
H16: 第六页

Sheet 配置明细
A1: ='项目评估汇总（昆山90%）'!A1 -> 吉利P162大电池包高压
A2: 序号 | B2: 零件号 | C2: 零件号SAP号 | D2: 零件名称 | E2: 数量 | F2: 单位 | G2: 材料成本（元） | H2: VAVE后材料成本 | I2: 线束铜重（KG） | J2: 线束铝重（KG） | K2: 导线成本 （元） | L2: 开线工时（H） | M2: 公共制成工时（H） | N2: 后工程工时（H） | O2: JPH | P2: 回路数 | Q2: 前工程直接人力（双班） | R2: 前工程间接人力（双班） | S2: 后工程直接人力（双班） | T2: 后工程间接人力（双班） | U2: 项目前工程占用面积（㎡） | V2: 项目后工程占用面积（㎡） | W2: 占地面积/㎡
A3: 1 | B3: 6608523073 | D3: 组合式充电插座线束总成 | E3: 1 | F3: PC | G3: =SUMIFS('KSK线束BOM明细 '!U:U,'KSK线束BOM明细 '!A:A,B3) -> 296.27997 | M3: 0.639 | N3: 0.487 | O3: 12 | P3: 25
A4: 2 | B4: 6608523072 | D4: 充电线束总成 | E4: 1 | F4: PC | G4: =SUMIFS('KSK线束BOM明细 '!U:U,'KSK线束BOM明细 '!A:A,B4) -> 90.851159 | M4: 0.315 | N4: 0.157 | O4: 29.45 | P4: 2
B14: 合计 | G14: {=SUMPRODUCT(G3:G13,$E$3:$E$13)} -> 387.13113 | H14: {=SUMPRODUCT(H3:H13,$E$3:$E$13)} -> 0 | I14: {=SUMPRODUCT(I3:I13,$E$3:$E$13)} -> 0 | J14: {=SUMPRODUCT(J3:J13,$E$3:$E$13)} -> 0 | K14: {=SUMPRODUCT(K3:K13,$E$3:$E$13)} -> 0 | L14: {=SUMPRODUCT(L3:L13,$E$3:$E$13)} -> 0 | M14: {=SUMPRODUCT(M3:M13,$E$3:$E$13)} -> 0.954 | N14: {=SUMPRODUCT(N3:N13,$E$3:$E$13)} -> 0.644 | ... P14: {=SUMPRODUCT(P3:P13,$E$3:$E$13)} -> 27 | Q14: =SUMPRODUCT(Q3:Q13,$E$3:$E$13) -> 0 | R14: =SUMPRODUCT(R3:R13,$E$3:$E$13) -> 0 | S14: =SUMPRODUCT(S3:S13,$E$3:$E$13) -> 0 | T14: =SUMPRODUCT(T3:T13,$E$3:$E$13) -> 0 | U14: =SUMPRODUCT(U3:U13,$E$3:$E$13) -> 0 | V14: =SUMPRODUCT(V3:V13,$E$3:$E$13) -> 0 | W14: =SUMPRODUCT(W3:W13,$E$3:$E$13) -> 0
G16: 铜价 | I16: 69.43
G17: 材料中铜成本 | I17: =I14*I16 -> 0
G18: 材料中铝成本 | I18: =J14*18.21 -> 0
L19: 第七页

Sheet KSK线束BOM明细 
A1: 线束零件号 | B1: 零件名称 | C1: 零件号 | D1: 物料名称/零件名称 | E1: 是否半成品 | F1: 物料型号/SAP | I1: 回路 | J1: 数量 | K1: 单位 | L1: 供应商 | M1: 总成件号 | N1: 其他备注 | O1: 责任人 | P1: 单价 | Q1: 铝重 | R1: 铜重 | S1: 非铜 | T1: 导线单价 | U1: 材料成本 | V1: 币别 | W1: 价格类型 | X1: 备注
A2: 6608523073 | B2: 组合式充电插座线束总成 | C2: PP3241918 | D2: 法兰组件 | E2: N | J2: 1 | K2: PCS | L2: 天海 | M2: TC-GADC-125A1000V32A250V-0 10Y1 充电座 | N2: 客户指定 | O2: =IFERROR(VLOOKUP($C2,二次物料明细!$A:$N,COLUMN(二次物料明细!H$1),),0) -> 江苏林 | P2: =IFERROR(VLOOKUP($C2,二次物料明细!$A:$N,COLUMN(二次物料明细!I$1),),0) -> 170 | Q2: =IFERROR(VLOOKUP($C2,二次物料明细!$A:$N,COLUMN(二次物料明细!J$1),),0) -> 0 | R2: =IFERROR(VLOOKUP($C2,二次物料明细!$A:$N,COLUMN(二次物料明细!K$1),),0) -> 0 | S2: =IFERROR(VLOOKUP($C2,二次物料明细!$A:$N,COLUMN(二次物料明细!L$1),),0) -> 0 | T2: =(R2*90.11+Q2*21.24+S2)/1000 -> 0 | U2: =(P2+T2)*J2 -> 170 | V2: =IFERROR(VLOOKUP($C2,二次物料明细!$A:$N,COLUMN(二次物料明细!M$1),),0) -> 0 | W2: =IFERROR(VLOOKUP($C2,二次物料明细!$A:$N,COLUMN(二次物料明细!N$1),),0) -> 总成参考价-销售估价
A3: 6608523073 | B3: 组合式充电插座线束总成 | C3: PP3241190 | D3: 防尘盖组件 | E3: N | F3: A02102700 | J3: 1 | K3: PCS | L3: 天海 | N3: 客户指定 | O3: =IFERROR(VLOOKUP($C3,二次物料明细!$A:$N,COLUMN(二次物料明细!H$1),),0) -> 江苏林 | P3: =IFERROR(VLOOKUP($C3,二次物料明细!$A:$N,COLUMN(二次物料明细!I$1),),0) -> 0 | Q3: =IFERROR(VLOOKUP($C3,二次物料明细!$A:$N,COLUMN(二次物料明细!J$1),),0) -> 0 | R3: =IFERROR(VLOOKUP($C3,二次物料明细!$A:$N,COLUMN(二次物料明细!K$1),),0) -> 0 | S3: =IFERROR(VLOOKUP($C3,二次物料明细!$A:$N,COLUMN(二次物料明细!L$1),),0) -> 0 | T3: =(R3*90.11+Q3*21.24+S3)/1000 -> 0 | U3: =(P3+T3)*J3 -> 0 | V3: =IFERROR(VLOOKUP($C3,二次物料明细!$A:$N,COLUMN(二次物料明细!M$1),),0) -> CNY | W3: =IFERROR(VLOOKUP($C3,二次物料明细!$A:$N,COLUMN(二次物料明细!N$1),),0) -> 散件
A4: 6608523073 | B4: 组合式充电插座线束总成 | C4: PP3241410 | D4: 70平DC端子 | E4: N | F4: A03103099 | J4: 2 | K4: PCS | L4: 天海 | N4: 客户指定 | O4: =IFERROR(VLOOKUP($C4,二次物料明细!$A:$N,COLUMN(二次物料明细!H$1),),0) -> 江苏林 | P4: =IFERROR(VLOOKUP($C4,二次物料明细!$A:$N,COLUMN(二次物料明细!I$1),),0) -> 0 | Q4: =IFERROR(VLOOKUP($C4,二次物料明细!$A:$N,COLUMN(二次物料明细!J$1),),0) -> 0 | R4: =IFERROR(VLOOKUP($C4,二次物料明细!$A:$N,COLUMN(二次物料明细!K$1),),0) -> 0 | S4: =IFERROR(VLOOKUP($C4,二次物料明细!$A:$N,COLUMN(二次物料明细!L$1),),0) -> 0 | T4: =(R4*90.11+Q4*21.24+S4)/1000 -> 0 | U4: =(P4+T4)*J4 -> 0 | V4: =IFERROR(VLOOKUP($C4,二次物料明细!$A:$N,COLUMN(二次物料明细!M$1),),0) -> 0 | W4: =IFERROR(VLOOKUP($C4,二次物料明细!$A:$N,COLUMN(二次物料明细!N$1),),0) -> 散件
A5: 6608523073 | B5: 组合式充电插座线束总成 | C5: PP3241183 | D5: 50平DC尾盖 | E5: N | F5: A02104381 | J5: 2 | K5: PCS | L5: 天海 | N5: 客户指定 | O5: =IFERROR(VLOOKUP($C5,二次物料明细!$A:$N,COLUMN(二次物料明细!H$1),),0) -> 江苏林 | P5: =IFERROR(VLOOKUP($C5,二次物料明细!$A:$N,COLUMN(二次物料明细!I$1),),0) -> 0 | Q5: =IFERROR(VLOOKUP($C5,二次物料明细!$A:$N,COLUMN(二次物料明细!J$1),),0) -> 0 | R5: =IFERROR(VLOOKUP($C5,二次物料明细!$A:$N,COLUMN(二次物料明细!K$1),),0) -> 0 | S5: =IFERROR(VLOOKUP($C5,二次物料明细!$A:$N,COLUMN(二次物料明细!L$1),),0) -> 0 | T5: =(R5*90.11+Q5*21.24+S5)/1000 -> 0 | U5: =(P5+T5)*J5 -> 0 | V5: =IFERROR(VLOOKUP($C5,二次物料明细!$A:$N,COLUMN(二次物料明细!M$1),),0) -> 0 | W5: =IFERROR(VLOOKUP($C5,二次物料明细!$A:$N,COLUMN(二次物料明细!N$1),),0) -> 散件
A6: 6608523073 | B6: 组合式充电插座线束总成 | C6: PP3241184 | D6: 50平DC线塞 | E6: N | F6: A02104379 | J6: 2 | K6: PCS | L6: 天海 | N6: 客户指定 | O6: =IFERROR(VLOOKUP($C6,二次物料明细!$A:$N,COLUMN(二次物料明细!H$1),),0) -> 江苏林 | P6: =IFERROR(VLOOKUP($C6,二次物料明细!$A:$N,COLUMN(二次物料明细!I$1),),0) -> 0 | Q6: =IFERROR(VLOOKUP($C6,二次物料明细!$A:$N,COLUMN(二次物料明细!J$1),),0) -> 0 | R6: =IFERROR(VLOOKUP($C6,二次物料明细!$A:$N,COLUMN(二次物料明细!K$1),),0) -> 0 | S6: =IFERROR(VLOOKUP($C6,二次物料明细!$A:$N,COLUMN(二次物料明细!L$1),),0) -> 0 | T6: =(R6*90.11+Q6*21.24+S6)/1000 -> 0 | U6: =(P6+T6)*J6 -> 0 | V6: =IFERROR(VLOOKUP($C6,二次物料明细!$A:$N,COLUMN(二次物料明细!M$1),),0) -> 0 | W6: =IFERROR(VLOOKUP($C6,二次物料明细!$A:$N,COLUMN(二次物料明细!N$1),),0) -> 散件
A7: 6608523073 | B7: 组合式充电插座线束总成 | C7: PP3241319 | D7: PE端子 | E7: N | F7: A03101934 | J7: 1 | K7: PCS | L7: 天海 | N7: 客户指定 | O7: =IFERROR(VLOOKUP($C7,二次物料明细!$A:$N,COLUMN(二次物料明细!H$1),),0) -> 江苏林 | P7: =IFERROR(VLOOKUP($C7,二次物料明细!$A:$N,COLUMN(二次物料明细!I$1),),0) -> 0 | Q7: =IFERROR(VLOOKUP($C7,二次物料明细!$A:$N,COLUMN(二次物料明细!J$1),),0) -> 0 | R7: =IFERROR(VLOOKUP($C7,二次物料明细!$A:$N,COLUMN(二次物料明细!K$1),),0) -> 0 | S7: =IFERROR(VLOOKUP($C7,二次物料明细!$A:$N,COLUMN(二次物料明细!L$1),),0) -> 0 | T7: =(R7*90.11+Q7*21.24+S7)/1000 -> 0 | U7: =(P7+T7)*J7 -> 0 | V7: =IFERROR(VLOOKUP($C7,二次物料明细!$A:$N,COLUMN(二次物料明细!M$1),),0) -> CNY | W7: =IFERROR(VLOOKUP($C7,二次物料明细!$A:$N,COLUMN(二次物料明细!N$1),),0) -> 散件
A8: 6608523073 | B8: 组合式充电插座线束总成 | C8: PP3241115 | D8: PE胶圈 | E8: N | F8: A02102631 | J8: 1 | K8: PCS | L8: 天海 | N8: 客户指定 | O8: =IFERROR(VLOOKUP($C8,二次物料明细!$A:$N,COLUMN(二次物料明细!H$1),),0) -> 江苏林 | P8: =IFERROR(VLOOKUP($C8,二次物料明细!$A:$N,COLUMN(二次物料明细!I$1),),0) -> 0 | Q8: =IFERROR(VLOOKUP($C8,二次物料明细!$A:$N,COLUMN(二次物料明细!J$1),),0) -> 0 | R8: =IFERROR(VLOOKUP($C8,二次物料明细!$A:$N,COLUMN(二次物料明细!K$1),),0) -> 0 | S8: =IFERROR(VLOOKUP($C8,二次物料明细!$A:$N,COLUMN(二次物料明细!L$1),),0) -> 0 | T8: =(R8*90.11+Q8*21.24+S8)/1000 -> 0 | U8: =(P8+T8)*J8 -> 0 | V8: =IFERROR(VLOOKUP($C8,二次物料明细!$A:$N,COLUMN(二次物料明细!M$1),),0) -> CNY | W8: =IFERROR(VLOOKUP($C8,二次物料明细!$A:$N,COLUMN(二次物料明细!N$1),),0) -> 散件
A9: 6608523073 | B9: 组合式充电插座线束总成 | C9: PP3241195 | D9: 6平PE尾盖 | E9: N | F9: A02102630 | J9: 1 | K9: PCS | L9: 天海 | N9: 客户指定 | O9: =IFERROR(VLOOKUP($C9,二次物料明细!$A:$N,COLUMN(二次物料明细!H$1),),0) -> 江苏林 | P9: =IFERROR(VLOOKUP($C9,二次物料明细!$A:$N,COLUMN(二次物料明细!I$1),),0) -> 0 | Q9: =IFERROR(VLOOKUP($C9,二次物料明细!$A:$N,COLUMN(二次物料明细!J$1),),0) -> 0 | R9: =IFERROR(VLOOKUP($C9,二次物料明细!$A:$N,COLUMN(二次物料明细!K$1),),0) -> 0 | S9: =IFERROR(VLOOKUP($C9,二次物料明细!$A:$N,COLUMN(二次物料明细!L$1),),0) -> 0 | T9: =(R9*90.11+Q9*21.24+S9)/1000 -> 0 | U9: =(P9+T9)*J9 -> 0 | V9: =IFERROR(VLOOKUP($C9,二次物料明细!$A:$N,COLUMN(二次物料明细!M$1),),0) -> CNY | W9: =IFERROR(VLOOKUP($C9,二次物料明细!$A:$N,COLUMN(二次物料明细!N$1),),0) -> 散件
A10: 6608523073 | B10: 组合式充电插座线束总成 | C10: PP3241196 | D10: 6平PE线塞 | E10: N | F10: A02102629 | J10: 1 | K10: PCS | L10: 天海 | N10: 客户指定 | O10: =IFERROR(VLOOKUP($C10,二次物料明细!$A:$N,COLUMN(二次物料明细!H$1),),0) -> 江苏林 | P10: =IFERROR(VLOOKUP($C10,二次物料明细!$A:$N,COLUMN(二次物料明细!I$1),),0) -> 0 | Q10: =IFERROR(VLOOKUP($C10,二次物料明细!$A:$N,COLUMN(二次物料明细!J$1),),0) -> 0 | R10: =IFERROR(VLOOKUP($C10,二次物料明细!$A:$N,COLUMN(二次物料明细!K$1),),0) -> 0 | S10: =IFERROR(VLOOKUP($C10,二次物料明细!$A:$N,COLUMN(二次物料明细!L$1),),0) -> 0 | T10: =(R10*90.11+Q10*21.24+S10)/1000 -> 0 | U10: =(P10+T10)*J10 -> 0 | V10: =IFERROR(VLOOKUP($C10,二次物料明细!$A:$N,COLUMN(二次物料明细!M$1),),0) -> CNY | W10: =IFERROR(VLOOKUP($C10,二次物料明细!$A:$N,COLUMN(二次物料明细!N$1),),0) -> 散件
A11: 6608523073 | B11: 组合式充电插座线束总成 | C11: PP3241175 | D11: 5平AC线塞 | E11: N | F11: A02104380 | J11: 1 | K11: PCS | L11: 天海 | N11: 客户指定 | O11: =IFERROR(VLOOKUP($C11,二次物料明细!$A:$N,COLUMN(二次物料明细!H$1),),0) -> 江苏林 | P11: =IFERROR(VLOOKUP($C11,二次物料明细!$A:$N,COLUMN(二次物料明细!I$1),),0) -> 0 | Q11: =IFERROR(VLOOKUP($C11,二次物料明细!$A:$N,COLUMN(二次物料明细!J$1),),0) -> 0 | R11: =IFERROR(VLOOKUP($C11,二次物料明细!$A:$N,COLUMN(二次物料明细!K$1),),0) -> 0 | S11: =IFERROR(VLOOKUP($C11,二次物料明细!$A:$N,COLUMN(二次物料明细!L$1),),0) -> 0 | T11: =(R11*90.11+Q11*21.24+S11)/1000 -> 0 | U11: =(P11+T11)*J11 -> 0 | V11: =IFERROR(VLOOKUP($C11,二次物料明细!$A:$N,COLUMN(二次物料明细!M$1),),0) -> 0 | W11: =IFERROR(VLOOKUP($C11,二次物料明细!$A:$N,COLUMN(二次物料明细!N$1),),0) -> 散件
A12: 6608523073 | B12: 组合式充电插座线束总成 | C12: PP3241174 | D12: 5平AC小尾盖 | E12: N | F12: A02104378 | J12: 1 | K12: PCS | L12: 天海 | N12: 客户指定 | O12: =IFERROR(VLOOKUP($C12,二次物料明细!$A:$N,COLUMN(二次物料明细!H$1),),0) -> 江苏林 | P12: =IFERROR(VLOOKUP($C12,二次物料明细!$A:$N,COLUMN(二次物料明细!I$1),),0) -> 0 | Q12: =IFERROR(VLOOKUP($C12,二次物料明细!$A:$N,COLUMN(二次物料明细!J$1),),0) -> 0 | R12: =IFERROR(VLOOKUP($C12,二次物料明细!$A:$N,COLUMN(二次物料明细!K$1),),0) -> 0 | S12: =IFERROR(VLOOKUP($C12,二次物料明细!$A:$N,COLUMN(二次物料明细!L$1),),0) -> 0 | T12: =(R12*90.11+Q12*21.24+S12)/1000 -> 0 | U12: =(P12+T12)*J12 -> 0 | V12: =IFERROR(VLOOKUP($C12,二次物料明细!$A:$N,COLUMN(二次物料明细!M$1),),0) -> 0 | W12: =IFERROR(VLOOKUP($C12,二次物料明细!$A:$N,COLUMN(二次物料明细!N$1),),0) -> 散件
A13: 6608523073 | B13: 组合式充电插座线束总成 | C13: PP3241321 | D13: 6平功率插孔 | E13: N | F13: A03101936 | J13: 3 | K13: PCS | L13: 天海 | N13: 客户指定 | O13: =IFERROR(VLOOKUP($C13,二次物料明细!$A:$N,COLUMN(二次物料明细!H$1),),0) -> 江苏林 | P13: =IFERROR(VLOOKUP($C13,二次物料明细!$A:$N,COLUMN(二次物料明细!I$1),),0) -> 0 | Q13: =IFERROR(VLOOKUP($C13,二次物料明细!$A:$N,COLUMN(二次物料明细!J$1),),0) -> 0 | R13: =IFERROR(VLOOKUP($C13,二次物料明细!$A:$N,COLUMN(二次物料明细!K$1),),0) -> 0 | S13: =IFERROR(VLOOKUP($C13,二次物料明细!$A:$N,COLUMN(二次物料明细!L$1),),0) -> 0 | T13: =(R13*90.11+Q13*21.24+S13)/1000 -> 0 | U13: =(P13+T13)*J13 -> 0 | V13: =IFERROR(VLOOKUP($C13,二次物料明细!$A:$N,COLUMN(二次物料明细!M$1),),0) -> CNY | W13: =IFERROR(VLOOKUP($C13,二次物料明细!$A:$N,COLUMN(二次物料明细!N$1),),0) -> 散件
A14: 6608523073 | B14: 组合式充电插座线束总成 | C14: PP3241117 | D14: 6mm功率胶圈 | E14: N | F14: A02102708 | J14: 3 | K14: PCS | L14: 天海 | N14: 客户指定 | O14: =IFERROR(VLOOKUP($C14,二次物料明细!$A:$N,COLUMN(二次物料明细!H$1),),0) -> 江苏林 | P14: =IFERROR(VLOOKUP($C14,二次物料明细!$A:$N,COLUMN(二次物料明细!I$1),),0) -> 0 | Q14: =IFERROR(VLOOKUP($C14,二次物料明细!$A:$N,COLUMN(二次物料明细!J$1),),0) -> 0 | R14: =IFERROR(VLOOKUP($C14,二次物料明细!$A:$N,COLUMN(二次物料明细!K$1),),0) -> 0 | S14: =IFERROR(VLOOKUP($C14,二次物料明细!$A:$N,COLUMN(二次物料明细!L$1),),0) -> 0 | T14: =(R14*90.11+Q14*21.24+S14)/1000 -> 0 | U14: =(P14+T14)*J14 -> 0 | V14: =IFERROR(VLOOKUP($C14,二次物料明细!$A:$N,COLUMN(二次物料明细!M$1),),0) -> CNY | W14: =IFERROR(VLOOKUP($C14,二次物料明细!$A:$N,COLUMN(二次物料明细!N$1),),0) -> 散件
A15: 6608523073 | B15: 组合式充电插座线束总成 | C15: M21009005 | D15: P161电子锁 | E15: N | J15: 1 | K15: PCS | L15: 天海 | N15: 客户指定 | O15: =IFERROR(VLOOKUP($C15,二次物料明细!$A:$N,COLUMN(二次物料明细!H$1),),0) -> 江苏林 | P15: =IFERROR(VLOOKUP($C15,二次物料明细!$A:$N,COLUMN(二次物料明细!I$1),),0) -> 0 | Q15: =IFERROR(VLOOKUP($C15,二次物料明细!$A:$N,COLUMN(二次物料明细!J$1),),0) -> 0 | R15: =IFERROR(VLOOKUP($C15,二次物料明细!$A:$N,COLUMN(二次物料明细!K$1),),0) -> 0 | S15: =IFERROR(VLOOKUP($C15,二次物料明细!$A:$N,COLUMN(二次物料明细!L$1),),0) -> 0 | T15: =(R15*90.11+Q15*21.24+S15)/1000 -> 0 | U15: =(P15+T15)*J15 -> 0 | V15: =IFERROR(VLOOKUP($C15,二次物料明细!$A:$N,COLUMN(二次物料明细!M$1),),0) -> 0 | W15: =IFERROR(VLOOKUP($C15,二次物料明细!$A:$N,COLUMN(二次物料明细!N$1),),0) -> 散件
A16: 6608523073 | B16: 组合式充电插座线束总成 | C16: M93000476 | D16: ST2.9*16 | E16: N | F16: A07100113 | J16: 2 | K16: PCS | L16: 天海 | N16: 客户指定 | O16: =IFERROR(VLOOKUP($C16,二次物料明细!$A:$N,COLUMN(二次物料明细!H$1),),0) -> 江苏林 | P16: =IFERROR(VLOOKUP($C16,二次物料明细!$A:$N,COLUMN(二次物料明细!I$1),),0) -> 0 | Q16: =IFERROR(VLOOKUP($C16,二次物料明细!$A:$N,COLUMN(二次物料明细!J$1),),0) -> 0 | R16: =IFERROR(VLOOKUP($C16,二次物料明细!$A:$N,COLUMN(二次物料明细!K$1),),0) -> 0 | S16: =IFERROR(VLOOKUP($C16,二次物料明细!$A:$N,COLUMN(二次物料明细!L$1),),0) -> 0 | T16: =(R16*90.11+Q16*21.24+S16)/1000 -> 0 | U16: =(P16+T16)*J16 -> 0 | V16: =IFERROR(VLOOKUP($C16,二次物料明细!$A:$N,COLUMN(二次物料明细!M$1),),0) -> 0 | W16: =IFERROR(VLOOKUP($C16,二次物料明细!$A:$N,COLUMN(二次物料明细!N$1),),0) -> 散件
A17: 6608523073 | B17: 组合式充电插座线束总成 | C17: HVPC2P1600FE6-NH-MP010 | D17: 护套塑壳 | E17: N | F17: A02104377 | J17: 1 | K17: PCS | L17: 安费诺 | M17: HVSPC2P1600FE650-NH-P010 50mm²单芯非屏蔽硅胶铝导线 直流接ODP端 | N17: 客户指定 | O17: =IFERROR(VLOOKUP($C17,二次物料明细!$A:$N,COLUMN(二次物料明细!H$1),),0) -> 胡继燕 | P17: =IFERROR(VLOOKUP($C17,二次物料明细!$A:$N,COLUMN(二次物料明细!I$1),),0) -> 24 | Q17: =IFERROR(VLOOKUP($C17,二次物料明细!$A:$N,COLUMN(二次物料明细!J$1),),0) -> 0 | R17: =IFERROR(VLOOKUP($C17,二次物料明细!$A:$N,COLUMN(二次物料明细!K$1),),0) -> 0 | S17: =IFERROR(VLOOKUP($C17,二次物料明细!$A:$N,COLUMN(二次物料明细!L$1),),0) -> 0 | T17: =(R17*90.11+Q17*21.24+S17)/1000 -> 0 | U17: =(P17+T17)*J17 -> 24 | V17: =IFERROR(VLOOKUP($C17,二次物料明细!$A:$N,COLUMN(二次物料明细!M$1),),0) -> 0 | W17: =IFERROR(VLOOKUP($C17,二次物料明细!$A:$N,COLUMN(二次物料明细!N$1),),0) -> 总成参考价
A18: 6608523073 | B18: 组合式充电插座线束总成 | C18: HVPC2P1600FE-05P010 | D18: 焊接端子 | E18: N | F18: A03103097 | J18: 2 | K18: PCS | L18: 安费诺 | N18: 客户指定 | O18: =IFERROR(VLOOKUP($C18,二次物料明细!$A:$N,COLUMN(二次物料明细!H$1),),0) -> 胡继燕 | P18: =IFERROR(VLOOKUP($C18,二次物料明细!$A:$N,COLUMN(二次物料明细!I$1),),0) -> 0 | Q18: =IFERROR(VLOOKUP($C18,二次物料明细!$A:$N,COLUMN(二次物料明细!J$1),),0) -> 0 | R18: =IFERROR(VLOOKUP($C18,二次物料明细!$A:$N,COLUMN(二次物料明细!K$1),),0) -> 0 | S18: =IFERROR(VLOOKUP($C18,二次物料明细!$A:$N,COLUMN(二次物料明细!L$1),),0) -> 0 | T18: =(R18*90.11+Q18*21.24+S18)/1000 -> 0 | U18: =(P18+T18)*J18 -> 0 | V18: =IFERROR(VLOOKUP($C18,二次物料明细!$A:$N,COLUMN(二次物料明细!M$1),),0) -> 0 | W18: =IFERROR(VLOOKUP($C18,二次物料明细!$A:$N,COLUMN(二次物料明细!N$1),),0) -> 散件
A19: 6608523073 | B19: 组合式充电插座线束总成 | C19: HVPC2P1600FV-15P010 | D19: 挡板 | E19: N | F19: A02104375 | J19: 2 | K19: PCS | L19: 安费诺 | N19: 客户指定 | O19: =IFERROR(VLOOKUP($C19,二次物料明细!$A:$N,COLUMN(二次物料明细!H$1),),0) -> 胡继燕 | P19: =IFERROR(VLOOKUP($C19,二次物料明细!$A:$N,COLUMN(二次物料明细!I$1),),0) -> 0 | Q19: =IFERROR(VLOOKUP($C19,二次物料明细!$A:$N,COLUMN(二次物料明细!J$1),),0) -> 0 | R19: =IFERROR(VLOOKUP($C19,二次物料明细!$A:$N,COLUMN(二次物料明细!K$1),),0) -> 0 | S19: =IFERROR(VLOOKUP($C19,二次物料明细!$A:$N,COLUMN(二次物料明细!L$1),),0) -> 0 | T19: =(R19*90.11+Q19*21.24+S19)/1000 -> 0 | U19: =(P19+T19)*J19 -> 0 | V19: =IFERROR(VLOOKUP($C19,二次物料明细!$A:$N,COLUMN(二次物料明细!M$1),),0) -> 0 | W19: =IFERROR(VLOOKUP($C19,二次物料明细!$A:$N,COLUMN(二次物料明细!N$1),),0) -> 散件
A20: 6608523073 | B20: 组合式充电插座线束总成 | C20: HVSPC2P1600FV-12-50P010 | D20: 插头线束密封圈 | E20: N | F20: A02104376 | J20: 2 | K20: PCS | L20: 安费诺 | N20: 客户指定 | O20: =IFERROR(VLOOKUP($C20,二次物料明细!$A:$N,COLUMN(二次物料明细!H$1),),0) -> 胡继燕 | P20: =IFERROR(VLOOKUP($C20,二次物料明细!$A:$N,COLUMN(二次物料明细!I$1),),0) -> 0 | Q20: =IFERROR(VLOOKUP($C20,二次物料明细!$A:$N,COLUMN(二次物料明细!J$1),),0) -> 0 | R20: =IFERROR(VLOOKUP($C20,二次物料明细!$A:$N,COLUMN(二次物料明细!K$1),),0) -> 0 | S20: =IFERROR(VLOOKUP($C20,二次物料明细!$A:$N,COLUMN(二次物料明细!L$1),),0) -> 0 | T20: =(R20*90.11+Q20*21.24+S20)/1000 -> 0 | U20: =(P20+T20)*J20 -> 0 | V20: =IFERROR(VLOOKUP($C20,二次物料明细!$A:$N,COLUMN(二次物料明细!M$1),),0) -> 0 | W20: =IFERROR(VLOOKUP($C20,二次物料明细!$A:$N,COLUMN(二次物料明细!N$1),),0) -> 散件
A21: 6608523073 | B21: 组合式充电插座线束总成 | C21: HVSPC2P1600FV-11-50P010 | D21: 插头线卡 | E21: N | F21: A02104374 | J21: 2 | K21: PCS | L21: 安费诺 | N21: 客户指定 | O21: =IFERROR(VLOOKUP($C21,二次物料明细!$A:$N,COLUMN(二次物料明细!H$1),),0) -> 胡继燕 | P21: =IFERROR(VLOOKUP($C21,二次物料明细!$A:$N,COLUMN(二次物料明细!I$1),),0) -> 0 | Q21: =IFERROR(VLOOKUP($C21,二次物料明细!$A:$N,COLUMN(二次物料明细!J$1),),0) -> 0 | R21: =IFERROR(VLOOKUP($C21,二次物料明细!$A:$N,COLUMN(二次物料明细!K$1),),0) -> 0 | S21: =IFERROR(VLOOKUP($C21,二次物料明细!$A:$N,COLUMN(二次物料明细!L$1),),0) -> 0 | T21: =(R21*90.11+Q21*21.24+S21)/1000 -> 0 | U21: =(P21+T21)*J21 -> 0 | V21: =IFERROR(VLOOKUP($C21,二次物料明细!$A:$N,COLUMN(二次物料明细!M$1),),0) -> 0 | W21: =IFERROR(VLOOKUP($C21,二次物料明细!$A:$N,COLUMN(二次物料明细!N$1),),0) -> 散件
A22: 6608523073 | B22: 组合式充电插座线束总成 | C22: HVSPC2P1600FV-10-50P010 | D22: 插头尾盖 | E22: N | F22: A02104373 | J22: 2 | K22: PCS | L22: 安费诺 | N22: 客户指定 | O22: =IFERROR(VLOOKUP($C22,二次物料明细!$A:$N,COLUMN(二次物料明细!H$1),),0) -> 胡继燕 | P22: =IFERROR(VLOOKUP($C22,二次物料明细!$A:$N,COLUMN(二次物料明细!I$1),),0) -> 0 | Q22: =IFERROR(VLOOKUP($C22,二次物料明细!$A:$N,COLUMN(二次物料明细!J$1),),0) -> 0 | R22: =IFERROR(VLOOKUP($C22,二次物料明细!$A:$N,COLUMN(二次物料明细!K$1),),0) -> 0 | S22: =IFERROR(VLOOKUP($C22,二次物料明细!$A:$N,COLUMN(二次物料明细!L$1),),0) -> 0 | T22: =(R22*90.11+Q22*21.24+S22)/1000 -> 0 | U22: =(P22+T22)*J22 -> 0 | V22: =IFERROR(VLOOKUP($C22,二次物料明细!$A:$N,COLUMN(二次物料明细!M$1),),0) -> 0 | W22: =IFERROR(VLOOKUP($C22,二次物料明细!$A:$N,COLUMN(二次物料明细!N$1),),0) -> 散件
A23: 6608523073 | B23: 组合式充电插座线束总成 | C23: HVC2PG263UFSW106-NH-P010 | D23: 高压线束总成 | E23: N | J23: 1 | K23: SET | L23: 安费诺 | M23: HVC2PG263UFSW106-NH-P010 6mm²高压非屏蔽交联铝线 交流接ODP端 | N23: 客户指定 | O23: =IFERROR(VLOOKUP($C23,二次物料明细!$A:$N,COLUMN(二次物料明细!H$1),),0) -> 胡继燕 | P23: =IFERROR(VLOOKUP($C23,二次物料明细!$A:$N,COLUMN(二次物料明细!I$1),),0) -> 10 | Q23: =IFERROR(VLOOKUP($C23,二次物料明细!$A:$N,COLUMN(二次物料明细!J$1),),0) -> 0 | R23: =IFERROR(VLOOKUP($C23,二次物料明细!$A:$N,COLUMN(二次物料明细!K$1),),0) -> 0 | S23: =IFERROR(VLOOKUP($C23,二次物料明细!$A:$N,COLUMN(二次物料明细!L$1),),0) -> 0 | T23: =(R23*90.11+Q23*21.24+S23)/1000 -> 0 | U23: =(P23+T23)*J23 -> 10 | V23: =IFERROR(VLOOKUP($C23,二次物料明细!$A:$N,COLUMN(二次物料明细!M$1),),0) -> 0 | W23: =IFERROR(VLOOKUP($C23,二次物料明细!$A:$N,COLUMN(二次物料明细!N$1),),0) -> 总成参考价
A24: 6608523073 | B24: 组合式充电插座线束总成 | C24: 5-2385463-1 | D24: 护套塑壳 | E24: N | F24: A02101947 | J24: 1 | K24: PCS | L24: TE | M24: 5-2385463-1 0.5mm²低压线 接整车低压线束 | N24: 客户指定 | O24: =IFERROR(VLOOKUP($C24,二次物料明细!$A:$N,COLUMN(二次物料明细!H$1),),0) -> 洪巧明 | P24: =IFERROR(VLOOKUP($C24,二次物料明细!$A:$N,COLUMN(二次物料明细!I$1),),0) -> 1.5 | Q24: =IFERROR(VLOOKUP($C24,二次物料明细!$A:$N,COLUMN(二次物料明细!J$1),),0) -> 0 | R24: =IFERROR(VLOOKUP($C24,二次物料明细!$A:$N,COLUMN(二次物料明细!K$1),),0) -> 0 | S24: =IFERROR(VLOOKUP($C24,二次物料明细!$A:$N,COLUMN(二次物料明细!L$1),),0) -> 0 | T24: =(R24*90.11+Q24*21.24+S24)/1000 -> 0 | U24: =(P24+T24)*J24 -> 1.5 | V24: =IFERROR(VLOOKUP($C24,二次物料明细!$A:$N,COLUMN(二次物料明细!M$1),),0) -> CNY | W24: =IFERROR(VLOOKUP($C24,二次物料明细!$A:$N,COLUMN(二次物料明细!N$1),),0) -> 系统价
A25: 6608523073 | B25: 组合式充电插座线束总成 | C25: 2377023-2 | D25: 压接端子 | E25: N | F25: A03033091 | J25: 17 | K25: PCS | L25: TE | N25: 客户指定 | O25: =IFERROR(VLOOKUP($C25,二次物料明细!$A:$N,COLUMN(二次物料明细!H$1),),0) -> 洪巧明 | P25: =IFERROR(VLOOKUP($C25,二次物料明细!$A:$N,COLUMN(二次物料明细!I$1),),0) -> 0.06 | Q25: =IFERROR(VLOOKUP($C25,二次物料明细!$A:$N,COLUMN(二次物料明细!J$1),),0) -> 0 | R25: =IFERROR(VLOOKUP($C25,二次物料明细!$A:$N,COLUMN(二次物料明细!K$1),),0) -> 0 | S25: =IFERROR(VLOOKUP($C25,二次物料明细!$A:$N,COLUMN(二次物料明细!L$1),),0) -> 0 | T25: =(R25*90.11+Q25*21.24+S25)/1000 -> 0 | U25: =(P25+T25)*J25 -> 1.02 | V25: =IFERROR(VLOOKUP($C25,二次物料明细!$A:$N,COLUMN(二次物料明细!M$1),),0) -> CNY | W25: =IFERROR(VLOOKUP($C25,二次物料明细!$A:$N,COLUMN(二次物料明细!N$1),),0) -> 系统价
A26: 6608523073 | B26: 组合式充电插座线束总成 | C26: 2377665-4 | D26: 密封塞 | E26: N | F26: A03033097 | J26: 17 | K26: PCS | L26: TE | N26: 客户指定 | O26: =IFERROR(VLOOKUP($C26,二次物料明细!$A:$N,COLUMN(二次物料明细!H$1),),0) -> 洪巧明 | P26: =IFERROR(VLOOKUP($C26,二次物料明细!$A:$N,COLUMN(二次物料明细!I$1),),0) -> 0.055 | Q26: =IFERROR(VLOOKUP($C26,二次物料明细!$A:$N,COLUMN(二次物料明细!J$1),),0) -> 0 | R26: =IFERROR(VLOOKUP($C26,二次物料明细!$A:$N,COLUMN(二次物料明细!K$1),),0) -> 0 | S26: =IFERROR(VLOOKUP($C26,二次物料明细!$A:$N,COLUMN(二次物料明细!L$1),),0) -> 0 | T26: =(R26*90.11+Q26*21.24+S26)/1000 -> 0 | U26: =(P26+T26)*J26 -> 0.935 | V26: =IFERROR(VLOOKUP($C26,二次物料明细!$A:$N,COLUMN(二次物料明细!M$1),),0) -> CNY | W26: =IFERROR(VLOOKUP($C26,二次物料明细!$A:$N,COLUMN(二次物料明细!N$1),),0) -> 系统价
A27: 6608523073 | B27: 组合式充电插座线束总成 | C27: 2377665-3 | D27: 小盲堵 | E27: N | F27: A02034386 | J27: 1 | K27: PCS | L27: TE | N27: 客户指定 | O27: =IFERROR(VLOOKUP($C27,二次物料明细!$A:$N,COLUMN(二次物料明细!H$1),),0) -> 洪巧明 | P27: =IFERROR(VLOOKUP($C27,二次物料明细!$A:$N,COLUMN(二次物料明细!I$1),),0) -> 0.045 | Q27: =IFERROR(VLOOKUP($C27,二次物料明细!$A:$N,COLUMN(二次物料明细!J$1),),0) -> 0 | R27: =IFERROR(VLOOKUP($C27,二次物料明细!$A:$N,COLUMN(二次物料明细!K$1),),0) -> 0 | S27: =IFERROR(VLOOKUP($C27,二次物料明细!$A:$N,COLUMN(二次物料明细!L$1),),0) -> 0 | T27: =(R27*90.11+Q27*21.24+S27)/1000 -> 0 | U27: =(P27+T27)*J27 -> 0.045 | V27: =IFERROR(VLOOKUP($C27,二次物料明细!$A:$N,COLUMN(二次物料明细!M$1),),0) -> CNY | W27: =IFERROR(VLOOKUP($C27,二次物料明细!$A:$N,COLUMN(二次物料明细!N$1),),0) -> 系统价
A28: 6608523073 | B28: 组合式充电插座线束总成 | C28: 963143-1 | D28: 大盲堵（1、8、15、22） | E28: N | F28: A02031363 | J28: 4 | K28: PCS | L28: TE | N28: 客户指定 | O28: =IFERROR(VLOOKUP($C28,二次物料明细!$A:$N,COLUMN(二次物料明细!H$1),),0) -> 洪巧明 | P28: =IFERROR(VLOOKUP($C28,二次物料明细!$A:$N,COLUMN(二次物料明细!I$1),),0) -> 0.182 | Q28: =IFERROR(VLOOKUP($C28,二次物料明细!$A:$N,COLUMN(二次物料明细!J$1),),0) -> 0 | R28: =IFERROR(VLOOKUP($C28,二次物料明细!$A:$N,COLUMN(二次物料明细!K$1),),0) -> 0 | S28: =IFERROR(VLOOKUP($C28,二次物料明细!$A:$N,COLUMN(二次物料明细!L$1),),0) -> 0 | T28: =(R28*90.11+Q28*21.24+S28)/1000 -> 0 | U28: =(P28+T28)*J28 -> 0.728 | V28: =IFERROR(VLOOKUP($C28,二次物料明细!$A:$N,COLUMN(二次物料明细!M$1),),0) -> CNY | W28: =IFERROR(VLOOKUP($C28,二次物料明细!$A:$N,COLUMN(二次物料明细!N$1),),0) -> 系统价
A29: 6608523073 | B29: 组合式充电插座线束总成 | C29: BH4311701 | D29: 卡花 | E29: N | F29: A06004040 | J29: 1 | K29: PCS | L29: 博昊 | N29: ★ | O29: =IFERROR(VLOOKUP($C29,二次物料明细!$A:$N,COLUMN(二次物料明细!H$1),),0) -> 邹娇 | P29: =IFERROR(VLOOKUP($C29,二次物料明细!$A:$N,COLUMN(二次物料明细!I$1),),0) -> 0.1 | Q29: =IFERROR(VLOOKUP($C29,二次物料明细!$A:$N,COLUMN(二次物料明细!J$1),),0) -> 0 | R29: =IFERROR(VLOOKUP($C29,二次物料明细!$A:$N,COLUMN(二次物料明细!K$1),),0) -> 0 | S29: =IFERROR(VLOOKUP($C29,二次物料明细!$A:$N,COLUMN(二次物料明细!L$1),),0) -> 0 | T29: =(R29*90.11+Q29*21.24+S29)/1000 -> 0 | U29: =(P29+T29)*J29 -> 0.1 | V29: =IFERROR(VLOOKUP($C29,二次物料明细!$A:$N,COLUMN(二次物料明细!M$1),),0) -> CNY | W29: =IFERROR(VLOOKUP($C29,二次物料明细!$A:$N,COLUMN(二次物料明细!N$1),),0) -> 系统价
A30: 6608523073 | B30: 组合式充电插座线束总成 | C30: PP6509712 | D30: 护套 | E30: N | F30: A02102696 | J30: 1 | K30: PCS | L30: 天海 | M30: DMS120LL-10P-10TA 0.5mm²低压线 接直流充电座 | N30: 客户指定 | O30: =IFERROR(VLOOKUP($C30,二次物料明细!$A:$N,COLUMN(二次物料明细!H$1),),0) -> 江苏林 | P30: =IFERROR(VLOOKUP($C30,二次物料明细!$A:$N,COLUMN(二次物料明细!I$1),),0) -> 3.3 | Q30: =IFERROR(VLOOKUP($C30,二次物料明细!$A:$N,COLUMN(二次物料明细!J$1),),0) -> 0 | R30: =IFERROR(VLOOKUP($C30,二次物料明细!$A:$N,COLUMN(二次物料明细!K$1),),0) -> 0 | S30: =IFERROR(VLOOKUP($C30,二次物料明细!$A:$N,COLUMN(二次物料明细!L$1),),0) -> 0 | T30: =(R30*90.11+Q30*21.24+S30)/1000 -> 0 | U30: =(P30+T30)*J30 -> 3.3 | V30: =IFERROR(VLOOKUP($C30,二次物料明细!$A:$N,COLUMN(二次物料明细!M$1),),0) -> CNY | W30: =IFERROR(VLOOKUP($C30,二次物料明细!$A:$N,COLUMN(二次物料明细!N$1),),0) -> 系统价
A31: 6608523073 | B31: 组合式充电插座线束总成 | C31: PP0147015 | D31: 端子 | E31: N | F31: A03101977 | J31: 9 | K31: PCS | L31: 天海 | N31: 客户指定 | O31: =IFERROR(VLOOKUP($C31,二次物料明细!$A:$N,COLUMN(二次物料明细!H$1),),0) -> 江苏林 | P31: =IFERROR(VLOOKUP($C31,二次物料明细!$A:$N,COLUMN(二次物料明细!I$1),),0) -> 0.15 | Q31: =IFERROR(VLOOKUP($C31,二次物料明细!$A:$N,COLUMN(二次物料明细!J$1),),0) -> 0 | R31: =IFERROR(VLOOKUP($C31,二次物料明细!$A:$N,COLUMN(二次物料明细!K$1),),0) -> 0 | S31: =IFERROR(VLOOKUP($C31,二次物料明细!$A:$N,COLUMN(二次物料明细!L$1),),0) -> 0 | T31: =(R31*90.11+Q31*21.24+S31)/1000 -> 0 | U31: =(P31+T31)*J31 -> 1.35 | V31: =IFERROR(VLOOKUP($C31,二次物料明细!$A:$N,COLUMN(二次物料明细!M$1),),0) -> CNY | W31: =IFERROR(VLOOKUP($C31,二次物料明细!$A:$N,COLUMN(二次物料明细!N$1),),0) -> 系统价
A32: 6608523073 | B32: 组合式充电插座线束总成 | C32: PP1509507 | D32: 密封堵 | E32: N | F32: A03031595 | J32: 9 | K32: PCS | L32: 天海 | N32: 客户指定 | O32: =IFERROR(VLOOKUP($C32,二次物料明细!$A:$N,COLUMN(二次物料明细!H$1),),0) -> 江苏林 | P32: =IFERROR(VLOOKUP($C32,二次物料明细!$A:$N,COLUMN(二次物料明细!I$1),),0) -> 0.085 | Q32: =IFERROR(VLOOKUP($C32,二次物料明细!$A:$N,COLUMN(二次物料明细!J$1),),0) -> 0 | R32: =IFERROR(VLOOKUP($C32,二次物料明细!$A:$N,COLUMN(二次物料明细!K$1),),0) -> 0 | S32: =IFERROR(VLOOKUP($C32,二次物料明细!$A:$N,COLUMN(二次物料明细!L$1),),0) -> 0 | T32: =(R32*90.11+Q32*21.24+S32)/1000 -> 0 | U32: =(P32+T32)*J32 -> 0.765 | V32: =IFERROR(VLOOKUP($C32,二次物料明细!$A:$N,COLUMN(二次物料明细!M$1),),0) -> CNY | W32: =IFERROR(VLOOKUP($C32,二次物料明细!$A:$N,COLUMN(二次物料明细!N$1),),0) -> 系统价
A33: 6608523073 | B33: 组合式充电插座线束总成 | C33: PP1509508 | D33: 密封堵 | E33: N | F33: A02031968 | J33: 1 | K33: PCS | L33: 天海 | N33: 客户指定 | O33: =IFERROR(VLOOKUP($C33,二次物料明细!$A:$N,COLUMN(二次物料明细!H$1),),0) -> 江苏林 | P33: =IFERROR(VLOOKUP($C33,二次物料明细!$A:$N,COLUMN(二次物料明细!I$1),),0) -> 0.1 | Q33: =IFERROR(VLOOKUP($C33,二次物料明细!$A:$N,COLUMN(二次物料明细!J$1),),0) -> 0 | R33: =IFERROR(VLOOKUP($C33,二次物料明细!$A:$N,COLUMN(二次物料明细!K$1),),0) -> 0 | S33: =IFERROR(VLOOKUP($C33,二次物料明细!$A:$N,COLUMN(二次物料明细!L$1),),0) -> 0 | T33: =(R33*90.11+Q33*21.24+S33)/1000 -> 0 | U33: =(P33+T33)*J33 -> 0.1 | V33: =IFERROR(VLOOKUP($C33,二次物料明细!$A:$N,COLUMN(二次物料明细!M$1),),0) -> CNY | W33: =IFERROR(VLOOKUP($C33,二次物料明细!$A:$N,COLUMN(二次物料明细!N$1),),0) -> 系统价
A34: 6608523073 | B34: 组合式充电插座线束总成 | C34: PP6507901 | D34: 护套 | E34: N | F34: A02102644 | J34: 1 | K34: PCS | L34: 天海 | M34: DMS120LL-6P-6TA 0.5mm²低压线 接交流充电座 | N34: 客户指定 | O34: =IFERROR(VLOOKUP($C34,二次物料明细!$A:$N,COLUMN(二次物料明细!H$1),),0) -> 江苏林 | P34: =IFERROR(VLOOKUP($C34,二次物料明细!$A:$N,COLUMN(二次物料明细!I$1),),0) -> 1.39 | Q34: =IFERROR(VLOOKUP($C34,二次物料明细!$A:$N,COLUMN(二次物料明细!J$1),),0) -> 0 | R34: =IFERROR(VLOOKUP($C34,二次物料明细!$A:$N,COLUMN(二次物料明细!K$1),),0) -> 0 | S34: =IFERROR(VLOOKUP($C34,二次物料明细!$A:$N,COLUMN(二次物料明细!L$1),),0) -> 0 | T34: =(R34*90.11+Q34*21.24+S34)/1000 -> 0 | U34: =(P34+T34)*J34 -> 1.39 | V34: =IFERROR(VLOOKUP($C34,二次物料明细!$A:$N,COLUMN(二次物料明细!M$1),),0) -> CNY | W34: =IFERROR(VLOOKUP($C34,二次物料明细!$A:$N,COLUMN(二次物料明细!N$1),),0) -> 系统价
A35: 6608523073 | B35: 组合式充电插座线束总成 | C35: 7-1452668-1 | D35: 端子 | E35: N | F35: A03011111 | J35: 6 | K35: PCS | L35: TE | N35: 客户指定 | O35: =IFERROR(VLOOKUP($C35,二次物料明细!$A:$N,COLUMN(二次物料明细!H$1),),0) -> 洪巧明 | P35: =IFERROR(VLOOKUP($C35,二次物料明细!$A:$N,COLUMN(二次物料明细!I$1),),0) -> 0.11915 | Q35: =IFERROR(VLOOKUP($C35,二次物料明细!$A:$N,COLUMN(二次物料明细!J$1),),0) -> 0 | R35: =IFERROR(VLOOKUP($C35,二次物料明细!$A:$N,COLUMN(二次物料明细!K$1),),0) -> 0 | S35: =IFERROR(VLOOKUP($C35,二次物料明细!$A:$N,COLUMN(二次物料明细!L$1),),0) -> 0 | T35: =(R35*90.11+Q35*21.24+S35)/1000 -> 0 | U35: =(P35+T35)*J35 -> 0.7149 | V35: =IFERROR(VLOOKUP($C35,二次物料明细!$A:$N,COLUMN(二次物料明细!M$1),),0) -> CNY | W35: =IFERROR(VLOOKUP($C35,二次物料明细!$A:$N,COLUMN(二次物料明细!N$1),),0) -> 系统价
A36: 6608523073 | B36: 组合式充电插座线束总成 | C36: PP1509507 | D36: 密封堵 | E36: N | F36: A03031595 | J36: 6 | K36: PCS | L36: 天海 | N36: 客户指定 | O36: =IFERROR(VLOOKUP($C36,二次物料明细!$A:$N,COLUMN(二次物料明细!H$1),),0) -> 江苏林 | P36: =IFERROR(VLOOKUP($C36,二次物料明细!$A:$N,COLUMN(二次物料明细!I$1),),0) -> 0.085 | Q36: =IFERROR(VLOOKUP($C36,二次物料明细!$A:$N,COLUMN(二次物料明细!J$1),),0) -> 0 | R36: =IFERROR(VLOOKUP($C36,二次物料明细!$A:$N,COLUMN(二次物料明细!K$1),),0) -> 0 | S36: =IFERROR(VLOOKUP($C36,二次物料明细!$A:$N,COLUMN(二次物料明细!L$1),),0) -> 0 | T36: =(R36*90.11+Q36*21.24+S36)/1000 -> 0 | U36: =(P36+T36)*J36 -> 0.51 | V36: =IFERROR(VLOOKUP($C36,二次物料明细!$A:$N,COLUMN(二次物料明细!M$1),),0) -> CNY | W36: =IFERROR(VLOOKUP($C36,二次物料明细!$A:$N,COLUMN(二次物料明细!N$1),),0) -> 系统价
A37: 6608523073 | B37: 组合式充电插座线束总成 | C37: 1-1456426-1 | D37: 护套塑壳 | E37: N | F37: A02104435 | J37: 1 | K37: PCS | L37: TE | M37: 1-1456426-1 0.5mm²低压线 接电子锁组件 | N37: 客户指定 | O37: =IFERROR(VLOOKUP($C37,二次物料明细!$A:$N,COLUMN(二次物料明细!H$1),),0) -> 洪巧明 | P37: =IFERROR(VLOOKUP($C37,二次物料明细!$A:$N,COLUMN(二次物料明细!I$1),),0) -> 3.8 | Q37: =IFERROR(VLOOKUP($C37,二次物料明细!$A:$N,COLUMN(二次物料明细!J$1),),0) -> 0 | R37: =IFERROR(VLOOKUP($C37,二次物料明细!$A:$N,COLUMN(二次物料明细!K$1),),0) -> 0 | S37: =IFERROR(VLOOKUP($C37,二次物料明细!$A:$N,COLUMN(二次物料明细!L$1),),0) -> 0 | T37: =(R37*90.11+Q37*21.24+S37)/1000 -> 0 | U37: =(P37+T37)*J37 -> 3.8 | V37: =IFERROR(VLOOKUP($C37,二次物料明细!$A:$N,COLUMN(二次物料明细!M$1),),0) -> CNY | W37: =IFERROR(VLOOKUP($C37,二次物料明细!$A:$N,COLUMN(二次物料明细!N$1),),0) -> 参考价
A38: 6608523073 | B38: 组合式充电插座线束总成 | C38: 1670146-1 | D38: 端子 | E38: N | F38: A03000092 | J38: 3 | K38: PCS | L38: TE | N38: 客户指定 | O38: =IFERROR(VLOOKUP($C38,二次物料明细!$A:$N,COLUMN(二次物料明细!H$1),),0) -> 洪巧明 | P38: =IFERROR(VLOOKUP($C38,二次物料明细!$A:$N,COLUMN(二次物料明细!I$1),),0) -> 0.14492 | Q38: =IFERROR(VLOOKUP($C38,二次物料明细!$A:$N,COLUMN(二次物料明细!J$1),),0) -> 0 | R38: =IFERROR(VLOOKUP($C38,二次物料明细!$A:$N,COLUMN(二次物料明细!K$1),),0) -> 0 | S38: =IFERROR(VLOOKUP($C38,二次物料明细!$A:$N,COLUMN(二次物料明细!L$1),),0) -> 0 | T38: =(R38*90.11+Q38*21.24+S38)/1000 -> 0 | U38: =(P38+T38)*J38 -> 0.43476 | V38: =IFERROR(VLOOKUP($C38,二次物料明细!$A:$N,COLUMN(二次物料明细!M$1),),0) -> CNY | W38: =IFERROR(VLOOKUP($C38,二次物料明细!$A:$N,COLUMN(二次物料明细!N$1),),0) -> 系统价
A39: 6608523073 | B39: 组合式充电插座线束总成 | C39: 967067-1 | D39: 密封堵 | E39: N | F39: A03011405 | J39: 3 | K39: PCS | L39: TE | N39: 客户指定 | O39: =IFERROR(VLOOKUP($C39,二次物料明细!$A:$N,COLUMN(二次物料明细!H$1),),0) -> 洪巧明 | P39: =IFERROR(VLOOKUP($C39,二次物料明细!$A:$N,COLUMN(二次物料明细!I$1),),0) -> 0.045 | Q39: =IFERROR(VLOOKUP($C39,二次物料明细!$A:$N,COLUMN(二次物料明细!J$1),),0) -> 0 | R39: =IFERROR(VLOOKUP($C39,二次物料明细!$A:$N,COLUMN(二次物料明细!K$1),),0) -> 0 | S39: =IFERROR(VLOOKUP($C39,二次物料明细!$A:$N,COLUMN(二次物料明细!L$1),),0) -> 0 | T39: =(R39*90.11+Q39*21.24+S39)/1000 -> 0 | U39: =(P39+T39)*J39 -> 0.135 | V39: =IFERROR(VLOOKUP($C39,二次物料明细!$A:$N,COLUMN(二次物料明细!M$1),),0) -> CNY | W39: =IFERROR(VLOOKUP($C39,二次物料明细!$A:$N,COLUMN(二次物料明细!N$1),),0) -> 系统价
A40: 6608523073 | B40: 组合式充电插座线束总成 | C40: 967056-1 | D40: 盲堵 | E40: N | F40: A02012110 | J40: 1 | K40: PCS | L40: TE | N40: 客户指定 | O40: =IFERROR(VLOOKUP($C40,二次物料明细!$A:$N,COLUMN(二次物料明细!H$1),),0) -> 洪巧明 | P40: =IFERROR(VLOOKUP($C40,二次物料明细!$A:$N,COLUMN(二次物料明细!I$1),),0) -> 0.1438 | Q40: =IFERROR(VLOOKUP($C40,二次物料明细!$A:$N,COLUMN(二次物料明细!J$1),),0) -> 0 | R40: =IFERROR(VLOOKUP($C40,二次物料明细!$A:$N,COLUMN(二次物料明细!K$1),),0) -> 0 | S40: =IFERROR(VLOOKUP($C40,二次物料明细!$A:$N,COLUMN(二次物料明细!L$1),),0) -> 0 | T40: =(R40*90.11+Q40*21.24+S40)/1000 -> 0 | U40: =(P40+T40)*J40 -> 0.1438 | V40: =IFERROR(VLOOKUP($C40,二次物料明细!$A:$N,COLUMN(二次物料明细!M$1),),0) -> CNY | W40: =IFERROR(VLOOKUP($C40,二次物料明细!$A:$N,COLUMN(二次物料明细!N$1),),0) -> 系统价
A41: 6608523073 | B41: 组合式充电插座线束总成 | C41: K03005541 | D41: DC端PE端子 | E41: N | F41: A03101932 | J41: 1 | K41: PCS | L41: 丰迪 | M41: K03005541 DC端PE端子 6mm²单芯非屏蔽交联铜导线 | N41: 客户指定 | O41: =IFERROR(VLOOKUP($C41,二次物料明细!$A:$N,COLUMN(二次物料明细!H$1),),0) -> 狄斌 | P41: =IFERROR(VLOOKUP($C41,二次物料明细!$A:$N,COLUMN(二次物料明细!I$1),),0) -> 2.2 | Q41: =IFERROR(VLOOKUP($C41,二次物料明细!$A:$N,COLUMN(二次物料明细!J$1),),0) -> 0 | R41: =IFERROR(VLOOKUP($C41,二次物料明细!$A:$N,COLUMN(二次物料明细!K$1),),0) -> 0 | S41: =IFERROR(VLOOKUP($C41,二次物料明细!$A:$N,COLUMN(二次物料明细!L$1),),0) -> 0 | T41: =(R41*90.11+Q41*21.24+S41)/1000 -> 0 | U41: =(P41+T41)*J41 -> 2.2 | V41: =IFERROR(VLOOKUP($C41,二次物料明细!$A:$N,COLUMN(二次物料明细!M$1),),0) -> CNY | W41: =IFERROR(VLOOKUP($C41,二次物料明细!$A:$N,COLUMN(二次物料明细!N$1),),0) -> 系统价
A42: 6608523073 | B42: 组合式充电插座线束总成 | C42: RSD2L0428 | D42: AC端PE端子 | E42: N | F42: A03103098 | J42: 1 | K42: PCS | L42: 荣盛达 | M42: RSD2L0428 AC端PE端子 5mm²单芯非屏蔽交联铜导线 | N42: 客户指定 | O42: =IFERROR(VLOOKUP($C42,二次物料明细!$A:$N,COLUMN(二次物料明细!H$1),),0) -> 狄斌 | P42: =IFERROR(VLOOKUP($C42,二次物料明细!$A:$N,COLUMN(二次物料明细!I$1),),0) -> 1.18 | Q42: =IFERROR(VLOOKUP($C42,二次物料明细!$A:$N,COLUMN(二次物料明细!J$1),),0) -> 0 | R42: =IFERROR(VLOOKUP($C42,二次物料明细!$A:$N,COLUMN(二次物料明细!K$1),),0) -> 0 | S42: =IFERROR(VLOOKUP($C42,二次物料明细!$A:$N,COLUMN(二次物料明细!L$1),),0) -> 0 | T42: =(R42*90.11+Q42*21.24+S42)/1000 -> 0 | U42: =(P42+T42)*J42 -> 1.18 | V42: =IFERROR(VLOOKUP($C42,二次物料明细!$A:$N,COLUMN(二次物料明细!M$1),),0) -> CNY | W42: =IFERROR(VLOOKUP($C42,二次物料明细!$A:$N,COLUMN(二次物料明细!N$1),),0) -> 系统价
A43: 6608523073 | B43: 组合式充电插座线束总成 | C43: 10106495 | D43: 接地热缩管 | E43: N | F43: A04030885 | J43: 2 | K43: PCS | L43: 深圳宏商/长春海达 | N43: ★ | O43: =IFERROR(VLOOKUP($C43,二次物料明细!$A:$N,COLUMN(二次物料明细!H$1),),0) -> 董培菊 | P43: =IFERROR(VLOOKUP($C43,二次物料明细!$A:$N,COLUMN(二次物料明细!I$1),),0) -> 0.28 | Q43: =IFERROR(VLOOKUP($C43,二次物料明细!$A:$N,COLUMN(二次物料明细!J$1),),0) -> 0 | R43: =IFERROR(VLOOKUP($C43,二次物料明细!$A:$N,COLUMN(二次物料明细!K$1),),0) -> 0 | S43: =IFERROR(VLOOKUP($C43,二次物料明细!$A:$N,COLUMN(二次物料明细!L$1),),0) -> 0 | T43: =(R43*90.11+Q43*21.24+S43)/1000 -> 0 | U43: =(P43+T43)*J43 -> 0.56 | V43: =IFERROR(VLOOKUP($C43,二次物料明细!$A:$N,COLUMN(二次物料明细!M$1),),0) -> CNY | W43: =IFERROR(VLOOKUP($C43,二次物料明细!$A:$N,COLUMN(二次物料明细!N$1),),0) -> 系统价
A44: 6608523073 | B44: 组合式充电插座线束总成 | C44: 6430060CLE1L30 | D44: 线线焊接热缩管 | F44: A04010425 | J44: 1 | K44: PCS | L44: 深圳宏商/长春海达 | N44: ★ | O44: =IFERROR(VLOOKUP($C44,二次物料明细!$A:$N,COLUMN(二次物料明细!H$1),),0) -> 董培菊 | P44: =IFERROR(VLOOKUP($C44,二次物料明细!$A:$N,COLUMN(二次物料明细!I$1),),0) -> 0.06148 | Q44: =IFERROR(VLOOKUP($C44,二次物料明细!$A:$N,COLUMN(二次物料明细!J$1),),0) -> 0 | R44: =IFERROR(VLOOKUP($C44,二次物料明细!$A:$N,COLUMN(二次物料明细!K$1),),0) -> 0 | S44: =IFERROR(VLOOKUP($C44,二次物料明细!$A:$N,COLUMN(二次物料明细!L$1),),0) -> 0 | T44: =(R44*90.11+Q44*21.24+S44)/1000 -> 0 | U44: =(P44+T44)*J44 -> 0.06148 | V44: =IFERROR(VLOOKUP($C44,二次物料明细!$A:$N,COLUMN(二次物料明细!M$1),),0) -> CNY | W44: =IFERROR(VLOOKUP($C44,二次物料明细!$A:$N,COLUMN(二次物料明细!N$1),),0) -> 系统价
A45: 6608523073 | B45: 组合式充电插座线束总成 | C45: FHLAL2G/50.0/橙 | D45: 50mm²单芯非屏蔽硅胶铝导线 | E45: N | F45: A01102138 | J45: 3.5 | K45: M | L45: 太平洋/鑫宏业/斯普乐 | N45: ★ | O45: =IFERROR(VLOOKUP($C45,二次物料明细!$A:$N,COLUMN(二次物料明细!H$1),),0) -> 郑锦清 | P45: =IFERROR(VLOOKUP($C45,二次物料明细!$A:$N,COLUMN(二次物料明细!I$1),),0) -> 0 | Q45: =IFERROR(VLOOKUP($C45,二次物料明细!$A:$N,COLUMN(二次物料明细!J$1),),0) -> 136.33 | R45: =IFERROR(VLOOKUP($C45,二次物料明细!$A:$N,COLUMN(二次物料明细!K$1),),0) -> 0 | S45: =IFERROR(VLOOKUP($C45,二次物料明细!$A:$N,COLUMN(二次物料明细!L$1),),0) -> 5311 | T45: =(R45*90.11+Q45*21.24+S45)/1000 -> 8.2066492 | U45: =(P45+T45)*J45 -> 28.723272 | V45: =IFERROR(VLOOKUP($C45,二次物料明细!$A:$N,COLUMN(二次物料明细!M$1),),0) -> 0 | W45: =IFERROR(VLOOKUP($C45,二次物料明细!$A:$N,COLUMN(二次物料明细!N$1),),0) -> 批量价
A46: 6608523073 | B46: 组合式充电插座线束总成 | C46: FHLAL91X/6.0/橙/AL8 | D46: 6mm²单芯非屏蔽交联铝导线 | E46: N | F46: A01103404 | J46: 3.54 | K46: M | L46: 鑫宏业/斯普乐 | N46: ★ | O46: =IFERROR(VLOOKUP($C46,二次物料明细!$A:$N,COLUMN(二次物料明细!H$1),),0) -> 郑锦清 | P46: =IFERROR(VLOOKUP($C46,二次物料明细!$A:$N,COLUMN(二次物料明细!I$1),),0) -> 0 | Q46: =IFERROR(VLOOKUP($C46,二次物料明细!$A:$N,COLUMN(二次物料明细!J$1),),0) -> 17.68 | R46: =IFERROR(VLOOKUP($C46,二次物料明细!$A:$N,COLUMN(二次物料明细!K$1),),0) -> 0 | S46: =IFERROR(VLOOKUP($C46,二次物料明细!$A:$N,COLUMN(二次物料明细!L$1),),0) -> 755.77 | T46: =(R46*90.11+Q46*21.24+S46)/1000 -> 1.1312932 | U46: =(P46+T46)*J46 -> 4.0047779 | V46: =IFERROR(VLOOKUP($C46,二次物料明细!$A:$N,COLUMN(二次物料明细!M$1),),0) -> 0 | W46: =IFERROR(VLOOKUP($C46,二次物料明细!$A:$N,COLUMN(二次物料明细!N$1),),0) -> 批量价
A47: 6608523073 | B47: 组合式充电插座线束总成 | C47: FHL91X/6.0/黄绿 | D47: 6mm²单芯铜导线 | E47: N | F47: A01101944 | J47: 0.39 | K47: M | L47: 鑫宏业/斯普乐 | N47: ★ | O47: =IFERROR(VLOOKUP($C47,二次物料明细!$A:$N,COLUMN(二次物料明细!H$1),),0) -> 郑锦清 | P47: =IFERROR(VLOOKUP($C47,二次物料明细!$A:$N,COLUMN(二次物料明细!I$1),),0) -> 0 | Q47: =IFERROR(VLOOKUP($C47,二次物料明细!$A:$N,COLUMN(二次物料明细!J$1),),0) -> 0 | R47: =IFERROR(VLOOKUP($C47,二次物料明细!$A:$N,COLUMN(二次物料明细!K$1),),0) -> 55.81 | S47: =IFERROR(VLOOKUP($C47,二次物料明细!$A:$N,COLUMN(二次物料明细!L$1),),0) -> 450 | T47: =(R47*90.11+Q47*21.24+S47)/1000 -> 5.4790391 | U47: =(P47+T47)*J47 -> 2.1368252 | V47: =IFERROR(VLOOKUP($C47,二次物料明细!$A:$N,COLUMN(二次物料明细!M$1),),0) -> 0 | W47: =IFERROR(VLOOKUP($C47,二次物料明细!$A:$N,COLUMN(二次物料明细!N$1),),0) -> 批量价
A48: 6608523073 | B48: 组合式充电插座线束总成 | C48: FHL91X/5.0/黄绿 | D48: 5mm²单芯铜导线 | E48: N | F48: A01103405 | J48: 0.42 | K48: M | L48: 鑫宏业/斯普乐 | N48: ★ | O48: =IFERROR(VLOOKUP($C48,二次物料明细!$A:$N,COLUMN(二次物料明细!H$1),),0) -> 郑锦清 | P48: =IFERROR(VLOOKUP($C48,二次物料明细!$A:$N,COLUMN(二次物料明细!I$1),),0) -> 0 | Q48: =IFERROR(VLOOKUP($C48,二次物料明细!$A:$N,COLUMN(二次物料明细!J$1),),0) -> 0 | R48: =IFERROR(VLOOKUP($C48,二次物料明细!$A:$N,COLUMN(二次物料明细!K$1),),0) -> 47.9 | S48: =IFERROR(VLOOKUP($C48,二次物料明细!$A:$N,COLUMN(二次物料明细!L$1),),0) -> 562.8 | T48: =(R48*90.11+Q48*21.24+S48)/1000 -> 4.879069 | U48: =(P48+T48)*J48 -> 2.049209 | V48: =IFERROR(VLOOKUP($C48,二次物料明细!$A:$N,COLUMN(二次物料明细!M$1),),0) -> 0 | W48: =IFERROR(VLOOKUP($C48,二次物料明细!$A:$N,COLUMN(二次物料明细!N$1),),0) -> 批量价
A49: 6608523073 | B49: 组合式充电插座线束总成 | C49: FLRY-B/0.5/绿 | D49: 低压导线 | E49: N | F49: A01011784 | J49: 0.4 | K49: M | L49: FORCE | N49: ★ | O49: =IFERROR(VLOOKUP($C49,二次物料明细!$A:$N,COLUMN(二次物料明细!H$1),),0) -> 郑锦清 | P49: =IFERROR(VLOOKUP($C49,二次物料明细!$A:$N,COLUMN(二次物料明细!I$1),),0) -> 0 | Q49: =IFERROR(VLOOKUP($C49,二次物料明细!$A:$N,COLUMN(二次物料明细!J$1),),0) -> 0 | R49: =IFERROR(VLOOKUP($C49,二次物料明细!$A:$N,COLUMN(二次物料明细!K$1),),0) -> 4.5 | S49: =IFERROR(VLOOKUP($C49,二次物料明细!$A:$N,COLUMN(二次物料明细!L$1),),0) -> 31.31 | T49: =(R49*90.11+Q49*21.24+S49)/1000 -> 0.436805 | U49: =(P49+T49)*J49 -> 0.174722 | V49: =IFERROR(VLOOKUP($C49,二次物料明细!$A:$N,COLUMN(二次物料明细!M$1),),0) -> 0 | W49: =IFERROR(VLOOKUP($C49,二次物料明细!$A:$N,COLUMN(二次物料明细!N$1),),0) -> 批量价
A50: 6608523073 | B50: 组合式充电插座线束总成 | C50: FLRY-B/0.5/棕 | D50: 低压导线 | E50: N | F50: A01011832 | J50: 0.4 | K50: M | L50: FORCE | N50: ★ | O50: =IFERROR(VLOOKUP($C50,二次物料明细!$A:$N,COLUMN(二次物料明细!H$1),),0) -> 郑锦清 | P50: =IFERROR(VLOOKUP($C50,二次物料明细!$A:$N,COLUMN(二次物料明细!I$1),),0) -> 0 | Q50: =IFERROR(VLOOKUP($C50,二次物料明细!$A:$N,COLUMN(二次物料明细!J$1),),0) -> 0 | R50: =IFERROR(VLOOKUP($C50,二次物料明细!$A:$N,COLUMN(二次物料明细!K$1),),0) -> 4.5 | S50: =IFERROR(VLOOKUP($C50,二次物料明细!$A:$N,COLUMN(二次物料明细!L$1),),0) -> 31.31 | T50: =(R50*90.11+Q50*21.24+S50)/1000 -> 0.436805 | U50: =(P50+T50)*J50 -> 0.174722 | V50: =IFERROR(VLOOKUP($C50,二次物料明细!$A:$N,COLUMN(二次物料明细!M$1),),0) -> 0 | W50: =IFERROR(VLOOKUP($C50,二次物料明细!$A:$N,COLUMN(二次物料明细!N$1),),0) -> 批量价
A51: 6608523073 | B51: 组合式充电插座线束总成 | C51: FLRY-B/0.5/橙兰 | D51: 低压导线 | E51: N | F51: A01000343 | J51: 0.4 | K51: M | L51: FORCE | N51: ★ | O51: =IFERROR(VLOOKUP($C51,二次物料明细!$A:$N,COLUMN(二次物料明细!H$1),),0) -> 郑锦清 | P51: =IFERROR(VLOOKUP($C51,二次物料明细!$A:$N,COLUMN(二次物料明细!I$1),),0) -> 0 | Q51: =IFERROR(VLOOKUP($C51,二次物料明细!$A:$N,COLUMN(二次物料明细!J$1),),0) -> 0 | R51: =IFERROR(VLOOKUP($C51,二次物料明细!$A:$N,COLUMN(二次物料明细!K$1),),0) -> 4.5 | S51: =IFERROR(VLOOKUP($C51,二次物料明细!$A:$N,COLUMN(二次物料明细!L$1),),0) -> 31.31 | T51: =(R51*90.11+Q51*21.24+S51)/1000 -> 0.436805 | U51: =(P51+T51)*J51 -> 0.174722 | V51: =IFERROR(VLOOKUP($C51,二次物料明细!$A:$N,COLUMN(二次物料明细!M$1),),0) -> 0 | W51: =IFERROR(VLOOKUP($C51,二次物料明细!$A:$N,COLUMN(二次物料明细!N$1),),0) -> 批量价
A52: 6608523073 | B52: 组合式充电插座线束总成 | C52: FLRY-B/0.5/白 | D52: 低压导线 | E52: N | F52: A01011749 | J52: 0.4 | K52: M | L52: FORCE | N52: ★ | O52: =IFERROR(VLOOKUP($C52,二次物料明细!$A:$N,COLUMN(二次物料明细!H$1),),0) -> 郑锦清 | P52: =IFERROR(VLOOKUP($C52,二次物料明细!$A:$N,COLUMN(二次物料明细!I$1),),0) -> 0 | Q52: =IFERROR(VLOOKUP($C52,二次物料明细!$A:$N,COLUMN(二次物料明细!J$1),),0) -> 0 | R52: =IFERROR(VLOOKUP($C52,二次物料明细!$A:$N,COLUMN(二次物料明细!K$1),),0) -> 4.5 | S52: =IFERROR(VLOOKUP($C52,二次物料明细!$A:$N,COLUMN(二次物料明细!L$1),),0) -> 31.31 | T52: =(R52*90.11+Q52*21.24+S52)/1000 -> 0.436805 | U52: =(P52+T52)*J52 -> 0.174722 | V52: =IFERROR(VLOOKUP($C52,二次物料明细!$A:$N,COLUMN(二次物料明细!M$1),),0) -> 0 | W52: =IFERROR(VLOOKUP($C52,二次物料明细!$A:$N,COLUMN(二次物料明细!N$1),),0) -> 批量价
A53: 6608523073 | B53: 组合式充电插座线束总成 | C53: FLRY-B/0.5/白黄 | D53: 低压导线 | E53: N | F53: A01011750 | J53: 0.4 | K53: M | L53: FORCE | N53: ★ | O53: =IFERROR(VLOOKUP($C53,二次物料明细!$A:$N,COLUMN(二次物料明细!H$1),),0) -> 郑锦清 | P53: =IFERROR(VLOOKUP($C53,二次物料明细!$A:$N,COLUMN(二次物料明细!I$1),),0) -> 0 | Q53: =IFERROR(VLOOKUP($C53,二次物料明细!$A:$N,COLUMN(二次物料明细!J$1),),0) -> 0 | R53: =IFERROR(VLOOKUP($C53,二次物料明细!$A:$N,COLUMN(二次物料明细!K$1),),0) -> 4.5 | S53: =IFERROR(VLOOKUP($C53,二次物料明细!$A:$N,COLUMN(二次物料明细!L$1),),0) -> 31.31 | T53: =(R53*90.11+Q53*21.24+S53)/1000 -> 0.436805 | U53: =(P53+T53)*J53 -> 0.174722 | V53: =IFERROR(VLOOKUP($C53,二次物料明细!$A:$N,COLUMN(二次物料明细!M$1),),0) -> 0 | W53: =IFERROR(VLOOKUP($C53,二次物料明细!$A:$N,COLUMN(二次物料明细!N$1),),0) -> 批量价
A54: 6608523073 | B54: 组合式充电插座线束总成 | C54: FLRY-B/0.5/白绿 | D54: 低压导线 | E54: N | F54: A01011751 | J54: 0.4 | K54: M | L54: FORCE | N54: ★ | O54: =IFERROR(VLOOKUP($C54,二次物料明细!$A:$N,COLUMN(二次物料明细!H$1),),0) -> 郑锦清 | P54: =IFERROR(VLOOKUP($C54,二次物料明细!$A:$N,COLUMN(二次物料明细!I$1),),0) -> 0 | Q54: =IFERROR(VLOOKUP($C54,二次物料明细!$A:$N,COLUMN(二次物料明细!J$1),),0) -> 0 | R54: =IFERROR(VLOOKUP($C54,二次物料明细!$A:$N,COLUMN(二次物料明细!K$1),),0) -> 4.5 | S54: =IFERROR(VLOOKUP($C54,二次物料明细!$A:$N,COLUMN(二次物料明细!L$1),),0) -> 31.31 | T54: =(R54*90.11+Q54*21.24+S54)/1000 -> 0.436805 | U54: =(P54+T54)*J54 -> 0.174722 | V54: =IFERROR(VLOOKUP($C54,二次物料明细!$A:$N,COLUMN(二次物料明细!M$1),),0) -> 0 | W54: =IFERROR(VLOOKUP($C54,二次物料明细!$A:$N,COLUMN(二次物料明细!N$1),),0) -> 批量价
A55: 6608523073 | B55: 组合式充电插座线束总成 | C55: FLRY-B/0.5/橙棕 | D55: 低压导线 | E55: N | F55: A01011767 | J55: 0.4 | K55: M | L55: FORCE | N55: ★ | O55: =IFERROR(VLOOKUP($C55,二次物料明细!$A:$N,COLUMN(二次物料明细!H$1),),0) -> 郑锦清 | P55: =IFERROR(VLOOKUP($C55,二次物料明细!$A:$N,COLUMN(二次物料明细!I$1),),0) -> 0 | Q55: =IFERROR(VLOOKUP($C55,二次物料明细!$A:$N,COLUMN(二次物料明细!J$1),),0) -> 0 | R55: =IFERROR(VLOOKUP($C55,二次物料明细!$A:$N,COLUMN(二次物料明细!K$1),),0) -> 4.5 | S55: =IFERROR(VLOOKUP($C55,二次物料明细!$A:$N,COLUMN(二次物料明细!L$1),),0) -> 31.31 | T55: =(R55*90.11+Q55*21.24+S55)/1000 -> 0.436805 | U55: =(P55+T55)*J55 -> 0.174722 | V55: =IFERROR(VLOOKUP($C55,二次物料明细!$A:$N,COLUMN(二次物料明细!M$1),),0) -> 0 | W55: =IFERROR(VLOOKUP($C55,二次物料明细!$A:$N,COLUMN(二次物料明细!N$1),),0) -> 批量价
A56: 6608523073 | B56: 组合式充电插座线束总成 | C56: FLRY-B/0.5/红 | D56: 低压导线 | E56: N | F56: A01011755 | J56: 0.4 | K56: M | L56: FORCE | N56: ★ | O56: =IFERROR(VLOOKUP($C56,二次物料明细!$A:$N,COLUMN(二次物料明细!H$1),),0) -> 郑锦清 | P56: =IFERROR(VLOOKUP($C56,二次物料明细!$A:$N,COLUMN(二次物料明细!I$1),),0) -> 0 | Q56: =IFERROR(VLOOKUP($C56,二次物料明细!$A:$N,COLUMN(二次物料明细!J$1),),0) -> 0 | R56: =IFERROR(VLOOKUP($C56,二次物料明细!$A:$N,COLUMN(二次物料明细!K$1),),0) -> 4.5 | S56: =IFERROR(VLOOKUP($C56,二次物料明细!$A:$N,COLUMN(二次物料明细!L$1),),0) -> 31.31 | T56: =(R56*90.11+Q56*21.24+S56)/1000 -> 0.436805 | U56: =(P56+T56)*J56 -> 0.174722 | V56: =IFERROR(VLOOKUP($C56,二次物料明细!$A:$N,COLUMN(二次物料明细!M$1),),0) -> 0 | W56: =IFERROR(VLOOKUP($C56,二次物料明细!$A:$N,COLUMN(二次物料明细!N$1),),0) -> 批量价
... A74: 6608523073 | B74: 组合式充电插座线束总成 | C74: SS21-ZJ-07 | D74: 金属支架 | E74: N | F74: A06101073 | J74: 1 | K74: PCS | L74: 贵龙 | N74: 沿用 | O74: =IFERROR(VLOOKUP($C74,二次物料明细!$A:$N,COLUMN(二次物料明细!H$1),),0) -> 王永东 | P74: =IFERROR(VLOOKUP($C74,二次物料明细!$A:$N,COLUMN(二次物料明细!I$1),),0) -> 3.5393 | Q74: =IFERROR(VLOOKUP($C74,二次物料明细!$A:$N,COLUMN(二次物料明细!J$1),),0) -> 0 | R74: =IFERROR(VLOOKUP($C74,二次物料明细!$A:$N,COLUMN(二次物料明细!K$1),),0) -> 0 | S74: =IFERROR(VLOOKUP($C74,二次物料明细!$A:$N,COLUMN(二次物料明细!L$1),),0) -> 0 | T74: =(R74*90.11+Q74*21.24+S74)/1000 -> 0 | U74: =(P74+T74)*J74 -> 3.5393 | V74: =IFERROR(VLOOKUP($C74,二次物料明细!$A:$N,COLUMN(二次物料明细!M$1),),0) -> CNY | W74: =IFERROR(VLOOKUP($C74,二次物料明细!$A:$N,COLUMN(二次物料明细!N$1),),0) -> 系统价
A75: 6608523073 | B75: 组合式充电插座线束总成 | C75: P162-ZJ-01 | D75: 金属支架 | E75: N | J75: 1 | K75: PCS | L75: 恒伟林/贵龙/华凯 | N75: ★ | O75: =IFERROR(VLOOKUP($C75,二次物料明细!$A:$N,COLUMN(二次物料明细!H$1),),0) -> 0 | P75: =IFERROR(VLOOKUP($C75,二次物料明细!$A:$N,COLUMN(二次物料明细!I$1),),0) -> 5 | Q75: =IFERROR(VLOOKUP($C75,二次物料明细!$A:$N,COLUMN(二次物料明细!J$1),),0) -> 0 | R75: =IFERROR(VLOOKUP($C75,二次物料明细!$A:$N,COLUMN(二次物料明细!K$1),),0) -> 0 | S75: =IFERROR(VLOOKUP($C75,二次物料明细!$A:$N,COLUMN(二次物料明细!L$1),),0) -> 0 | T75: =(R75*90.11+Q75*21.24+S75)/1000 -> 0 | U75: =(P75+T75)*J75 -> 5 | V75: =IFERROR(VLOOKUP($C75,二次物料明细!$A:$N,COLUMN(二次物料明细!M$1),),0) -> 0 | W75: =IFERROR(VLOOKUP($C75,二次物料明细!$A:$N,COLUMN(二次物料明细!N$1),),0) -> 销售估价
A76: 6608523073 | B76: 组合式充电插座线束总成 | C76: P162-KK-01 | D76: 管夹 | E76: N | J76: 1 | K76: PCS | L76: 博昊/天久/华凯 | N76: ★ | O76: =IFERROR(VLOOKUP($C76,二次物料明细!$A:$N,COLUMN(二次物料明细!H$1),),0) -> 邹娇 | P76: =IFERROR(VLOOKUP($C76,二次物料明细!$A:$N,COLUMN(二次物料明细!I$1),),0) -> 1.51 | Q76: =IFERROR(VLOOKUP($C76,二次物料明细!$A:$N,COLUMN(二次物料明细!J$1),),0) -> 0 | R76: =IFERROR(VLOOKUP($C76,二次物料明细!$A:$N,COLUMN(二次物料明细!K$1),),0) -> 0 | S76: =IFERROR(VLOOKUP($C76,二次物料明细!$A:$N,COLUMN(二次物料明细!L$1),),0) -> 0 | T76: =(R76*90.11+Q76*21.24+S76)/1000 -> 0 | U76: =(P76+T76)*J76 -> 1.51 | V76: =IFERROR(VLOOKUP($C76,二次物料明细!$A:$N,COLUMN(二次物料明细!M$1),),0) -> CNY | W76: =IFERROR(VLOOKUP($C76,二次物料明细!$A:$N,COLUMN(二次物料明细!N$1),),0) -> 含5W分摊价
A77: 6608523073 | B77: 组合式充电插座线束总成 | C77: X1-XJ-08 | D77: 橡胶件 | E77: N | F77: A04032754 | J77: 1 | K77: PCS | L77: 深州亚东 | N77: ★ | O77: =IFERROR(VLOOKUP($C77,二次物料明细!$A:$N,COLUMN(二次物料明细!H$1),),0) -> 狄斌 | P77: =IFERROR(VLOOKUP($C77,二次物料明细!$A:$N,COLUMN(二次物料明细!I$1),),0) -> 1.358 | Q77: =IFERROR(VLOOKUP($C77,二次物料明细!$A:$N,COLUMN(二次物料明细!J$1),),0) -> 0 | R77: =IFERROR(VLOOKUP($C77,二次物料明细!$A:$N,COLUMN(二次物料明细!K$1),),0) -> 0 | S77: =IFERROR(VLOOKUP($C77,二次物料明细!$A:$N,COLUMN(二次物料明细!L$1),),0) -> 0 | T77: =(R77*90.11+Q77*21.24+S77)/1000 -> 0 | U77: =(P77+T77)*J77 -> 1.358 | V77: =IFERROR(VLOOKUP($C77,二次物料明细!$A:$N,COLUMN(二次物料明细!M$1),),0) -> CNY | W77: =IFERROR(VLOOKUP($C77,二次物料明细!$A:$N,COLUMN(二次物料明细!N$1),),0) -> 系统价
A78: 6608523073 | B78: 组合式充电插座线束总成 | C78: MS11-XJ-05 | D78: 橡胶件 | E78: N | F78: A04032520 | J78: 2 | K78: PCS | L78: 金坛博盟 | N78: ★ | O78: =IFERROR(VLOOKUP($C78,二次物料明细!$A:$N,COLUMN(二次物料明细!H$1),),0) -> 狄斌 | P78: =IFERROR(VLOOKUP($C78,二次物料明细!$A:$N,COLUMN(二次物料明细!I$1),),0) -> 0.76352 | Q78: =IFERROR(VLOOKUP($C78,二次物料明细!$A:$N,COLUMN(二次物料明细!J$1),),0) -> 0 | R78: =IFERROR(VLOOKUP($C78,二次物料明细!$A:$N,COLUMN(二次物料明细!K$1),),0) -> 0 | S78: =IFERROR(VLOOKUP($C78,二次物料明细!$A:$N,COLUMN(二次物料明细!L$1),),0) -> 0 | T78: =(R78*90.11+Q78*21.24+S78)/1000 -> 0 | U78: =(P78+T78)*J78 -> 1.52704 | V78: =IFERROR(VLOOKUP($C78,二次物料明细!$A:$N,COLUMN(二次物料明细!M$1),),0) -> CNY | W78: =IFERROR(VLOOKUP($C78,二次物料明细!$A:$N,COLUMN(二次物料明细!N$1),),0) -> 系统价
A79: 6608523073 | B79: 组合式充电插座线束总成 | C79: PP9123601 | D79: φ6.5卡扣 | E79: N | F79: A06004936 | J79: 1 | K79: PCS | L79: 海尔曼太通/上海众安 | N79: ★ | O79: =IFERROR(VLOOKUP($C79,二次物料明细!$A:$N,COLUMN(二次物料明细!H$1),),0) -> 邹娇 | P79: =IFERROR(VLOOKUP($C79,二次物料明细!$A:$N,COLUMN(二次物料明细!I$1),),0) -> 0.095 | Q79: =IFERROR(VLOOKUP($C79,二次物料明细!$A:$N,COLUMN(二次物料明细!J$1),),0) -> 0 | R79: =IFERROR(VLOOKUP($C79,二次物料明细!$A:$N,COLUMN(二次物料明细!K$1),),0) -> 0 | S79: =IFERROR(VLOOKUP($C79,二次物料明细!$A:$N,COLUMN(二次物料明细!L$1),),0) -> 0 | T79: =(R79*90.11+Q79*21.24+S79)/1000 -> 0 | U79: =(P79+T79)*J79 -> 0.095 | V79: =IFERROR(VLOOKUP($C79,二次物料明细!$A:$N,COLUMN(二次物料明细!M$1),),0) -> CNY | W79: =IFERROR(VLOOKUP($C79,二次物料明细!$A:$N,COLUMN(二次物料明细!N$1),),0) -> 系统价
A80: 6608523073 | B80: 组合式充电插座线束总成 | C80: 157-00127 | D80: φ6.5卡扣 | E80: N | F80: A06010538 | J80: 1 | K80: PCS | L80: 海尔曼太通/上海众安 | N80: ★ | O80: =IFERROR(VLOOKUP($C80,二次物料明细!$A:$N,COLUMN(二次物料明细!H$1),),0) -> 邹娇 | P80: =IFERROR(VLOOKUP($C80,二次物料明细!$A:$N,COLUMN(二次物料明细!I$1),),0) -> 0.09 | Q80: =IFERROR(VLOOKUP($C80,二次物料明细!$A:$N,COLUMN(二次物料明细!J$1),),0) -> 0 | R80: =IFERROR(VLOOKUP($C80,二次物料明细!$A:$N,COLUMN(二次物料明细!K$1),),0) -> 0 | S80: =IFERROR(VLOOKUP($C80,二次物料明细!$A:$N,COLUMN(二次物料明细!L$1),),0) -> 0 | T80: =(R80*90.11+Q80*21.24+S80)/1000 -> 0 | U80: =(P80+T80)*J80 -> 0.09 | V80: =IFERROR(VLOOKUP($C80,二次物料明细!$A:$N,COLUMN(二次物料明细!M$1),),0) -> CNY | W80: =IFERROR(VLOOKUP($C80,二次物料明细!$A:$N,COLUMN(二次物料明细!N$1),),0) -> 系统价
A81: 6608523073 | B81: 组合式充电插座线束总成 | C81: 126-00207 | D81: 7*12箭头扎带 | E81: N | F81: A06000006 | J81: 4 | K81: PCS | L81: 海尔曼太通/上海众安 | N81: ★ | O81: =IFERROR(VLOOKUP($C81,二次物料明细!$A:$N,COLUMN(二次物料明细!H$1),),0) -> 邹娇 | P81: =IFERROR(VLOOKUP($C81,二次物料明细!$A:$N,COLUMN(二次物料明细!I$1),),0) -> 0.085 | Q81: =IFERROR(VLOOKUP($C81,二次物料明细!$A:$N,COLUMN(二次物料明细!J$1),),0) -> 0 | R81: =IFERROR(VLOOKUP($C81,二次物料明细!$A:$N,COLUMN(二次物料明细!K$1),),0) -> 0 | S81: =IFERROR(VLOOKUP($C81,二次物料明细!$A:$N,COLUMN(二次物料明细!L$1),),0) -> 0 | T81: =(R81*90.11+Q81*21.24+S81)/1000 -> 0 | U81: =(P81+T81)*J81 -> 0.34 | V81: =IFERROR(VLOOKUP($C81,二次物料明细!$A:$N,COLUMN(二次物料明细!M$1),),0) -> CNY | W81: =IFERROR(VLOOKUP($C81,二次物料明细!$A:$N,COLUMN(二次物料明细!N$1),),0) -> 系统价
A82: 6608523073 | B82: 组合式充电插座线束总成 | C82: 156-01650 | D82: 双绳M5扎带 | E82: N | F82: A06004019 | J82: 1 | K82: PCS | L82: 海尔曼太通/上海众安 | N82: ★ | O82: =IFERROR(VLOOKUP($C82,二次物料明细!$A:$N,COLUMN(二次物料明细!H$1),),0) -> 邹娇 | P82: =IFERROR(VLOOKUP($C82,二次物料明细!$A:$N,COLUMN(二次物料明细!I$1),),0) -> 0.35 | Q82: =IFERROR(VLOOKUP($C82,二次物料明细!$A:$N,COLUMN(二次物料明细!J$1),),0) -> 0 | R82: =IFERROR(VLOOKUP($C82,二次物料明细!$A:$N,COLUMN(二次物料明细!K$1),),0) -> 0 | S82: =IFERROR(VLOOKUP($C82,二次物料明细!$A:$N,COLUMN(二次物料明细!L$1),),0) -> 0 | T82: =(R82*90.11+Q82*21.24+S82)/1000 -> 0 | U82: =(P82+T82)*J82 -> 0.35 | V82: =IFERROR(VLOOKUP($C82,二次物料明细!$A:$N,COLUMN(二次物料明细!M$1),),0) -> CNY | W82: =IFERROR(VLOOKUP($C82,二次物料明细!$A:$N,COLUMN(二次物料明细!N$1),),0) -> 系统价
A83: 6608523073 | B83: 组合式充电插座线束总成 | C83: PP9127401 | D83: 隔线扎带绳 | E83: N | F83: A06101064 | J83: 1 | K83: PCS | L83: 海尔曼太通/上海众安 | N83: ★ | O83: =IFERROR(VLOOKUP($C83,二次物料明细!$A:$N,COLUMN(二次物料明细!H$1),),0) -> 邹娇 | P83: =IFERROR(VLOOKUP($C83,二次物料明细!$A:$N,COLUMN(二次物料明细!I$1),),0) -> 0.23275 | Q83: =IFERROR(VLOOKUP($C83,二次物料明细!$A:$N,COLUMN(二次物料明细!J$1),),0) -> 0 | R83: =IFERROR(VLOOKUP($C83,二次物料明细!$A:$N,COLUMN(二次物料明细!K$1),),0) -> 0 | S83: =IFERROR(VLOOKUP($C83,二次物料明细!$A:$N,COLUMN(二次物料明细!L$1),),0) -> 0 | T83: =(R83*90.11+Q83*21.24+S83)/1000 -> 0 | U83: =(P83+T83)*J83 -> 0.23275 | V83: =IFERROR(VLOOKUP($C83,二次物料明细!$A:$N,COLUMN(二次物料明细!M$1),),0) -> CNY | W83: =IFERROR(VLOOKUP($C83,二次物料明细!$A:$N,COLUMN(二次物料明细!N$1),),0) -> 系统价
A84: 6608523073 | B84: 组合式充电插座线束总成 | C84: PP9121001 | D84: 水管卡 | E84: N | F84: A06004889 | J84: 1 | K84: PCS | L84: 海尔曼太通/上海众安 | N84: ★ | O84: =IFERROR(VLOOKUP($C84,二次物料明细!$A:$N,COLUMN(二次物料明细!H$1),),0) -> 邹娇 | P84: =IFERROR(VLOOKUP($C84,二次物料明细!$A:$N,COLUMN(二次物料明细!I$1),),0) -> 0.21 | Q84: =IFERROR(VLOOKUP($C84,二次物料明细!$A:$N,COLUMN(二次物料明细!J$1),),0) -> 0 | R84: =IFERROR(VLOOKUP($C84,二次物料明细!$A:$N,COLUMN(二次物料明细!K$1),),0) -> 0 | S84: =IFERROR(VLOOKUP($C84,二次物料明细!$A:$N,COLUMN(二次物料明细!L$1),),0) -> 0 | T84: =(R84*90.11+Q84*21.24+S84)/1000 -> 0 | U84: =(P84+T84)*J84 -> 0.21 | V84: =IFERROR(VLOOKUP($C84,二次物料明细!$A:$N,COLUMN(二次物料明细!M$1),),0) -> CNY | W84: =IFERROR(VLOOKUP($C84,二次物料明细!$A:$N,COLUMN(二次物料明细!N$1),),0) -> 询价
A85: 6608523073 | B85: 组合式充电插座线束总成 | C85: 111-00563 | D85: 扎带绳 | E85: N | F85: A06010012 | J85: 17 | K85: PCS | L85: 海尔曼太通/上海众安 | N85: ★ | O85: =IFERROR(VLOOKUP($C85,二次物料明细!$A:$N,COLUMN(二次物料明细!H$1),),0) -> 邹娇 | P85: =IFERROR(VLOOKUP($C85,二次物料明细!$A:$N,COLUMN(二次物料明细!I$1),),0) -> 0.053 | Q85: =IFERROR(VLOOKUP($C85,二次物料明细!$A:$N,COLUMN(二次物料明细!J$1),),0) -> 0 | R85: =IFERROR(VLOOKUP($C85,二次物料明细!$A:$N,COLUMN(二次物料明细!K$1),),0) -> 0 | S85: =IFERROR(VLOOKUP($C85,二次物料明细!$A:$N,COLUMN(二次物料明细!L$1),),0) -> 0 | T85: =(R85*90.11+Q85*21.24+S85)/1000 -> 0 | U85: =(P85+T85)*J85 -> 0.901 | V85: =IFERROR(VLOOKUP($C85,二次物料明细!$A:$N,COLUMN(二次物料明细!M$1),),0) -> CNY | W85: =IFERROR(VLOOKUP($C85,二次物料明细!$A:$N,COLUMN(二次物料明细!N$1),),0) -> 系统价
A86: 6608523073 | B86: 组合式充电插座线束总成 | C86: 111-00580 | D86: 扎带绳 | E86: N | F86: A06000221 | J86: 1 | K86: PCS | L86: 海尔曼太通/上海众安 | N86: ★ | O86: =IFERROR(VLOOKUP($C86,二次物料明细!$A:$N,COLUMN(二次物料明细!H$1),),0) -> 邹娇 | P86: =IFERROR(VLOOKUP($C86,二次物料明细!$A:$N,COLUMN(二次物料明细!I$1),),0) -> 0.25 | Q86: =IFERROR(VLOOKUP($C86,二次物料明细!$A:$N,COLUMN(二次物料明细!J$1),),0) -> 0 | R86: =IFERROR(VLOOKUP($C86,二次物料明细!$A:$N,COLUMN(二次物料明细!K$1),),0) -> 0 | S86: =IFERROR(VLOOKUP($C86,二次物料明细!$A:$N,COLUMN(二次物料明细!L$1),),0) -> 0 | T86: =(R86*90.11+Q86*21.24+S86)/1000 -> 0 | U86: =(P86+T86)*J86 -> 0.25 | V86: =IFERROR(VLOOKUP($C86,二次物料明细!$A:$N,COLUMN(二次物料明细!M$1),),0) -> CNY | W86: =IFERROR(VLOOKUP($C86,二次物料明细!$A:$N,COLUMN(二次物料明细!N$1),),0) -> 系统价
A87: 6608523073 | B87: 组合式充电插座线束总成 | C87: M01-032 | D87: 产品标签 | E87: N | F87: 70002052 | J87: 1 | K87: PCS | L87: 金满地 | N87: ★ | O87: =IFERROR(VLOOKUP($C87,二次物料明细!$A:$N,COLUMN(二次物料明细!H$1),),0) -> 0 | P87: =IFERROR(VLOOKUP($C87,二次物料明细!$A:$N,COLUMN(二次物料明细!I$1),),0) -> 0.055 | Q87: =IFERROR(VLOOKUP($C87,二次物料明细!$A:$N,COLUMN(二次物料明细!J$1),),0) -> 0 | R87: =IFERROR(VLOOKUP($C87,二次物料明细!$A:$N,COLUMN(二次物料明细!K$1),),0) -> 0 | S87: =IFERROR(VLOOKUP($C87,二次物料明细!$A:$N,COLUMN(二次物料明细!L$1),),0) -> 0 | T87: =(R87*90.11+Q87*21.24+S87)/1000 -> 0 | U87: =(P87+T87)*J87 -> 0.055 | V87: =IFERROR(VLOOKUP($C87,二次物料明细!$A:$N,COLUMN(二次物料明细!M$1),),0) -> CNY | W87: =IFERROR(VLOOKUP($C87,二次物料明细!$A:$N,COLUMN(二次物料明细!N$1),),0) -> 系统价
A88: 6608523072 | B88: 充电线束总成 | C88: HVPC2P1600FE5-NH-M | D88: 护套塑壳 | E88: N | F88: A02104370 | J88: 1 | K88: PCS | L88: 安费诺 | M88: HVPC2P1600FE550-NH-P010 50mm²单芯屏蔽硅胶铝导线 接ODP端 | N88: 客户指定 | O88: =IFERROR(VLOOKUP($C88,二次物料明细!$A:$N,COLUMN(二次物料明细!H$1),),0) -> 胡继燕 | P88: =IFERROR(VLOOKUP($C88,二次物料明细!$A:$N,COLUMN(二次物料明细!I$1),),0) -> 24 | Q88: =IFERROR(VLOOKUP($C88,二次物料明细!$A:$N,COLUMN(二次物料明细!J$1),),0) -> 0 | R88: =IFERROR(VLOOKUP($C88,二次物料明细!$A:$N,COLUMN(二次物料明细!K$1),),0) -> 0 | S88: =IFERROR(VLOOKUP($C88,二次物料明细!$A:$N,COLUMN(二次物料明细!L$1),),0) -> 0 | T88: =(R88*90.11+Q88*21.24+S88)/1000 -> 0 | U88: =(P88+T88)*J88 -> 24 | V88: =IFERROR(VLOOKUP($C88,二次物料明细!$A:$N,COLUMN(二次物料明细!M$1),),0) -> 0 | W88: =IFERROR(VLOOKUP($C88,二次物料明细!$A:$N,COLUMN(二次物料明细!N$1),),0) -> 总成参考价
A89: 6608523072 | B89: 充电线束总成 | C89: HVPC2P1600FE-05P010 | D89: 焊接端子 | E89: N | F89: A03103097 | J89: 2 | K89: PCS | L89: 安费诺 | N89: 客户指定 | O89: =IFERROR(VLOOKUP($C89,二次物料明细!$A:$N,COLUMN(二次物料明细!H$1),),0) -> 胡继燕 | P89: =IFERROR(VLOOKUP($C89,二次物料明细!$A:$N,COLUMN(二次物料明细!I$1),),0) -> 0 | Q89: =IFERROR(VLOOKUP($C89,二次物料明细!$A:$N,COLUMN(二次物料明细!J$1),),0) -> 0 | R89: =IFERROR(VLOOKUP($C89,二次物料明细!$A:$N,COLUMN(二次物料明细!K$1),),0) -> 0 | S89: =IFERROR(VLOOKUP($C89,二次物料明细!$A:$N,COLUMN(二次物料明细!L$1),),0) -> 0 | T89: =(R89*90.11+Q89*21.24+S89)/1000 -> 0 | U89: =(P89+T89)*J89 -> 0 | V89: =IFERROR(VLOOKUP($C89,二次物料明细!$A:$N,COLUMN(二次物料明细!M$1),),0) -> 0 | W89: =IFERROR(VLOOKUP($C89,二次物料明细!$A:$N,COLUMN(二次物料明细!N$1),),0) -> 散件
A90: 6608523072 | B90: 充电线束总成 | C90: HVPC2P1600FV-15 | D90: 挡板 | E90: N | F90: A02103577 | J90: 2 | K90: PCS | L90: 安费诺 | N90: 客户指定 | O90: =IFERROR(VLOOKUP($C90,二次物料明细!$A:$N,COLUMN(二次物料明细!H$1),),0) -> 胡继燕 | P90: =IFERROR(VLOOKUP($C90,二次物料明细!$A:$N,COLUMN(二次物料明细!I$1),),0) -> 0 | Q90: =IFERROR(VLOOKUP($C90,二次物料明细!$A:$N,COLUMN(二次物料明细!J$1),),0) -> 0 | R90: =IFERROR(VLOOKUP($C90,二次物料明细!$A:$N,COLUMN(二次物料明细!K$1),),0) -> 0 | S90: =IFERROR(VLOOKUP($C90,二次物料明细!$A:$N,COLUMN(二次物料明细!L$1),),0) -> 0 | T90: =(R90*90.11+Q90*21.24+S90)/1000 -> 0 | U90: =(P90+T90)*J90 -> 0 | V90: =IFERROR(VLOOKUP($C90,二次物料明细!$A:$N,COLUMN(二次物料明细!M$1),),0) -> 0 | W90: =IFERROR(VLOOKUP($C90,二次物料明细!$A:$N,COLUMN(二次物料明细!N$1),),0) -> 散件
A91: 6608523072 | B91: 充电线束总成 | C91: HVPC2P1600FV-06-50 | D91: 外屏蔽环 | E91: N | F91: A03102581 | J91: 2 | K91: PCS | L91: 安费诺 | N91: 客户指定 | O91: =IFERROR(VLOOKUP($C91,二次物料明细!$A:$N,COLUMN(二次物料明细!H$1),),0) -> 胡继燕 | P91: =IFERROR(VLOOKUP($C91,二次物料明细!$A:$N,COLUMN(二次物料明细!I$1),),0) -> 0 | Q91: =IFERROR(VLOOKUP($C91,二次物料明细!$A:$N,COLUMN(二次物料明细!J$1),),0) -> 0 | R91: =IFERROR(VLOOKUP($C91,二次物料明细!$A:$N,COLUMN(二次物料明细!K$1),),0) -> 0 | S91: =IFERROR(VLOOKUP($C91,二次物料明细!$A:$N,COLUMN(二次物料明细!L$1),),0) -> 0 | T91: =(R91*90.11+Q91*21.24+S91)/1000 -> 0 | U91: =(P91+T91)*J91 -> 0 | V91: =IFERROR(VLOOKUP($C91,二次物料明细!$A:$N,COLUMN(二次物料明细!M$1),),0) -> 0 | W91: =IFERROR(VLOOKUP($C91,二次物料明细!$A:$N,COLUMN(二次物料明细!N$1),),0) -> 散件
A92: 6608523072 | B92: 充电线束总成 | C92: HVPC2P1800FS-11-50 | D92: 内屏蔽环 | E92: N | F92: A03102580 | J92: 2 | K92: PCS | L92: 安费诺 | N92: 客户指定 | O92: =IFERROR(VLOOKUP($C92,二次物料明细!$A:$N,COLUMN(二次物料明细!H$1),),0) -> 胡继燕 | P92: =IFERROR(VLOOKUP($C92,二次物料明细!$A:$N,COLUMN(二次物料明细!I$1),),0) -> 0 | Q92: =IFERROR(VLOOKUP($C92,二次物料明细!$A:$N,COLUMN(二次物料明细!J$1),),0) -> 0 | R92: =IFERROR(VLOOKUP($C92,二次物料明细!$A:$N,COLUMN(二次物料明细!K$1),),0) -> 0 | S92: =IFERROR(VLOOKUP($C92,二次物料明细!$A:$N,COLUMN(二次物料明细!L$1),),0) -> 0 | T92: =(R92*90.11+Q92*21.24+S92)/1000 -> 0 | U92: =(P92+T92)*J92 -> 0 | V92: =IFERROR(VLOOKUP($C92,二次物料明细!$A:$N,COLUMN(二次物料明细!M$1),),0) -> 0 | W92: =IFERROR(VLOOKUP($C92,二次物料明细!$A:$N,COLUMN(二次物料明细!N$1),),0) -> 散件
A93: 6608523072 | B93: 充电线束总成 | C93: HVPC2P1600FV-12-50 | D93: 密封圈 | E93: N | F93: A02104371 | J93: 2 | K93: PCS | L93: 安费诺 | N93: 客户指定 | O93: =IFERROR(VLOOKUP($C93,二次物料明细!$A:$N,COLUMN(二次物料明细!H$1),),0) -> 胡继燕 | P93: =IFERROR(VLOOKUP($C93,二次物料明细!$A:$N,COLUMN(二次物料明细!I$1),),0) -> 0 | Q93: =IFERROR(VLOOKUP($C93,二次物料明细!$A:$N,COLUMN(二次物料明细!J$1),),0) -> 0 | R93: =IFERROR(VLOOKUP($C93,二次物料明细!$A:$N,COLUMN(二次物料明细!K$1),),0) -> 0 | S93: =IFERROR(VLOOKUP($C93,二次物料明细!$A:$N,COLUMN(二次物料明细!L$1),),0) -> 0 | T93: =(R93*90.11+Q93*21.24+S93)/1000 -> 0 | U93: =(P93+T93)*J93 -> 0 | V93: =IFERROR(VLOOKUP($C93,二次物料明细!$A:$N,COLUMN(二次物料明细!M$1),),0) -> 0 | W93: =IFERROR(VLOOKUP($C93,二次物料明细!$A:$N,COLUMN(二次物料明细!N$1),),0) -> 散件
A94: 6608523072 | B94: 充电线束总成 | C94: HVPC2P1600FV-11-50 | D94: 线夹 | E94: N | F94: A02103573 | J94: 2 | K94: PCS | L94: 安费诺 | N94: 客户指定 | O94: =IFERROR(VLOOKUP($C94,二次物料明细!$A:$N,COLUMN(二次物料明细!H$1),),0) -> 胡继燕 | P94: =IFERROR(VLOOKUP($C94,二次物料明细!$A:$N,COLUMN(二次物料明细!I$1),),0) -> 0 | Q94: =IFERROR(VLOOKUP($C94,二次物料明细!$A:$N,COLUMN(二次物料明细!J$1),),0) -> 0 | R94: =IFERROR(VLOOKUP($C94,二次物料明细!$A:$N,COLUMN(二次物料明细!K$1),),0) -> 0 | S94: =IFERROR(VLOOKUP($C94,二次物料明细!$A:$N,COLUMN(二次物料明细!L$1),),0) -> 0 | T94: =(R94*90.11+Q94*21.24+S94)/1000 -> 0 | U94: =(P94+T94)*J94 -> 0 | V94: =IFERROR(VLOOKUP($C94,二次物料明细!$A:$N,COLUMN(二次物料明细!M$1),),0) -> 0 | W94: =IFERROR(VLOOKUP($C94,二次物料明细!$A:$N,COLUMN(二次物料明细!N$1),),0) -> 散件
A95: 6608523072 | B95: 充电线束总成 | C95: HVPC2P1600FV-10-50 | D95: 尾盖 | E95: N | F95: A02104369 | J95: 2 | K95: PCS | L95: 安费诺 | N95: 客户指定 | O95: =IFERROR(VLOOKUP($C95,二次物料明细!$A:$N,COLUMN(二次物料明细!H$1),),0) -> 胡继燕 | P95: =IFERROR(VLOOKUP($C95,二次物料明细!$A:$N,COLUMN(二次物料明细!I$1),),0) -> 0 | Q95: =IFERROR(VLOOKUP($C95,二次物料明细!$A:$N,COLUMN(二次物料明细!J$1),),0) -> 0 | R95: =IFERROR(VLOOKUP($C95,二次物料明细!$A:$N,COLUMN(二次物料明细!K$1),),0) -> 0 | S95: =IFERROR(VLOOKUP($C95,二次物料明细!$A:$N,COLUMN(二次物料明细!L$1),),0) -> 0 | T95: =(R95*90.11+Q95*21.24+S95)/1000 -> 0 | U95: =(P95+T95)*J95 -> 0 | V95: =IFERROR(VLOOKUP($C95,二次物料明细!$A:$N,COLUMN(二次物料明细!M$1),),0) -> 0 | W95: =IFERROR(VLOOKUP($C95,二次物料明细!$A:$N,COLUMN(二次物料明细!N$1),),0) -> 散件
A96: 6608523072 | B96: 充电线束总成 | C96: PP3219916 | D96: 二线线端护套总成 | E96: N | F96: A02104388 | J96: 1 | K96: PCS | L96: 天海 | M96: TP180F-2P1A50-V-JL 50mm²单芯屏蔽硅胶铝导线 接电池包端 | N96: 客户指定 | O96: =IFERROR(VLOOKUP($C96,二次物料明细!$A:$N,COLUMN(二次物料明细!H$1),),0) -> 江苏林 | P96: =IFERROR(VLOOKUP($C96,二次物料明细!$A:$N,COLUMN(二次物料明细!I$1),),0) -> 10.235 | Q96: =IFERROR(VLOOKUP($C96,二次物料明细!$A:$N,COLUMN(二次物料明细!J$1),),0) -> 0 | R96: =IFERROR(VLOOKUP($C96,二次物料明细!$A:$N,COLUMN(二次物料明细!K$1),),0) -> 0 | S96: =IFERROR(VLOOKUP($C96,二次物料明细!$A:$N,COLUMN(二次物料明细!L$1),),0) -> 0 | T96: =(R96*90.11+Q96*21.24+S96)/1000 -> 0 | U96: =(P96+T96)*J96 -> 10.235 | V96: =IFERROR(VLOOKUP($C96,二次物料明细!$A:$N,COLUMN(二次物料明细!M$1),),0) -> CNY | W96: =IFERROR(VLOOKUP($C96,二次物料明细!$A:$N,COLUMN(二次物料明细!N$1),),0) -> 询价
A97: 6608523072 | B97: 充电线束总成 | C97: PP3220006 | D97: 插针端子 | E97: N | F97: A03103102 | J97: 2 | K97: PCS | L97: 天海 | N97: 客户指定 | O97: =IFERROR(VLOOKUP($C97,二次物料明细!$A:$N,COLUMN(二次物料明细!H$1),),0) -> 江苏林 | P97: =IFERROR(VLOOKUP($C97,二次物料明细!$A:$N,COLUMN(二次物料明细!I$1),),0) -> 3.399 | Q97: =IFERROR(VLOOKUP($C97,二次物料明细!$A:$N,COLUMN(二次物料明细!J$1),),0) -> 0 | R97: =IFERROR(VLOOKUP($C97,二次物料明细!$A:$N,COLUMN(二次物料明细!K$1),),0) -> 0 | S97: =IFERROR(VLOOKUP($C97,二次物料明细!$A:$N,COLUMN(二次物料明细!L$1),),0) -> 0 | T97: =(R97*90.11+Q97*21.24+S97)/1000 -> 0 | U97: =(P97+T97)*J97 -> 6.798 | V97: =IFERROR(VLOOKUP($C97,二次物料明细!$A:$N,COLUMN(二次物料明细!M$1),),0) -> CNY | W97: =IFERROR(VLOOKUP($C97,二次物料明细!$A:$N,COLUMN(二次物料明细!N$1),),0) -> 询价
A98: 6608523072 | B98: 充电线束总成 | C98: PP3220009 | D98: 屏蔽层III | E98: N | F98: A03103108 | J98: 2 | K98: PCS | L98: 天海 | N98: 客户指定 | O98: =IFERROR(VLOOKUP($C98,二次物料明细!$A:$N,COLUMN(二次物料明细!H$1),),0) -> 江苏林 | P98: =IFERROR(VLOOKUP($C98,二次物料明细!$A:$N,COLUMN(二次物料明细!I$1),),0) -> 2.8152 | Q98: =IFERROR(VLOOKUP($C98,二次物料明细!$A:$N,COLUMN(二次物料明细!J$1),),0) -> 0 | R98: =IFERROR(VLOOKUP($C98,二次物料明细!$A:$N,COLUMN(二次物料明细!K$1),),0) -> 0 | S98: =IFERROR(VLOOKUP($C98,二次物料明细!$A:$N,COLUMN(二次物料明细!L$1),),0) -> 0 | T98: =(R98*90.11+Q98*21.24+S98)/1000 -> 0 | U98: =(P98+T98)*J98 -> 5.6304 | V98: =IFERROR(VLOOKUP($C98,二次物料明细!$A:$N,COLUMN(二次物料明细!M$1),),0) -> CNY | W98: =IFERROR(VLOOKUP($C98,二次物料明细!$A:$N,COLUMN(二次物料明细!N$1),),0) -> 询价
A99: 6608523072 | B99: 充电线束总成 | C99: PP3220013 | D99: 金属箍 | E99: N | F99: A03103109 | J99: 2 | K99: PCS | L99: 天海 | N99: 客户指定 | O99: =IFERROR(VLOOKUP($C99,二次物料明细!$A:$N,COLUMN(二次物料明细!H$1),),0) -> 江苏林 | P99: =IFERROR(VLOOKUP($C99,二次物料明细!$A:$N,COLUMN(二次物料明细!I$1),),0) -> 0.4623 | Q99: =IFERROR(VLOOKUP($C99,二次物料明细!$A:$N,COLUMN(二次物料明细!J$1),),0) -> 0 | R99: =IFERROR(VLOOKUP($C99,二次物料明细!$A:$N,COLUMN(二次物料明细!K$1),),0) -> 0 | S99: =IFERROR(VLOOKUP($C99,二次物料明细!$A:$N,COLUMN(二次物料明细!L$1),),0) -> 0 | T99: =(R99*90.11+Q99*21.24+S99)/1000 -> 0 | U99: =(P99+T99)*J99 -> 0.9246 | V99: =IFERROR(VLOOKUP($C99,二次物料明细!$A:$N,COLUMN(二次物料明细!M$1),),0) -> CNY | W99: =IFERROR(VLOOKUP($C99,二次物料明细!$A:$N,COLUMN(二次物料明细!N$1),),0) -> 询价
A100: 6608523072 | B100: 充电线束总成 | C100: PP3220017 | D100: 外金属箍 | E100: N | F100: A03103107 | J100: 2 | K100: PCS | L100: 天海 | N100: 客户指定 | O100: =IFERROR(VLOOKUP($C100,二次物料明细!$A:$N,COLUMN(二次物料明细!H$1),),0) -> 江苏林 | P100: =IFERROR(VLOOKUP($C100,二次物料明细!$A:$N,COLUMN(二次物料明细!I$1),),0) -> 0.6935 | Q100: =IFERROR(VLOOKUP($C100,二次物料明细!$A:$N,COLUMN(二次物料明细!J$1),),0) -> 0 | R100: =IFERROR(VLOOKUP($C100,二次物料明细!$A:$N,COLUMN(二次物料明细!K$1),),0) -> 0 | S100: =IFERROR(VLOOKUP($C100,二次物料明细!$A:$N,COLUMN(二次物料明细!L$1),),0) -> 0 | T100: =(R100*90.11+Q100*21.24+S100)/1000 -> 0 | U100: =(P100+T100)*J100 -> 1.387 | V100: =IFERROR(VLOOKUP($C100,二次物料明细!$A:$N,COLUMN(二次物料明细!M$1),),0) -> CNY | W100: =IFERROR(VLOOKUP($C100,二次物料明细!$A:$N,COLUMN(二次物料明细!N$1),),0) -> 询价
A101: 6608523072 | B101: 充电线束总成 | C101: PP3220021 | D101: 密封堵 | E101: N | F101: A02104394 | J101: 1 | K101: PCS | L101: 天海 | N101: 客户指定 | O101: =IFERROR(VLOOKUP($C101,二次物料明细!$A:$N,COLUMN(二次物料明细!H$1),),0) -> 江苏林 | P101: =IFERROR(VLOOKUP($C101,二次物料明细!$A:$N,COLUMN(二次物料明细!I$1),),0) -> 1.1385 | Q101: =IFERROR(VLOOKUP($C101,二次物料明细!$A:$N,COLUMN(二次物料明细!J$1),),0) -> 0 | R101: =IFERROR(VLOOKUP($C101,二次物料明细!$A:$N,COLUMN(二次物料明细!K$1),),0) -> 0 | S101: =IFERROR(VLOOKUP($C101,二次物料明细!$A:$N,COLUMN(二次物料明细!L$1),),0) -> 0 | T101: =(R101*90.11+Q101*21.24+S101)/1000 -> 0 | U101: =(P101+T101)*J101 -> 1.1385 | V101: =IFERROR(VLOOKUP($C101,二次物料明细!$A:$N,COLUMN(二次物料明细!M$1),),0) -> CNY | W101: =IFERROR(VLOOKUP($C101,二次物料明细!$A:$N,COLUMN(二次物料明细!N$1),),0) -> 询价
A102: 6608523072 | B102: 充电线束总成 | C102: PP3220029 | D102: 尾卡 | E102: N | F102: A02104396 | J102: 1 | K102: PCS | L102: 天海 | N102: 客户指定 | O102: =IFERROR(VLOOKUP($C102,二次物料明细!$A:$N,COLUMN(二次物料明细!H$1),),0) -> 江苏林 | P102: =IFERROR(VLOOKUP($C102,二次物料明细!$A:$N,COLUMN(二次物料明细!I$1),),0) -> 0.9315 | Q102: =IFERROR(VLOOKUP($C102,二次物料明细!$A:$N,COLUMN(二次物料明细!J$1),),0) -> 0 | R102: =IFERROR(VLOOKUP($C102,二次物料明细!$A:$N,COLUMN(二次物料明细!K$1),),0) -> 0 | S102: =IFERROR(VLOOKUP($C102,二次物料明细!$A:$N,COLUMN(二次物料明细!L$1),),0) -> 0 | T102: =(R102*90.11+Q102*21.24+S102)/1000 -> 0 | U102: =(P102+T102)*J102 -> 0.9315 | V102: =IFERROR(VLOOKUP($C102,二次物料明细!$A:$N,COLUMN(二次物料明细!M$1),),0) -> CNY | W102: =IFERROR(VLOOKUP($C102,二次物料明细!$A:$N,COLUMN(二次物料明细!N$1),),0) -> 询价
A103: 6608523072 | B103: 充电线束总成 | C103: PP3220025 | D103: 固线夹 | E103: N | F103: A02104395 | J103: 1 | K103: PCS | L103: 天海 | N103: 客户指定 | O103: =IFERROR(VLOOKUP($C103,二次物料明细!$A:$N,COLUMN(二次物料明细!H$1),),0) -> 江苏林 | P103: =IFERROR(VLOOKUP($C103,二次物料明细!$A:$N,COLUMN(二次物料明细!I$1),),0) -> 0.6394 | Q103: =IFERROR(VLOOKUP($C103,二次物料明细!$A:$N,COLUMN(二次物料明细!J$1),),0) -> 0 | R103: =IFERROR(VLOOKUP($C103,二次物料明细!$A:$N,COLUMN(二次物料明细!K$1),),0) -> 0 | S103: =IFERROR(VLOOKUP($C103,二次物料明细!$A:$N,COLUMN(二次物料明细!L$1),),0) -> 0 | T103: =(R103*90.11+Q103*21.24+S103)/1000 -> 0 | U103: =(P103+T103)*J103 -> 0.6394 | V103: =IFERROR(VLOOKUP($C103,二次物料明细!$A:$N,COLUMN(二次物料明细!M$1),),0) -> CNY | W103: =IFERROR(VLOOKUP($C103,二次物料明细!$A:$N,COLUMN(二次物料明细!N$1),),0) -> 询价
A104: 6608523072 | B104: 充电线束总成 | C104: PP3220005 | D104: 内芯护套总成 | E104: N | F104: A02104383 | J104: 1 | K104: PCS | L104: 天海 | N104: 客户指定 | O104: =IFERROR(VLOOKUP($C104,二次物料明细!$A:$N,COLUMN(二次物料明细!H$1),),0) -> 江苏林 | P104: =IFERROR(VLOOKUP($C104,二次物料明细!$A:$N,COLUMN(二次物料明细!I$1),),0) -> 5.5775 | Q104: =IFERROR(VLOOKUP($C104,二次物料明细!$A:$N,COLUMN(二次物料明细!J$1),),0) -> 0 | R104: =IFERROR(VLOOKUP($C104,二次物料明细!$A:$N,COLUMN(二次物料明细!K$1),),0) -> 0 | S104: =IFERROR(VLOOKUP($C104,二次物料明细!$A:$N,COLUMN(二次物料明细!L$1),),0) -> 0 | T104: =(R104*90.11+Q104*21.24+S104)/1000 -> 0 | U104: =(P104+T104)*J104 -> 5.5775 | V104: =IFERROR(VLOOKUP($C104,二次物料明细!$A:$N,COLUMN(二次物料明细!M$1),),0) -> CNY | W104: =IFERROR(VLOOKUP($C104,二次物料明细!$A:$N,COLUMN(二次物料明细!N$1),),0) -> 询价
A105: 6608523072 | B105: 充电线束总成 | C105: PP3220031 | D105: 垫块 | E105: N | F105: A02104384 | J105: 1 | K105: PCS | L105: 天海 | N105: 客户指定 | O105: =IFERROR(VLOOKUP($C105,二次物料明细!$A:$N,COLUMN(二次物料明细!H$1),),0) -> 江苏林 | P105: =IFERROR(VLOOKUP($C105,二次物料明细!$A:$N,COLUMN(二次物料明细!I$1),),0) -> 0.1771 | Q105: =IFERROR(VLOOKUP($C105,二次物料明细!$A:$N,COLUMN(二次物料明细!J$1),),0) -> 0 | R105: =IFERROR(VLOOKUP($C105,二次物料明细!$A:$N,COLUMN(二次物料明细!K$1),),0) -> 0 | S105: =IFERROR(VLOOKUP($C105,二次物料明细!$A:$N,COLUMN(二次物料明细!L$1),),0) -> 0 | T105: =(R105*90.11+Q105*21.24+S105)/1000 -> 0 | U105: =(P105+T105)*J105 -> 0.1771 | V105: =IFERROR(VLOOKUP($C105,二次物料明细!$A:$N,COLUMN(二次物料明细!M$1),),0) -> CNY | W105: =IFERROR(VLOOKUP($C105,二次物料明细!$A:$N,COLUMN(二次物料明细!N$1),),0) -> 询价
A106: 6608523072 | B106: 充电线束总成 | C106: FHLALR2GCCAATB2G/50.0/橙 | D106: 50mm²单芯导体铝屏蔽铜包铝导线 | E106: N | F106: / | J106: 1.429 | K106: M | L106: 太平洋/鑫宏业 | N106: ★ | O106: =IFERROR(VLOOKUP($C106,二次物料明细!$A:$N,COLUMN(二次物料明细!H$1),),0) -> 郑锦清 | P106: =IFERROR(VLOOKUP($C106,二次物料明细!$A:$N,COLUMN(二次物料明细!I$1),),0) -> 0 | Q106: =IFERROR(VLOOKUP($C106,二次物料明细!$A:$N,COLUMN(二次物料明细!J$1),),0) -> 151.6 | R106: =IFERROR(VLOOKUP($C106,二次物料明细!$A:$N,COLUMN(二次物料明细!K$1),),0) -> 15.8 | S106: =IFERROR(VLOOKUP($C106,二次物料明细!$A:$N,COLUMN(二次物料明细!L$1),),0) -> 11520 | T106: =(R106*90.11+Q106*21.24+S106)/1000 -> 16.163722 | U106: =(P106+T106)*J106 -> 23.097959 | V106: =IFERROR(VLOOKUP($C106,二次物料明细!$A:$N,COLUMN(二次物料明细!M$1),),0) -> 0 | W106: =IFERROR(VLOOKUP($C106,二次物料明细!$A:$N,COLUMN(二次物料明细!N$1),),0) -> 批量价
A107: 6608523072 | B107: 充电线束总成 | C107: LG3305D017B | D107: PP17波纹管 | E107: N | F107: A04102069 | J107: 0.79 | K107: M | L107: 骏鼎达/诗兰姆 | N107: ★ | O107: =IFERROR(VLOOKUP($C107,二次物料明细!$A:$N,COLUMN(二次物料明细!H$1),),0) -> 董培菊 | P107: =IFERROR(VLOOKUP($C107,二次物料明细!$A:$N,COLUMN(二次物料明细!I$1),),0) -> 1.14 | Q107: =IFERROR(VLOOKUP($C107,二次物料明细!$A:$N,COLUMN(二次物料明细!J$1),),0) -> 0 | R107: =IFERROR(VLOOKUP($C107,二次物料明细!$A:$N,COLUMN(二次物料明细!K$1),),0) -> 0 | S107: =IFERROR(VLOOKUP($C107,二次物料明细!$A:$N,COLUMN(二次物料明细!L$1),),0) -> 0 | T107: =(R107*90.11+Q107*21.24+S107)/1000 -> 0 | U107: =(P107+T107)*J107 -> 0.9006 | V107: =IFERROR(VLOOKUP($C107,二次物料明细!$A:$N,COLUMN(二次物料明细!M$1),),0) -> CNY | W107: =IFERROR(VLOOKUP($C107,二次物料明细!$A:$N,COLUMN(二次物料明细!N$1),),0) -> 系统价
A108: 6608523072 | B108: 充电线束总成 | C108: P111W0192510003 | D108: PVC胶带 | E108: N | F108: A04101791 | J108: 6 | K108: M | L108: 亚化 | N108: ★ | O108: =IFERROR(VLOOKUP($C108,二次物料明细!$A:$N,COLUMN(二次物料明细!H$1),),0) -> 董培菊 | P108: =IFERROR(VLOOKUP($C108,二次物料明细!$A:$N,COLUMN(二次物料明细!I$1),),0) -> 0.0686 | Q108: =IFERROR(VLOOKUP($C108,二次物料明细!$A:$N,COLUMN(二次物料明细!J$1),),0) -> 0 | R108: =IFERROR(VLOOKUP($C108,二次物料明细!$A:$N,COLUMN(二次物料明细!K$1),),0) -> 0 | S108: =IFERROR(VLOOKUP($C108,二次物料明细!$A:$N,COLUMN(二次物料明细!L$1),),0) -> 0 | T108: =(R108*90.11+Q108*21.24+S108)/1000 -> 0 | U108: =(P108+T108)*J108 -> 0.4116 | V108: =IFERROR(VLOOKUP($C108,二次物料明细!$A:$N,COLUMN(二次物料明细!M$1),),0) -> CNY | W108: =IFERROR(VLOOKUP($C108,二次物料明细!$A:$N,COLUMN(二次物料明细!N$1),),0) -> 系统价
... A111: 6608523072 | B111: 充电线束总成 | C111: 157-00253 | D111: 7*12杉树扎带 | E111: N | F111: A06003471 | J111: 4 | K111: PCS | L111: 海尔曼太通/上海众安 | N111: ★ | O111: =IFERROR(VLOOKUP($C111,二次物料明细!$A:$N,COLUMN(二次物料明细!H$1),),0) -> 邹娇 | P111: =IFERROR(VLOOKUP($C111,二次物料明细!$A:$N,COLUMN(二次物料明细!I$1),),0) -> 0.1 | Q111: =IFERROR(VLOOKUP($C111,二次物料明细!$A:$N,COLUMN(二次物料明细!J$1),),0) -> 0 | R111: =IFERROR(VLOOKUP($C111,二次物料明细!$A:$N,COLUMN(二次物料明细!K$1),),0) -> 0 | S111: =IFERROR(VLOOKUP($C111,二次物料明细!$A:$N,COLUMN(二次物料明细!L$1),),0) -> 0 | T111: =(R111*90.11+Q111*21.24+S111)/1000 -> 0 | U111: =(P111+T111)*J111 -> 0.4 | V111: =IFERROR(VLOOKUP($C111,二次物料明细!$A:$N,COLUMN(二次物料明细!M$1),),0) -> CNY | W111: =IFERROR(VLOOKUP($C111,二次物料明细!$A:$N,COLUMN(二次物料明细!N$1),),0) -> 系统价
A112: 6608523072 | B112: 充电线束总成 | C112: M01-032 | D112: 产品标签 | E112: N | F112: 70002052 | J112: 1 | K112: PCS | L112: 金满地 | N112: ★ | O112: =IFERROR(VLOOKUP($C112,二次物料明细!$A:$N,COLUMN(二次物料明细!H$1),),0) -> 0 | P112: =IFERROR(VLOOKUP($C112,二次物料明细!$A:$N,COLUMN(二次物料明细!I$1),),0) -> 0.055 | Q112: =IFERROR(VLOOKUP($C112,二次物料明细!$A:$N,COLUMN(二次物料明细!J$1),),0) -> 0 | R112: =IFERROR(VLOOKUP($C112,二次物料明细!$A:$N,COLUMN(二次物料明细!K$1),),0) -> 0 | S112: =IFERROR(VLOOKUP($C112,二次物料明细!$A:$N,COLUMN(二次物料明细!L$1),),0) -> 0 | T112: =(R112*90.11+Q112*21.24+S112)/1000 -> 0 | U112: =(P112+T112)*J112 -> 0.055 | V112: =IFERROR(VLOOKUP($C112,二次物料明细!$A:$N,COLUMN(二次物料明细!M$1),),0) -> CNY | W112: =IFERROR(VLOOKUP($C112,二次物料明细!$A:$N,COLUMN(二次物料明细!N$1),),0) -> 系统价

Sheet 二次物料明细
A1: ★ | B1: 若有其他方案推荐,经评估可行后可更新至K列
A2: 组件描述 | B2: 物料名称（英文/中文） | C2: 用量 | D2: 单位 | E2: 供应商名称 | F2: SAP号 | G2: 备注 | H2: 责任人 | I2: 单价 | J2: 铝重 | K2: 铜重 | L2: 非铜 | M2: 币别 | N2: 价格类型 | O2: VAVE供应商 | P2: VAVE型号 | Q2: VAVE单价
A3: PP3241918 | B3: 法兰组件 | C3: 1 | D3: PCS | E3: 天海 | G3: 客户指定 | H3: 江苏林 | I3: 170 | N3: 总成参考价-销售估价
A4: PP3241190 | B4: 防尘盖组件 | C4: 1 | D4: PCS | E4: 天海 | F4: A02102700 | G4: 客户指定 | H4: 江苏林 | M4: CNY | N4: 散件
A5: PP3241410 | B5: 70平DC端子 | C5: 2 | D5: PCS | E5: 天海 | F5: A03103099 | G5: 客户指定 | H5: 江苏林 | N5: 散件
A6: PP3241183 | B6: 50平DC尾盖 | C6: 2 | D6: PCS | E6: 天海 | F6: A02104381 | G6: 客户指定 | H6: 江苏林 | N6: 散件
A7: PP3241184 | B7: 50平DC线塞 | C7: 2 | D7: PCS | E7: 天海 | F7: A02104379 | G7: 客户指定 | H7: 江苏林 | N7: 散件
A8: PP3241319 | B8: PE端子 | C8: 1 | D8: PCS | E8: 天海 | F8: A03101934 | G8: 客户指定 | H8: 江苏林 | M8: CNY | N8: 散件
A9: PP3241115 | B9: PE胶圈 | C9: 1 | D9: PCS | E9: 天海 | F9: A02102631 | G9: 客户指定 | H9: 江苏林 | M9: CNY | N9: 散件
A10: PP3241195 | B10: 6平PE尾盖 | C10: 1 | D10: PCS | E10: 天海 | F10: A02102630 | G10: 客户指定 | H10: 江苏林 | M10: CNY | N10: 散件
A11: PP3241196 | B11: 6平PE线塞 | C11: 1 | D11: PCS | E11: 天海 | F11: A02102629 | G11: 客户指定 | H11: 江苏林 | M11: CNY | N11: 散件
A12: PP3241175 | B12: 5平AC线塞 | C12: 1 | D12: PCS | E12: 天海 | F12: A02104380 | G12: 客户指定 | H12: 江苏林 | N12: 散件
A13: PP3241174 | B13: 5平AC小尾盖 | C13: 1 | D13: PCS | E13: 天海 | F13: A02104378 | G13: 客户指定 | H13: 江苏林 | N13: 散件
A14: PP3241321 | B14: 6平功率插孔 | C14: 3 | D14: PCS | E14: 天海 | F14: A03101936 | G14: 客户指定 | H14: 江苏林 | M14: CNY | N14: 散件
A15: PP3241117 | B15: 6mm功率胶圈 | C15: 3 | D15: PCS | E15: 天海 | F15: A02102708 | G15: 客户指定 | H15: 江苏林 | M15: CNY | N15: 散件
A16: M21009005 | B16: P161电子锁 | C16: 1 | D16: PCS | E16: 天海 | G16: 客户指定 | H16: 江苏林 | N16: 散件
A17: M93000476 | B17: ST2.9*16 | C17: 2 | D17: PCS | E17: 天海 | F17: A07100113 | G17: 客户指定 | H17: 江苏林 | N17: 散件
A18: HVPC2P1600FE6-NH-MP010 | B18: 护套塑壳 | C18: 1 | D18: PCS | E18: 安费诺 | F18: A02104377 | G18: 客户指定 | H18: 胡继燕 | I18: 24 | N18: 总成参考价
A19: HVPC2P1600FE-05P010 | B19: 焊接端子 | C19: 4 | D19: PCS | E19: 安费诺 | F19: A03103097 | G19: 客户指定 | H19: 胡继燕 | N19: 散件
A20: HVPC2P1600FV-15P010 | B20: 挡板 | C20: 2 | D20: PCS | E20: 安费诺 | F20: A02104375 | G20: 客户指定 | H20: 胡继燕 | N20: 散件
A21: HVSPC2P1600FV-12-50P010 | B21: 插头线束密封圈 | C21: 2 | D21: PCS | E21: 安费诺 | F21: A02104376 | G21: 客户指定 | H21: 胡继燕 | N21: 散件
A22: HVSPC2P1600FV-11-50P010 | B22: 插头线卡 | C22: 2 | D22: PCS | E22: 安费诺 | F22: A02104374 | G22: 客户指定 | H22: 胡继燕 | N22: 散件
A23: HVSPC2P1600FV-10-50P010 | B23: 插头尾盖 | C23: 2 | D23: PCS | E23: 安费诺 | F23: A02104373 | G23: 客户指定 | H23: 胡继燕 | N23: 散件
A24: HVC2PG263UFSW106-NH-P010 | B24: 高压线束总成 | C24: 1 | D24: SET | E24: 安费诺 | G24: 客户指定 | H24: 胡继燕 | I24: 10 | N24: 总成参考价
A25: 5-2385463-1 | B25: 护套塑壳 | C25: 1 | D25: PCS | E25: TE | F25: A02101947 | G25: 客户指定 | H25: 洪巧明 | I25: 1.5 | M25: CNY | N25: 系统价
A26: 2377023-2 | B26: 压接端子 | C26: 17 | D26: PCS | E26: TE | F26: A03033091 | G26: 客户指定 | H26: 洪巧明 | I26: 0.06 | M26: CNY | N26: 系统价
A27: 2377665-4 | B27: 密封塞 | C27: 17 | D27: PCS | E27: TE | F27: A03033097 | G27: 客户指定 | H27: 洪巧明 | I27: 0.055 | M27: CNY | N27: 系统价
A28: 2377665-3 | B28: 小盲堵 | C28: 1 | D28: PCS | E28: TE | F28: A02034386 | G28: 客户指定 | H28: 洪巧明 | I28: 0.045 | M28: CNY | N28: 系统价
A29: 963143-1 | B29: 大盲堵（1、8、15、22） | C29: 4 | D29: PCS | E29: TE | F29: A02031363 | G29: 客户指定 | H29: 洪巧明 | I29: 0.182 | M29: CNY | N29: 系统价
A30: BH4311701 | B30: 卡花 | C30: 1 | D30: PCS | E30: 博昊 | F30: A06004040 | G30: ★ | H30: 邹娇 | I30: 0.1 | M30: CNY | N30: 系统价
A31: PP6509712 | B31: 护套 | C31: 1 | D31: PCS | E31: 天海 | F31: A02102696 | G31: 客户指定 | H31: 江苏林 | I31: 3.3 | M31: CNY | N31: 系统价
A32: PP0147015 | B32: 端子 | C32: 9 | D32: PCS | E32: 天海 | F32: A03101977 | G32: 客户指定 | H32: 江苏林 | I32: 0.15 | M32: CNY | N32: 系统价
A33: PP1509507 | B33: 密封堵 | C33: 15 | D33: PCS | E33: 天海 | F33: A03031595 | G33: 客户指定 | H33: 江苏林 | I33: 0.085 | M33: CNY | N33: 系统价
A34: PP1509508 | B34: 密封堵 | C34: 1 | D34: PCS | E34: 天海 | F34: A02031968 | G34: 客户指定 | H34: 江苏林 | I34: 0.1 | M34: CNY | N34: 系统价
A35: PP6507901 | B35: 护套 | C35: 1 | D35: PCS | E35: 天海 | F35: A02102644 | G35: 客户指定 | H35: 江苏林 | I35: 1.39 | M35: CNY | N35: 系统价
A36: 7-1452668-1 | B36: 端子 | C36: 6 | D36: PCS | E36: TE | F36: A03011111 | G36: 客户指定 | H36: 洪巧明 | I36: 0.11915 | M36: CNY | N36: 系统价
... A42: RSD2L0428 | B42: AC端PE端子 | C42: 1 | D42: PCS | E42: 荣盛达 | F42: A03103098 | G42: 客户指定 | H42: 狄斌 | I42: 1.18 | M42: CNY | N42: 系统价
A43: 10106495 | B43: 接地热缩管 | C43: 2 | D43: PCS | E43: 深圳宏商/长春海达 | F43: A04030885 | G43: ★ | H43: 董培菊 | I43: 0.28 | M43: CNY | N43: 系统价 | O43: 双宇 | P43: DPHS12-00-11.0/2.4-L40 | Q43: 0.09
A44: 6430060CLE1L30 | B44: 线线焊接热缩管 | C44: 1 | D44: PCS | E44: 深圳宏商/长春海达 | F44: A04010425 | G44: ★ | H44: 董培菊 | I44: 0.06148 | M44: CNY | N44: 系统价 | O44: 双宇 | P44: DPHS12-X0-5.75/1.27-L30 | Q44: 0.0324
A45: FHLAL2G/50.0/橙 | B45: 50mm²单芯非屏蔽硅胶铝导线 | C45: 3.5 | D45: M | E45: 太平洋/鑫宏业/斯普乐 | F45: A01102138 | G45: ★ | H45: 郑锦清 | J45: 136.33 | L45: 5311 | N45: 批量价
A46: FHLAL91X/6.0/橙/AL8 | B46: 6mm²单芯非屏蔽交联铝导线 | C46: 3.54 | D46: M | E46: 鑫宏业/斯普乐 | F46: A01103404 | G46: ★ | H46: 郑锦清 | J46: 17.68 | L46: 755.77 | N46: 批量价
A47: FHL91X/6.0/黄绿 | B47: 6mm²单芯铜导线 | C47: 0.39 | D47: M | E47: 鑫宏业/斯普乐 | F47: A01101944 | G47: ★ | H47: 郑锦清 | K47: 55.81 | L47: 450 | N47: 批量价
A48: FHL91X/5.0/黄绿 | B48: 5mm²单芯铜导线 | C48: 0.42 | D48: M | E48: 鑫宏业/斯普乐 | F48: A01103405 | G48: ★ | H48: 郑锦清 | K48: 47.9 | L48: 562.8 | N48: 批量价
A49: FLRY-B/0.5/绿 | B49: 低压导线 | C49: 0.4 | D49: M | E49: FORCE | F49: A01011784 | G49: ★ | H49: 郑锦清 | K49: 4.5 | L49: 31.31 | N49: 批量价
A50: FLRY-B/0.5/棕 | B50: 低压导线 | C50: 0.4 | D50: M | E50: FORCE | F50: A01011832 | G50: ★ | H50: 郑锦清 | K50: 4.5 | L50: 31.31 | N50: 批量价
A51: FLRY-B/0.5/橙兰 | B51: 低压导线 | C51: 0.4 | D51: M | E51: FORCE | F51: A01000343 | G51: ★ | H51: 郑锦清 | K51: 4.5 | L51: 31.31 | N51: 批量价
A52: FLRY-B/0.5/白 | B52: 低压导线 | C52: 0.4 | D52: M | E52: FORCE | F52: A01011749 | G52: ★ | H52: 郑锦清 | K52: 4.5 | L52: 31.31 | N52: 批量价
A53: FLRY-B/0.5/白黄 | B53: 低压导线 | C53: 0.4 | D53: M | E53: FORCE | F53: A01011750 | G53: ★ | H53: 郑锦清 | K53: 4.5 | L53: 31.31 | N53: 批量价
A54: FLRY-B/0.5/白绿 | B54: 低压导线 | C54: 0.4 | D54: M | E54: FORCE | F54: A01011751 | G54: ★ | H54: 郑锦清 | K54: 4.5 | L54: 31.31 | N54: 批量价
A55: FLRY-B/0.5/橙棕 | B55: 低压导线 | C55: 0.4 | D55: M | E55: FORCE | F55: A01011767 | G55: ★ | H55: 郑锦清 | K55: 4.5 | L55: 31.31 | N55: 批量价
A56: FLRY-B/0.5/红 | B56: 低压导线 | C56: 0.4 | D56: M | E56: FORCE | F56: A01011755 | G56: ★ | H56: 郑锦清 | K56: 4.5 | L56: 31.31 | N56: 批量价
A57: FLRY-B/0.5/兰白 | B57: 低压导线 | C57: 0.4 | D57: M | E57: FORCE | F57: A01011803 | G57: ★ | H57: 郑锦清 | K57: 4.5 | L57: 31.31 | N57: 批量价
A58: FLRY-B/0.5/黄白 | B58: 低压导线 | C58: 0.4 | D58: M | E58: FORCE | F58: A01011769 | G58: ★ | H58: 郑锦清 | K58: 4.5 | L58: 31.31 | N58: 批量价
... A65: FLRY-B/0.5/绿黑 | B65: 低压导线 | C65: 0.4 | D65: M | E65: FORCE | F65: A01011786 | G65: ★ | H65: 郑锦清 | K65: 4.5 | L65: 31.31 | N65: 批量价
A66: LG3305D014B | B66: PP14橙色波纹管 | C66: 2.62 | D66: M | E66: 骏鼎达/诗兰姆 | F66: A04100965 | G66: ★ | H66: 董培菊 | I66: 0.77 | M66: CNY | N66: 系统价
A67: MX-PC-OR-013 | B67: 13开口式-套管 | C67: 0.3 | D67: M | E67: 骏鼎达/明鑫 | F67: A04101346 | G67: ★ | H67: 董培菊 | I67: 1.027 | M67: CNY | N67: 系统价
A68: LG3305D012B | B68: PP12橙色波纹管 | C68: 1.49 | D68: M | E68: 骏鼎达/诗兰姆 | F68: A04101161 | G68: ★ | H68: 董培菊 | I68: 0.62 | M68: CNY | N68: 系统价
A69: P111W0192510003 | B69: PVC胶带 | C69: 18 | D69: M | E69: 亚化 | F69: A04101791 | G69: ★ | H69: 董培菊 | I69: 0.0686 | M69: CNY | N69: 系统价
A70: LY5016019-OR2 | B70: 橙色布基胶带 | C70: 8 | D70: M | E70: 联益 | F70: A04101159 | G70: ★ | H70: 董培菊 | I70: 0.209 | M70: CNY | N70: 系统价
A71: LY5016019 | B71: 黑色布基胶带 | C71: 2 | D71: M | E71: 联益 | F71: A04030943 | G71: ★ | H71: 董培菊 | I71: 0.14136 | M71: CNY | N71: 系统价
A72: SS21-HB-02 | B72: 护线槽 | C72: 1 | D72: PCS | E72: 华凯 | F72: A06101093 | G72: 沿用 | H72: 王永东 | I72: 8.294 | M72: CNY | N72: 系统价
A73: SS21-ZJ-06 | B73: 金属支架 | C73: 1 | D73: PCS | E73: 贵龙 | F73: A06101085 | G73: 沿用 | H73: 王永东 | I73: 2.183 | M73: CNY | N73: 系统价
A74: SS21-ZJ-07 | B74: 金属支架 | C74: 1 | D74: PCS | E74: 贵龙 | F74: A06101073 | G74: 沿用 | H74: 王永东 | I74: 3.5393 | M74: CNY | N74: 系统价
A75: P162-ZJ-01 | B75: 金属支架 | C75: 1 | D75: PCS | E75: 恒伟林/贵龙/华凯 | G75: ★ | I75: 5 | N75: 销售估价
A76: P162-KK-01 | B76: 管夹 | C76: 1 | D76: PCS | E76: 博昊/天久/华凯 | G76: 天久 | H76: 邹娇 | I76: 1.51 | M76: CNY | N76: 含5W分摊价
A77: X1-XJ-08 | B77: 橡胶件 | C77: 1 | D77: PCS | E77: 深州亚东 | F77: A04032754 | G77: ★ | H77: 狄斌 | I77: 1.358 | M77: CNY | N77: 系统价
A78: MS11-XJ-05 | B78: 橡胶件 | C78: 2 | D78: PCS | E78: 金坛博盟 | F78: A04032520 | G78: ★ | H78: 狄斌 | I78: 0.76352 | M78: CNY | N78: 系统价
A79: PP9123601 | B79: φ6.5卡扣 | C79: 1 | D79: PCS | E79: 海尔曼太通/上海众安 | F79: A06004936 | G79: ★ | H79: 邹娇 | I79: 0.095 | M79: CNY | N79: 系统价
A80: 157-00127 | B80: φ6.5卡扣 | C80: 1 | D80: PCS | E80: 海尔曼太通/上海众安 | F80: A06010538 | G80: ★ | H80: 邹娇 | I80: 0.09 | M80: CNY | N80: 系统价
A81: 126-00207 | B81: 7*12箭头扎带 | C81: 4 | D81: PCS | E81: 海尔曼太通/上海众安 | F81: A06000006 | G81: ★ | H81: 邹娇 | I81: 0.085 | M81: CNY | N81: 系统价
A82: 156-01650 | B82: 双绳M5扎带 | C82: 1 | D82: PCS | E82: 海尔曼太通/上海众安 | F82: A06004019 | G82: ★ | H82: 邹娇 | I82: 0.35 | M82: CNY | N82: 系统价
A83: PP9127401 | B83: 隔线扎带绳 | C83: 1 | D83: PCS | E83: 海尔曼太通/上海众安 | F83: A06101064 | G83: ★ | H83: 邹娇 | I83: 0.23275 | M83: CNY | N83: 系统价
A84: 111-00563 | B84: 扎带绳 | C84: 17 | D84: PCS | E84: 海尔曼太通/上海众安 | F84: A06010012 | G84: ★ | H84: 邹娇 | I84: 0.053 | M84: CNY | N84: 系统价
A85: 111-00580 | B85: 扎带绳 | C85: 1 | D85: PCS | E85: 海尔曼太通/上海众安 | F85: A06000221 | G85: ★ | H85: 邹娇 | I85: 0.25 | M85: CNY | N85: 系统价
A86: M01-032 | B86: 产品标签 | C86: 2 | D86: PCS | E86: 金满地 | F86: 70002052 | G86: ★ | I86: 0.055 | M86: CNY | N86: 系统价
A87: HVPC2P1600FE5-NH-M | B87: 护套塑壳 | C87: 1 | D87: PCS | E87: 安费诺 | F87: A02104370 | G87: 客户指定 | H87: 胡继燕 | I87: 24 | N87: 总成参考价
A88: HVPC2P1600FV-15 | B88: 挡板 | C88: 2 | D88: PCS | E88: 安费诺 | F88: A02103577 | G88: 客户指定 | H88: 胡继燕 | N88: 散件
A89: HVPC2P1600FV-06-50 | B89: 外屏蔽环 | C89: 2 | D89: PCS | E89: 安费诺 | F89: A03102581 | G89: 客户指定 | H89: 胡继燕 | N89: 散件
A90: HVPC2P1800FS-11-50 | B90: 内屏蔽环 | C90: 2 | D90: PCS | E90: 安费诺 | F90: A03102580 | G90: 客户指定 | H90: 胡继燕 | N90: 散件
A91: HVPC2P1600FV-12-50 | B91: 密封圈 | C91: 2 | D91: PCS | E91: 安费诺 | F91: A02104371 | G91: 客户指定 | H91: 胡继燕 | N91: 散件
A92: HVPC2P1600FV-11-50 | B92: 线夹 | C92: 2 | D92: PCS | E92: 安费诺 | F92: A02103573 | G92: 客户指定 | H92: 胡继燕 | N92: 散件
A93: HVPC2P1600FV-10-50 | B93: 尾盖 | C93: 2 | D93: PCS | E93: 安费诺 | F93: A02104369 | G93: 客户指定 | H93: 胡继燕 | N93: 散件
A94: PP3219916 | B94: 二线线端护套总成 | C94: 1 | D94: PCS | E94: 天海 | F94: A02104388 | G94: 客户指定 | H94: 江苏林 | I94: 10.235 | M94: CNY | N94: 询价
A95: PP3220006 | B95: 插针端子 | C95: 2 | D95: PCS | E95: 天海 | F95: A03103102 | G95: 客户指定 | H95: 江苏林 | I95: 3.399 | M95: CNY | N95: 询价
A96: PP3220009 | B96: 屏蔽层III | C96: 2 | D96: PCS | E96: 天海 | F96: A03103108 | G96: 客户指定 | H96: 江苏林 | I96: 2.8152 | M96: CNY | N96: 询价
A97: PP3220013 | B97: 金属箍 | C97: 2 | D97: PCS | E97: 天海 | F97: A03103109 | G97: 客户指定 | H97: 江苏林 | I97: 0.4623 | M97: CNY | N97: 询价
A98: PP3220017 | B98: 外金属箍 | C98: 2 | D98: PCS | E98: 天海 | F98: A03103107 | G98: 客户指定 | H98: 江苏林 | I98: 0.6935 | M98: CNY | N98: 询价
A99: PP3220021 | B99: 密封堵 | C99: 1 | D99: PCS | E99: 天海 | F99: A02104394 | G99: 客户指定 | H99: 江苏林 | I99: 1.1385 | M99: CNY | N99: 询价
A100: PP3220029 | B100: 尾卡 | C100: 1 | D100: PCS | E100: 天海 | F100: A02104396 | G100: 客户指定 | H100: 江苏林 | I100: 0.9315 | M100: CNY | N100: 询价
A101: PP3220025 | B101: 固线夹 | C101: 1 | D101: PCS | E101: 天海 | F101: A02104395 | G101: 客户指定 | H101: 江苏林 | I101: 0.6394 | M101: CNY | N101: 询价
A102: PP3220005 | B102: 内芯护套总成 | C102: 1 | D102: PCS | E102: 天海 | F102: A02104383 | G102: 客户指定 | H102: 江苏林 | I102: 5.5775 | M102: CNY | N102: 询价
A103: PP3220031 | B103: 垫块 | C103: 1 | D103: PCS | E103: 天海 | F103: A02104384 | G103: 客户指定 | H103: 江苏林 | I103: 0.1771 | M103: CNY | N103: 询价
A104: FHLALR2GCCAATB2G/50.0/橙 | B104: 50mm²单芯导体铝屏蔽铜包铝导线 | C104: 1.429 | D104: M | E104: 太平洋/鑫宏业 | G104: ★ | H104: 郑锦清 | J104: 151.6 | K104: 15.8 | L104: 11520 | N104: 批量价
A105: LG3305D017B | B105: PP17波纹管 | C105: 0.79 | D105: M | E105: 骏鼎达/诗兰姆 | F105: A04102069 | G105: ★ | H105: 董培菊 | I105: 1.14 | M105: CNY | N105: 系统价
A106: SS21-ZJ-10 | B106: 金属支架 | C106: 1 | D106: PCS | E106: 贵龙 | F106: A06101083 | G106: 沿用 | H106: 王永东 | I106: 7.92 | M106: CNY | N106: 系统价
A107: 157-00253 | B107: 7*12杉树扎带 | C107: 4 | D107: PCS | E107: 海尔曼太通/上海众安 | F107: A06003471 | G107: ★ | H107: 邹娇 | I107: 0.1 | M107: CNY | N107: 系统价
A108: PP9121001 | B108: 水管卡 | C108: 1 | D108: PCS | E108: 海尔曼太通/上海众安 | G108: ★ | H108: 邹娇 | I108: 0.21 | M108: CNY | N108: 询价

Sheet 总成散件清单
A1: NO. | B1: Function 功能 | C1: 单价 | D1: Part Number 零件号 | E1: Part Name 零件名称 | F1: Semi-Finished 是否半成品 | G1: Wire NO. 回路号 | H1: PIN | I1: OPTION | J1: SPEC 规格 | K1: Quantity 数量 | L1: Unit 单位 | M1: Remark | N1: 其他备注
A2: 1 | B2: TC-GADC-125A1000V32A250V-0 10Y1 充电座 | D2: PP3241918 | E2: 法兰组件 | F2: N | K2: 1 | L2: PCS | M2: 天海
A3: 2 | D3: PP3241190 | E3: 防尘盖组件 | F3: N | G3: A02102700 | K3: 1 | L3: PCS | M3: 天海
A4: 3 | D4: PP3241410 | E4: 70平DC端子 | F4: N | G4: A03103099 | K4: 2 | L4: PCS | M4: 天海
A5: 4 | D5: PP3241183 | E5: 50平DC尾盖 | F5: N | G5: A02104381 | K5: 2 | L5: PCS | M5: 天海
A6: 5 | D6: PP3241184 | E6: 50平DC线塞 | F6: N | G6: A02104379 | K6: 2 | L6: PCS | M6: 天海
A7: 6 | D7: PP3241319 | E7: PE端子 | F7: N | G7: A03101934 | K7: 1 | L7: PCS | M7: 天海
A8: 7 | D8: PP3241115 | E8: PE胶圈 | F8: N | G8: A02102631 | K8: 1 | L8: PCS | M8: 天海
A9: 8 | D9: PP3241195 | E9: 6平PE尾盖 | F9: N | G9: A02102630 | K9: 1 | L9: PCS | M9: 天海
A10: 9 | D10: PP3241196 | E10: 6平PE线塞 | F10: N | G10: A02102629 | K10: 1 | L10: PCS | M10: 天海
A11: 10 | D11: PP3241175 | E11: 5平AC线塞 | F11: N | G11: A02104380 | K11: 1 | L11: PCS | M11: 天海
A12: 11 | D12: PP3241174 | E12: 5平AC小尾盖 | F12: N | G12: A02104378 | K12: 1 | L12: PCS | M12: 天海
A13: 12 | D13: PP3241321 | E13: 6平功率插孔 | F13: N | G13: A03101936 | K13: 3 | L13: PCS | M13: 天海
A14: 13 | D14: PP3241117 | E14: 6mm功率胶圈 | F14: N | G14: A02102708 | K14: 3 | L14: PCS | M14: 天海
A15: 14 | D15: M21009005 | E15: P161电子锁 | F15: N | K15: 1 | L15: PCS | M15: 天海 | N15: 电子锁绳正式方案加长，可多报些
A16: 15 | D16: M93000476 | E16: ST2.9*16 | F16: N | G16: A07100113 | K16: 2 | L16: PCS | M16: 天海
A17: 16 | B17: HVSPC2P1600FE650-NH-P010 50mm²单芯非屏蔽硅胶铝导线 直流接ODP端 | C17: 24 | D17: HVPC2P1600FE6-NH-MP010 | E17: 护套塑壳 | F17: N | G17: A02104377 | K17: 1 | L17: PCS | M17: 安费诺
A18: 17 | D18: HVPC2P1600FE-05P010 | E18: 焊接端子 | F18: N | G18: A03103097 | K18: 2 | L18: PCS | M18: 安费诺
A19: 18 | D19: HVPC2P1600FV-15P010 | E19: 挡板 | F19: N | G19: A02104375 | K19: 2 | L19: PCS | M19: 安费诺
A20: 19 | D20: HVSPC2P1600FV-12-50P010 | E20: 插头线束密封圈 | F20: N | G20: A02104376 | K20: 2 | L20: PCS | M20: 安费诺
A21: 20 | D21: HVSPC2P1600FV-11-50P010 | E21: 插头线卡 | F21: N | G21: A02104374 | K21: 2 | L21: PCS | M21: 安费诺
A22: 21 | D22: HVSPC2P1600FV-10-50P010 | E22: 插头尾盖 | F22: N | G22: A02104373 | K22: 2 | L22: PCS | M22: 安费诺
A23: 22 | B23: HVC2PG263UFSW106-NH-P010 6mm²高压非屏蔽交联铝线 交流接ODP端 | C23: 10 | D23: HVC2PG263UFSW106-NH-P010 | E23: 高压线束总成 | F23: N | K23: 1 | L23: SET | M23: 安费诺
A24: 23 | B24: 5-2385463-1 0.5mm²低压线 接整车低压线束 | D24: 5-2385463-1 | E24: 护套塑壳 | F24: N | G24: A02101947 | K24: 1 | L24: PCS | M24: TE
A25: 24 | D25: 2377023-2 | E25: 压接端子 | F25: N | G25: A03033091 | K25: 17 | L25: PCS | M25: TE
A26: 25 | D26: 2377665-4 | E26: 密封塞 | F26: N | G26: A03033097 | K26: 17 | L26: PCS | M26: TE
A27: 26 | D27: 2377665-3 | E27: 小盲堵 | F27: N | G27: A02034386 | K27: 1 | L27: PCS | M27: TE
A28: 27 | D28: 963143-1 | E28: 大盲堵（1、8、15、22） | F28: N | G28: A02031363 | K28: 4 | L28: PCS | M28: TE
A29: 28 | B29: DMS120LL-10P-10TA 0.5mm²低压线 接直流充电座 | D29: PP6509712 | E29: 护套 | F29: N | G29: A02102696 | K29: 1 | L29: PCS | M29: 天海
A30: 29 | D30: PP0147015 | E30: 端子 | F30: N | G30: A03101977 | K30: 9 | L30: PCS | M30: 天海
A31: 30 | D31: PP1509507 | E31: 密封堵 | F31: N | G31: A03031595 | K31: 9 | L31: PCS | M31: 天海
A32: 31 | D32: PP1509508 | E32: 密封堵 | F32: N | G32: A02031968 | K32: 1 | L32: PCS | M32: 天海
A33: 32 | B33: DMS120LL-6P-6TA 0.5mm²低压线 接交流充电座 | D33: PP6507901 | E33: 护套 | F33: N | G33: A02102644 | K33: 1 | L33: PCS | M33: 天海
A34: 33 | D34: 7-1452668-1 | E34: 端子 | F34: N | G34: A03011111 | K34: 6 | L34: PCS | M34: TE
A35: 34 | D35: PP1509507 | E35: 密封堵 | F35: N | G35: A03031595 | K35: 6 | L35: PCS | M35: 天海
A36: 35 | B36: 1-1456426-1 0.5mm²低压线 接电子锁组件 | D36: 1-1456426-1 | E36: 护套塑壳 | F36: N | G36: A02104435 | K36: 1 | L36: PCS | M36: TE
A37: 36 | D37: 1670146-1 | E37: 端子 | F37: N | G37: A03000092 | K37: 3 | L37: PCS | M37: TE
A38: 37 | D38: 967067-1 | E38: 密封堵 | F38: N | G38: A03011405 | K38: 3 | L38: PCS | M38: TE
A39: 38 | D39: 967056-1 | E39: 盲堵 | F39: N | G39: A02012110 | K39: 1 | L39: PCS | M39: TE
A40: 39 | B40: HVPC2P1600FE550-NH-P010 50mm²单芯屏蔽硅胶铝导线 接ODP端 | C40: 24 | D40: HVPC2P1600FE5-NH-M | E40: 护套塑壳 | F40: N | G40: A02104370 | K40: 1 | L40: PCS | M40: 安费诺
A41: 40 | D41: HVPC2P1600FE-05P010 | E41: 焊接端子 | F41: N | G41: A03103097 | K41: 2 | L41: PCS | M41: 安费诺
A42: 41 | D42: HVPC2P1600FV-15 | E42: 挡板 | F42: N | G42: A02103577 | K42: 2 | L42: PCS | M42: 安费诺
A43: 42 | D43: HVPC2P1600FV-06-50 | E43: 外屏蔽环 | F43: N | G43: A03102581 | K43: 2 | L43: PCS | M43: 安费诺
A44: 43 | D44: HVPC2P1800FS-11-50 | E44: 内屏蔽环 | F44: N | G44: A03102580 | K44: 2 | L44: PCS | M44: 安费诺
A45: 44 | D45: HVPC2P1600FV-12-50 | E45: 密封圈 | F45: N | G45: A02104371 | K45: 2 | L45: PCS | M45: 安费诺
A46: 45 | D46: HVPC2P1600FV-11-50 | E46: 线夹 | F46: N | G46: A02103573 | K46: 2 | L46: PCS | M46: 安费诺
A47: 46 | D47: HVPC2P1600FV-10-50 | E47: 尾盖 | F47: N | G47: A02104369 | K47: 2 | L47: PCS | M47: 安费诺
A48: 47 | B48: TP180F-2P1A50-V-JL 50mm²单芯屏蔽硅胶铝导线 接电池包端 | D48: PP3219916 | E48: 二线线端护套总成 | F48: N | G48: A02104388 | K48: 1 | L48: PCS | M48: 天海
A49: 48 | D49: PP3220006 | E49: 插针端子 | F49: N | G49: A03103102 | K49: 2 | L49: PCS | M49: 天海
A50: 49 | D50: PP3220009 | E50: 屏蔽层III | F50: N | G50: A03103108 | K50: 2 | L50: PCS | M50: 天海
A51: 50 | D51: PP3220013 | E51: 金属箍 | F51: N | G51: A03103109 | K51: 2 | L51: PCS | M51: 天海
A52: 51 | D52: PP3220017 | E52: 外金属箍 | F52: N | G52: A03103107 | K52: 2 | L52: PCS | M52: 天海
A53: 52 | D53: PP3220021 | E53: 密封堵 | F53: N | G53: A02104394 | K53: 1 | L53: PCS | M53: 天海
A54: 53 | D54: PP3220029 | E54: 尾卡 | F54: N | G54: A02104396 | K54: 1 | L54: PCS | M54: 天海
A55: 54 | D55: PP3220025 | E55: 固线夹 | F55: N | G55: A02104395 | K55: 1 | L55: PCS | M55: 天海
A56: 55 | D56: PP3220005 | E56: 内芯护套总成 | F56: N | G56: A02104383 | K56: 1 | L56: PCS | M56: 天海
A57: 56 | D57: PP3220031 | E57: 垫块 | F57: N | G57: A02104384 | K57: 1 | L57: PCS | M57: 天海
